Workbook

Sheet %Accettato
A1: MESE | B1: POSITIVI | C1: NEGATIVI | D1: % Accettato | E1: % Non Accettato | G1: OPPORTUNITA' DI VENDITA | H1: POSITIVI | I1: NEGATIVI | J1: % Accettato | K1: % Non Accettato
A2: GENNAIO | B2: =COUNTIF(INDIRECT("'" & $A2 & "'!$A$11:$A$1000"), "INZIA IL TRATTAMENTO-VENDITA") -> 15 | C2: =COUNTIF(INDIRECT("'" & $A2 & "'!$A$11:$A$1000"), "NESSUNA VENDITA") -> 14 | D2: =IFERROR(B2 / (B2 + C2), 0) -> 0.51724138 | E2: =IFERROR(C2 / (B2 + C2), 0) -> 0.48275862 | G2: OPPORTUNITA' DI VENDITA | H2: {=COUNTIF(INDIRECT("'" & $G2 & "'!$B$198:$B$1000"), "ESEGUITO")} -> 5 | I2: {=COUNTIF(INDIRECT("'" & $G2 & "'!$B$198:$B$1000"), "NON ESEGUITO")} -> 0 | J2: =IFERROR(H2 / (H2 + I2), 0) -> 1 | K2: =IFERROR(I2 / (H2 + I2), 0) -> 0
A3: FEBBRAIO | B3: =COUNTIF(INDIRECT("'" & $A3 & "'!$A$11:$A$1000"), "INZIA IL TRATTAMENTO-VENDITA") -> 32 | C3: =COUNTIF(INDIRECT("'" & $A3 & "'!$A$11:$A$1000"), "NESSUNA VENDITA") -> 12 | D3: =IFERROR(B3 / (B3 + C3), 0) -> 0.72727273 | E3: =IFERROR(C3 / (B3 + C3), 0) -> 0.27272727
A4: MARZO | B4: =COUNTIF(INDIRECT("'" & $A4 & "'!$A$11:$A$1000"), "INZIA IL TRATTAMENTO-VENDITA") -> 29 | C4: =COUNTIF(INDIRECT("'" & $A4 & "'!$A$11:$A$1000"), "NESSUNA VENDITA") -> 21 | D4: =IFERROR(B4 / (B4 + C4), 0) -> 0.58 | E4: =IFERROR(C4 / (B4 + C4), 0) -> 0.42
A5: APRILE | B5: =COUNTIF(INDIRECT("'" & $A5 & "'!$A$11:$A$1000"), "INZIA IL TRATTAMENTO-VENDITA") -> 20 | C5: =COUNTIF(INDIRECT("'" & $A5 & "'!$A$11:$A$1000"), "NESSUNA VENDITA") -> 22 | D5: =IFERROR(B5 / (B5 + C5), 0) -> 0.47619048 | E5: =IFERROR(C5 / (B5 + C5), 0) -> 0.52380952
A6: MAGGIO | B6: =COUNTIF(INDIRECT("'" & $A6 & "'!$A$11:$A$1000"), "INZIA IL TRATTAMENTO-VENDITA") -> 31 | C6: =COUNTIF(INDIRECT("'" & $A6 & "'!$A$11:$A$1000"), "NESSUNA VENDITA") -> 7 | D6: =IFERROR(B6 / (B6 + C6), 0) -> 0.81578947 | E6: =IFERROR(C6 / (B6 + C6), 0) -> 0.18421053
A7: GIUGNO | B7: =COUNTIF(INDIRECT("'" & $A7 & "'!$A$11:$A$1000"), "INZIA IL TRATTAMENTO-VENDITA") -> 21 | C7: =COUNTIF(INDIRECT("'" & $A7 & "'!$A$11:$A$1000"), "NESSUNA VENDITA") -> 2 | D7: =IFERROR(B7 / (B7 + C7), 0) -> 0.91304348 | E7: =IFERROR(C7 / (B7 + C7), 0) -> 0.086956522
A8: LUGLIO | B8: =COUNTIF(INDIRECT("'" & $A8 & "'!$A$11:$A$1000"), "INZIA IL TRATTAMENTO-VENDITA") -> 0 | C8: =COUNTIF(INDIRECT("'" & $A8 & "'!$A$11:$A$1000"), "NESSUNA VENDITA") -> 0 | D8: =IFERROR(B8 / (B8 + C8), 0) -> 0 | E8: =IFERROR(C8 / (B8 + C8), 0) -> 0
A9: AGOSTO | B9: =COUNTIF(INDIRECT("'" & $A9 & "'!$A$11:$A$1000"), "INZIA IL TRATTAMENTO-VENDITA") -> 0 | C9: =COUNTIF(INDIRECT("'" & $A9 & "'!$A$11:$A$1000"), "NESSUNA VENDITA") -> 0 | D9: =IFERROR(B9 / (B9 + C9), 0) -> 0 | E9: =IFERROR(C9 / (B9 + C9), 0) -> 0
A10: SETTEMBRE | B10: =COUNTIF(INDIRECT("'" & $A10 & "'!$A$11:$A$1000"), "INZIA IL TRATTAMENTO-VENDITA") -> 0 | C10: =COUNTIF(INDIRECT("'" & $A10 & "'!$A$11:$A$1000"), "NESSUNA VENDITA") -> 0 | D10: =IFERROR(B10 / (B10 + C10), 0) -> 0 | E10: =IFERROR(C10 / (B10 + C10), 0) -> 0
A11: OTTOBRE | B11: =COUNTIF(INDIRECT("'" & $A11 & "'!$A$11:$A$1000"), "INZIA IL TRATTAMENTO-VENDITA") -> 0 | C11: =COUNTIF(INDIRECT("'" & $A11 & "'!$A$11:$A$1000"), "NESSUNA VENDITA") -> 0 | D11: =IFERROR(B11 / (B11 + C11), 0) -> 0 | E11: =IFERROR(C11 / (B11 + C11), 0) -> 0
A12: NOVEMBRE | B12: =COUNTIF(INDIRECT("'" & $A12 & "'!$A$11:$A$1000"), "INZIA IL TRATTAMENTO-VENDITA") -> 0 | C12: =COUNTIF(INDIRECT("'" & $A12 & "'!$A$11:$A$1000"), "NESSUNA VENDITA") -> 0 | D12: =IFERROR(B12 / (B12 + C12), 0) -> 0 | E12: =IFERROR(C12 / (B12 + C12), 0) -> 0
A13: DICEMBRE | B13: =COUNTIF(INDIRECT("'" & $A13 & "'!$A$11:$A$1000"), "INZIA IL TRATTAMENTO-VENDITA") -> 0 | C13: =COUNTIF(INDIRECT("'" & $A13 & "'!$A$11:$A$1000"), "NESSUNA VENDITA") -> 0 | D13: =IFERROR(B13 / (B13 + C13), 0) -> 0 | E13: =IFERROR(C13 / (B13 + C13), 0) -> 0

Sheet CONSUNTIVO
E1: nb. questo è un foglio dedicato al controllo, si prega di non modificare gli importi che sono generati automaticamente da formule incrociate.
B3: Consuntivo Annuale | C3: Opp.tà di Vendita | D3: Colonna 2 | E3: Preventivato Mese ACCETTATO | F3: 1 | G3: 2 | H3: 3 | I3: 4 | J3: 5 | K3: 6 | L3: 7 | M3: 8 | N3: 9 | O3: 10 | P3: 11 | Q3: 12 | R3: TOTALE | S3: ,,
F4: gennaio | G4: febbraio | H4: marzo | I4: aprile | J4: maggio | K4: giugno | L4: luglio | M4: agosto | N4: settembre | O4: ottobre | P4: novembre | Q4: dicembre
B5: DOMENICI | C5: =SUMIFS('OPPORTUNITA DI VENDITA'!$J$198:$J$1000, 'OPPORTUNITA DI VENDITA'!$H$198:$H$1000, B5, 'OPPORTUNITA DI VENDITA'!$B$198:$B$1000, "ESEGUITO") -> 0 | E5: DOMENICI | F5: =SUMIFS(INDIRECT("'" & $F$4 & "'!$I$11:$I$1000"), INDIRECT("'" & $F$4 & "'!$G$11:$G$1000"), $E5, INDIRECT("'" & $F$4 & "'!$A$11:$A$1000"), "INZIA IL TRATTAMENTO-VENDITA") -> 3285 | G5: =SUMIFS(INDIRECT("'" & $G$4 & "'!$I$11:$I$1000"), INDIRECT("'" & $G$4 & "'!$G$11:$G$1000"), $E5, INDIRECT("'" & $G$4 & "'!$A$11:$A$1000"), "INZIA IL TRATTAMENTO-VENDITA") -> 63368 | H5: =SUMIFS(INDIRECT("'" & $H$4 & "'!$I$11:$I$1000"), INDIRECT("'" & $H$4 & "'!$G$11:$G$1000"), $E5, INDIRECT("'" & $H$4 & "'!$A$11:$A$1000"), "INZIA IL TRATTAMENTO-VENDITA") -> 2155 | I5: =SUMIFS(INDIRECT("'" & I$4 & "'!$I$11:$I$1000"), INDIRECT("'" & I$4 & "'!$G$11:$G$1000"), $E5, INDIRECT("'" & I$4 & "'!$A$11:$A$1000"), "INZIA IL TRATTAMENTO-VENDITA") -> 520 | J5: =SUMIFS(INDIRECT("'" & J$4 & "'!$I$11:$I$1000"), INDIRECT("'" & J$4 & "'!$G$11:$G$1000"), $E5, INDIRECT("'" & J$4 & "'!$A$11:$A$1000"), "INZIA IL TRATTAMENTO-VENDITA") -> 5637 | K5: =SUMIFS(INDIRECT("'" & K$4 & "'!$I$11:$I$1000"), INDIRECT("'" & K$4 & "'!$G$11:$G$1000"), $E5, INDIRECT("'" & K$4 & "'!$A$11:$A$1000"), "INZIA IL TRATTAMENTO-VENDITA") -> 5970 | L5: =SUMIFS(INDIRECT("'" & L$4 & "'!$I$11:$I$1000"), INDIRECT("'" & L$4 & "'!$G$11:$G$1000"), $E5, INDIRECT("'" & L$4 & "'!$A$11:$A$1000"), "INZIA IL TRATTAMENTO-VENDITA") -> 0 | M5: =SUMIFS(INDIRECT("'" & M$4 & "'!$I$11:$I$1000"), INDIRECT("'" & M$4 & "'!$G$11:$G$1000"), $E5, INDIRECT("'" & M$4 & "'!$A$11:$A$1000"), "INZIA IL TRATTAMENTO-VENDITA") -> 0 | N5: =SUMIFS(INDIRECT("'" & N$4 & "'!$I$11:$I$1000"), INDIRECT("'" & N$4 & "'!$G$11:$G$1000"), $E5, INDIRECT("'" & N$4 & "'!$A$11:$A$1000"), "INZIA IL TRATTAMENTO-VENDITA") -> 0 | O5: =SUMIFS(INDIRECT("'" & O$4 & "'!$I$11:$I$1000"), INDIRECT("'" & O$4 & "'!$G$11:$G$1000"), $E5, INDIRECT("'" & O$4 & "'!$A$11:$A$1000"), "INZIA IL TRATTAMENTO-VENDITA") -> 0 | P5: =SUMIFS(INDIRECT("'" & P$4 & "'!$I$11:$I$1000"), INDIRECT("'" & P$4 & "'!$G$11:$G$1000"), $E5, INDIRECT("'" & P$4 & "'!$A$11:$A$1000"), "INZIA IL TRATTAMENTO-VENDITA") -> 0 | Q5: =SUMIFS(INDIRECT("'" & Q$4 & "'!$I$11:$I$1000"), INDIRECT("'" & Q$4 & "'!$G$11:$G$1000"), $E5, INDIRECT("'" & Q$4 & "'!$A$11:$A$1000"), "INZIA IL TRATTAMENTO-VENDITA") -> 0 | R5: =SUM(C5:Q5) -> 80935
B6: AMOROSO | C6: =SUMIFS('OPPORTUNITA DI VENDITA'!$J$198:$J$1000, 'OPPORTUNITA DI VENDITA'!$H$198:$H$1000, B6, 'OPPORTUNITA DI VENDITA'!$B$198:$B$1000, "ESEGUITO") -> 25388 | E6: AMOROSO | F6: =SUMIFS(INDIRECT("'" & $F$4 & "'!$I$11:$I$1000"), INDIRECT("'" & $F$4 & "'!$G$11:$G$1000"), $E6, INDIRECT("'" & $F$4 & "'!$A$11:$A$1000"), "INZIA IL TRATTAMENTO-VENDITA") -> 2280 | G6: =SUMIFS(INDIRECT("'" & $G$4 & "'!$I$11:$I$1000"), INDIRECT("'" & $G$4 & "'!$G$11:$G$1000"), $E6, INDIRECT("'" & $G$4 & "'!$A$11:$A$1000"), "INZIA IL TRATTAMENTO-VENDITA") -> 18963 | H6: =SUMIFS(INDIRECT("'" & $H$4 & "'!$I$11:$I$1000"), INDIRECT("'" & $H$4 & "'!$G$11:$G$1000"), $E6, INDIRECT("'" & $H$4 & "'!$A$11:$A$1000"), "INZIA IL TRATTAMENTO-VENDITA") -> 21116 | I6: =SUMIFS(INDIRECT("'" & $I$4 & "'!$I$11:$I$1000"), INDIRECT("'" & $I$4 & "'!$G$11:$G$1000"), $E6, INDIRECT("'" & $I$4 & "'!$A$11:$A$1000"), "INZIA IL TRATTAMENTO-VENDITA") -> 17210 | J6: =SUMIFS(INDIRECT("'" & J$4 & "'!$I$11:$I$1000"), INDIRECT("'" & J$4 & "'!$G$11:$G$1000"), $E6, INDIRECT("'" & J$4 & "'!$A$11:$A$1000"), "INZIA IL TRATTAMENTO-VENDITA") -> 14170 | K6: =SUMIFS(INDIRECT("'" & K$4 & "'!$I$11:$I$1000"), INDIRECT("'" & K$4 & "'!$G$11:$G$1000"), $E6, INDIRECT("'" & K$4 & "'!$A$11:$A$1000"), "INZIA IL TRATTAMENTO-VENDITA") -> 11970 | L6: =SUMIFS(INDIRECT("'" & L$4 & "'!$I$11:$I$1000"), INDIRECT("'" & L$4 & "'!$G$11:$G$1000"), $E6, INDIRECT("'" & L$4 & "'!$A$11:$A$1000"), "INZIA IL TRATTAMENTO-VENDITA") -> 0 | M6: =SUMIFS(INDIRECT("'" & M$4 & "'!$I$11:$I$1000"), INDIRECT("'" & M$4 & "'!$G$11:$G$1000"), $E6, INDIRECT("'" & M$4 & "'!$A$11:$A$1000"), "INZIA IL TRATTAMENTO-VENDITA") -> 0 | N6: =SUMIFS(INDIRECT("'" & N$4 & "'!$I$11:$I$1000"), INDIRECT("'" & N$4 & "'!$G$11:$G$1000"), $E6, INDIRECT("'" & N$4 & "'!$A$11:$A$1000"), "INZIA IL TRATTAMENTO-VENDITA") -> 0 | O6: =SUMIFS(INDIRECT("'" & O$4 & "'!$I$11:$I$1000"), INDIRECT("'" & O$4 & "'!$G$11:$G$1000"), $E6, INDIRECT("'" & O$4 & "'!$A$11:$A$1000"), "INZIA IL TRATTAMENTO-VENDITA") -> 0 | P6: =SUMIFS(INDIRECT("'" & P$4 & "'!$I$11:$I$1000"), INDIRECT("'" & P$4 & "'!$G$11:$G$1000"), $E6, INDIRECT("'" & P$4 & "'!$A$11:$A$1000"), "INZIA IL TRATTAMENTO-VENDITA") -> 0 | Q6: =SUMIFS(INDIRECT("'" & Q$4 & "'!$I$11:$I$1000"), INDIRECT("'" & Q$4 & "'!$G$11:$G$1000"), $E6, INDIRECT("'" & Q$4 & "'!$A$11:$A$1000"), "INZIA IL TRATTAMENTO-VENDITA") -> 0 | R6: =SUM(C6:Q6) -> 111097
B7: INNOCENTE | C7: =SUMIFS('OPPORTUNITA DI VENDITA'!$J$198:$J$1000, 'OPPORTUNITA DI VENDITA'!$H$198:$H$1000, B7, 'OPPORTUNITA DI VENDITA'!$B$198:$B$1000, "ESEGUITO") -> 0 | E7: INNOCENTE | F7: =SUMIFS(INDIRECT("'" & $F$4 & "'!$I$11:$I$1000"), INDIRECT("'" & $F$4 & "'!$G$11:$G$1000"), $E7, INDIRECT("'" & $F$4 & "'!$A$11:$A$1000"), "INZIA IL TRATTAMENTO-VENDITA") -> 0 | G7: =SUMIFS(INDIRECT("'" & $G$4 & "'!$I$11:$I$1000"), INDIRECT("'" & $G$4 & "'!$G$11:$G$1000"), $E7, INDIRECT("'" & $G$4 & "'!$A$11:$A$1000"), "INZIA IL TRATTAMENTO-VENDITA") -> 0 | H7: =SUMIFS(INDIRECT("'" & $H$4 & "'!$I$11:$I$1000"), INDIRECT("'" & $H$4 & "'!$G$11:$G$1000"), $E7, INDIRECT("'" & $H$4 & "'!$A$11:$A$1000"), "INZIA IL TRATTAMENTO-VENDITA") -> 770 | I7: =SUMIFS(INDIRECT("'" & $I$4 & "'!$I$11:$I$1000"), INDIRECT("'" & $I$4 & "'!$G$11:$G$1000"), $E7, INDIRECT("'" & $I$4 & "'!$A$11:$A$1000"), "INZIA IL TRATTAMENTO-VENDITA") -> 0 | J7: =SUMIFS(INDIRECT("'" & J$4 & "'!$I$11:$I$1000"), INDIRECT("'" & J$4 & "'!$G$11:$G$1000"), $E7, INDIRECT("'" & J$4 & "'!$A$11:$A$1000"), "INZIA IL TRATTAMENTO-VENDITA") -> 0 | K7: =SUMIFS(INDIRECT("'" & K$4 & "'!$I$11:$I$1000"), INDIRECT("'" & K$4 & "'!$G$11:$G$1000"), $E7, INDIRECT("'" & K$4 & "'!$A$11:$A$1000"), "INZIA IL TRATTAMENTO-VENDITA") -> 0 | L7: =SUMIFS(INDIRECT("'" & L$4 & "'!$I$11:$I$1000"), INDIRECT("'" & L$4 & "'!$G$11:$G$1000"), $E7, INDIRECT("'" & L$4 & "'!$A$11:$A$1000"), "INZIA IL TRATTAMENTO-VENDITA") -> 0 | M7: =SUMIFS(INDIRECT("'" & M$4 & "'!$I$11:$I$1000"), INDIRECT("'" & M$4 & "'!$G$11:$G$1000"), $E7, INDIRECT("'" & M$4 & "'!$A$11:$A$1000"), "INZIA IL TRATTAMENTO-VENDITA") -> 0 | N7: =SUMIFS(INDIRECT("'" & N$4 & "'!$I$11:$I$1000"), INDIRECT("'" & N$4 & "'!$G$11:$G$1000"), $E7, INDIRECT("'" & N$4 & "'!$A$11:$A$1000"), "INZIA IL TRATTAMENTO-VENDITA") -> 0 | O7: =SUMIFS(INDIRECT("'" & O$4 & "'!$I$11:$I$1000"), INDIRECT("'" & O$4 & "'!$G$11:$G$1000"), $E7, INDIRECT("'" & O$4 & "'!$A$11:$A$1000"), "INZIA IL TRATTAMENTO-VENDITA") -> 0 | P7: =SUMIFS(INDIRECT("'" & P$4 & "'!$I$11:$I$1000"), INDIRECT("'" & P$4 & "'!$G$11:$G$1000"), $E7, INDIRECT("'" & P$4 & "'!$A$11:$A$1000"), "INZIA IL TRATTAMENTO-VENDITA") -> 0 | Q7: =SUMIFS(INDIRECT("'" & Q$4 & "'!$I$11:$I$1000"), INDIRECT("'" & Q$4 & "'!$G$11:$G$1000"), $E7, INDIRECT("'" & Q$4 & "'!$A$11:$A$1000"), "INZIA IL TRATTAMENTO-VENDITA") -> 0 | R7: =SUM(C7:Q7) -> 770
B8: BERARDI | C8: =SUMIFS('OPPORTUNITA DI VENDITA'!$J$198:$J$1000, 'OPPORTUNITA DI VENDITA'!$H$198:$H$1000, B8, 'OPPORTUNITA DI VENDITA'!$B$198:$B$1000, "ESEGUITO") -> 0 | E8: BERARDI | F8: =SUMIFS(INDIRECT("'" & $F$4 & "'!$I$11:$I$1000"), INDIRECT("'" & $F$4 & "'!$G$11:$G$1000"), $E8, INDIRECT("'" & $F$4 & "'!$A$11:$A$1000"), "INZIA IL TRATTAMENTO-VENDITA") -> 0 | G8: =SUMIFS(INDIRECT("'" & $G$4 & "'!$I$11:$I$1000"), INDIRECT("'" & $G$4 & "'!$G$11:$G$1000"), $E8, INDIRECT("'" & $G$4 & "'!$A$11:$A$1000"), "INZIA IL TRATTAMENTO-VENDITA") -> 0 | H8: =SUMIFS(INDIRECT("'" & $H$4 & "'!$I$11:$I$1000"), INDIRECT("'" & $H$4 & "'!$G$11:$G$1000"), $E8, INDIRECT("'" & $H$4 & "'!$A$11:$A$1000"), "INZIA IL TRATTAMENTO-VENDITA") -> 0 | I8: =SUMIFS(INDIRECT("'" & $I$4 & "'!$I$11:$I$1000"), INDIRECT("'" & $I$4 & "'!$G$11:$G$1000"), $E8, INDIRECT("'" & $I$4 & "'!$A$11:$A$1000"), "INZIA IL TRATTAMENTO-VENDITA") -> 0 | J8: =SUMIFS(INDIRECT("'" & J$4 & "'!$I$11:$I$1000"), INDIRECT("'" & J$4 & "'!$G$11:$G$1000"), $E8, INDIRECT("'" & J$4 & "'!$A$11:$A$1000"), "INZIA IL TRATTAMENTO-VENDITA") -> 0 | K8: =SUMIFS(INDIRECT("'" & K$4 & "'!$I$11:$I$1000"), INDIRECT("'" & K$4 & "'!$G$11:$G$1000"), $E8, INDIRECT("'" & K$4 & "'!$A$11:$A$1000"), "INZIA IL TRATTAMENTO-VENDITA") -> 0 | L8: =SUMIFS(INDIRECT("'" & L$4 & "'!$I$11:$I$1000"), INDIRECT("'" & L$4 & "'!$G$11:$G$1000"), $E8, INDIRECT("'" & L$4 & "'!$A$11:$A$1000"), "INZIA IL TRATTAMENTO-VENDITA") -> 0 | M8: =SUMIFS(INDIRECT("'" & M$4 & "'!$I$11:$I$1000"), INDIRECT("'" & M$4 & "'!$G$11:$G$1000"), $E8, INDIRECT("'" & M$4 & "'!$A$11:$A$1000"), "INZIA IL TRATTAMENTO-VENDITA") -> 0 | N8: =SUMIFS(INDIRECT("'" & N$4 & "'!$I$11:$I$1000"), INDIRECT("'" & N$4 & "'!$G$11:$G$1000"), $E8, INDIRECT("'" & N$4 & "'!$A$11:$A$1000"), "INZIA IL TRATTAMENTO-VENDITA") -> 0 | O8: =SUMIFS(INDIRECT("'" & O$4 & "'!$I$11:$I$1000"), INDIRECT("'" & O$4 & "'!$G$11:$G$1000"), $E8, INDIRECT("'" & O$4 & "'!$A$11:$A$1000"), "INZIA IL TRATTAMENTO-VENDITA") -> 0 | P8: =SUMIFS(INDIRECT("'" & P$4 & "'!$I$11:$I$1000"), INDIRECT("'" & P$4 & "'!$G$11:$G$1000"), $E8, INDIRECT("'" & P$4 & "'!$A$11:$A$1000"), "INZIA IL TRATTAMENTO-VENDITA") -> 0 | Q8: =SUMIFS(INDIRECT("'" & Q$4 & "'!$I$11:$I$1000"), INDIRECT("'" & Q$4 & "'!$G$11:$G$1000"), $E8, INDIRECT("'" & Q$4 & "'!$A$11:$A$1000"), "INZIA IL TRATTAMENTO-VENDITA") -> 0 | R8: =SUM(C8:Q8) -> 0
B9: BERNARDINI | C9: =SUMIFS('OPPORTUNITA DI VENDITA'!$J$198:$J$1000, 'OPPORTUNITA DI VENDITA'!$H$198:$H$1000, B9, 'OPPORTUNITA DI VENDITA'!$B$198:$B$1000, "ESEGUITO") -> 0 | E9: BERNARDINI | F9: =SUMIFS(INDIRECT("'" & $F$4 & "'!$I$11:$I$1000"), INDIRECT("'" & $F$4 & "'!$G$11:$G$1000"), $E9, INDIRECT("'" & $F$4 & "'!$A$11:$A$1000"), "INZIA IL TRATTAMENTO-VENDITA") -> 0 | G9: =SUMIFS(INDIRECT("'" & $G$4 & "'!$I$11:$I$1000"), INDIRECT("'" & $G$4 & "'!$G$11:$G$1000"), $E9, INDIRECT("'" & $G$4 & "'!$A$11:$A$1000"), "INZIA IL TRATTAMENTO-VENDITA") -> 0 | H9: =SUMIFS(INDIRECT("'" & $H$4 & "'!$I$11:$I$1000"), INDIRECT("'" & $H$4 & "'!$G$11:$G$1000"), $E9, INDIRECT("'" & $H$4 & "'!$A$11:$A$1000"), "INZIA IL TRATTAMENTO-VENDITA") -> 0 | I9: =SUMIFS(INDIRECT("'" & $I$4 & "'!$I$11:$I$1000"), INDIRECT("'" & $I$4 & "'!$G$11:$G$1000"), $E9, INDIRECT("'" & $I$4 & "'!$A$11:$A$1000"), "INZIA IL TRATTAMENTO-VENDITA") -> 0 | J9: =SUMIFS(INDIRECT("'" & J$4 & "'!$I$11:$I$1000"), INDIRECT("'" & J$4 & "'!$G$11:$G$1000"), $E9, INDIRECT("'" & J$4 & "'!$A$11:$A$1000"), "INZIA IL TRATTAMENTO-VENDITA") -> 0 | K9: =SUMIFS(INDIRECT("'" & K$4 & "'!$I$11:$I$1000"), INDIRECT("'" & K$4 & "'!$G$11:$G$1000"), $E9, INDIRECT("'" & K$4 & "'!$A$11:$A$1000"), "INZIA IL TRATTAMENTO-VENDITA") -> 0 | L9: =SUMIFS(INDIRECT("'" & L$4 & "'!$I$11:$I$1000"), INDIRECT("'" & L$4 & "'!$G$11:$G$1000"), $E9, INDIRECT("'" & L$4 & "'!$A$11:$A$1000"), "INZIA IL TRATTAMENTO-VENDITA") -> 0 | M9: =SUMIFS(INDIRECT("'" & M$4 & "'!$I$11:$I$1000"), INDIRECT("'" & M$4 & "'!$G$11:$G$1000"), $E9, INDIRECT("'" & M$4 & "'!$A$11:$A$1000"), "INZIA IL TRATTAMENTO-VENDITA") -> 0 | N9: =SUMIFS(INDIRECT("'" & N$4 & "'!$I$11:$I$1000"), INDIRECT("'" & N$4 & "'!$G$11:$G$1000"), $E9, INDIRECT("'" & N$4 & "'!$A$11:$A$1000"), "INZIA IL TRATTAMENTO-VENDITA") -> 0 | O9: =SUMIFS(INDIRECT("'" & O$4 & "'!$I$11:$I$1000"), INDIRECT("'" & O$4 & "'!$G$11:$G$1000"), $E9, INDIRECT("'" & O$4 & "'!$A$11:$A$1000"), "INZIA IL TRATTAMENTO-VENDITA") -> 0 | P9: =SUMIFS(INDIRECT("'" & P$4 & "'!$I$11:$I$1000"), INDIRECT("'" & P$4 & "'!$G$11:$G$1000"), $E9, INDIRECT("'" & P$4 & "'!$A$11:$A$1000"), "INZIA IL TRATTAMENTO-VENDITA") -> 0 | Q9: =SUMIFS(INDIRECT("'" & Q$4 & "'!$I$11:$I$1000"), INDIRECT("'" & Q$4 & "'!$G$11:$G$1000"), $E9, INDIRECT("'" & Q$4 & "'!$A$11:$A$1000"), "INZIA IL TRATTAMENTO-VENDITA") -> 0 | R9: =SUM(C9:Q9) -> 0
B10: MASTRORILLI | C10: =SUMIFS('OPPORTUNITA DI VENDITA'!$J$198:$J$1000, 'OPPORTUNITA DI VENDITA'!$H$198:$H$1000, B10, 'OPPORTUNITA DI VENDITA'!$B$198:$B$1000, "ESEGUITO") -> 0 | E10: MASTRORILLI | F10: =SUMIFS(INDIRECT("'" & $F$4 & "'!$I$11:$I$1000"), INDIRECT("'" & $F$4 & "'!$G$11:$G$1000"), $E10, INDIRECT("'" & $F$4 & "'!$A$11:$A$1000"), "INZIA IL TRATTAMENTO-VENDITA") -> 0 | G10: =SUMIFS(INDIRECT("'" & $G$4 & "'!$I$11:$I$1000"), INDIRECT("'" & $G$4 & "'!$G$11:$G$1000"), $E10, INDIRECT("'" & $G$4 & "'!$A$11:$A$1000"), "INZIA IL TRATTAMENTO-VENDITA") -> 0 | H10: =SUMIFS(INDIRECT("'" & $H$4 & "'!$I$11:$I$1000"), INDIRECT("'" & $H$4 & "'!$G$11:$G$1000"), $E10, INDIRECT("'" & $H$4 & "'!$A$11:$A$1000"), "INZIA IL TRATTAMENTO-VENDITA") -> 0 | I10: =SUMIFS(INDIRECT("'" & $I$4 & "'!$I$11:$I$1000"), INDIRECT("'" & $I$4 & "'!$G$11:$G$1000"), $E10, INDIRECT("'" & $I$4 & "'!$A$11:$A$1000"), "INZIA IL TRATTAMENTO-VENDITA") -> 759 | J10: =SUMIFS(INDIRECT("'" & J$4 & "'!$I$11:$I$1000"), INDIRECT("'" & J$4 & "'!$G$11:$G$1000"), $E10, INDIRECT("'" & J$4 & "'!$A$11:$A$1000"), "INZIA IL TRATTAMENTO-VENDITA") -> 100 | K10: =SUMIFS(INDIRECT("'" & K$4 & "'!$I$11:$I$1000"), INDIRECT("'" & K$4 & "'!$G$11:$G$1000"), $E10, INDIRECT("'" & K$4 & "'!$A$11:$A$1000"), "INZIA IL TRATTAMENTO-VENDITA") -> 640 | L10: =SUMIFS(INDIRECT("'" & L$4 & "'!$I$11:$I$1000"), INDIRECT("'" & L$4 & "'!$G$11:$G$1000"), $E10, INDIRECT("'" & L$4 & "'!$A$11:$A$1000"), "INZIA IL TRATTAMENTO-VENDITA") -> 0 | M10: =SUMIFS(INDIRECT("'" & M$4 & "'!$I$11:$I$1000"), INDIRECT("'" & M$4 & "'!$G$11:$G$1000"), $E10, INDIRECT("'" & M$4 & "'!$A$11:$A$1000"), "INZIA IL TRATTAMENTO-VENDITA") -> 0 | N10: =SUMIFS(INDIRECT("'" & N$4 & "'!$I$11:$I$1000"), INDIRECT("'" & N$4 & "'!$G$11:$G$1000"), $E10, INDIRECT("'" & N$4 & "'!$A$11:$A$1000"), "INZIA IL TRATTAMENTO-VENDITA") -> 0 | O10: =SUMIFS(INDIRECT("'" & O$4 & "'!$I$11:$I$1000"), INDIRECT("'" & O$4 & "'!$G$11:$G$1000"), $E10, INDIRECT("'" & O$4 & "'!$A$11:$A$1000"), "INZIA IL TRATTAMENTO-VENDITA") -> 0 | P10: =SUMIFS(INDIRECT("'" & P$4 & "'!$I$11:$I$1000"), INDIRECT("'" & P$4 & "'!$G$11:$G$1000"), $E10, INDIRECT("'" & P$4 & "'!$A$11:$A$1000"), "INZIA IL TRATTAMENTO-VENDITA") -> 0 | Q10: =SUMIFS(INDIRECT("'" & Q$4 & "'!$I$11:$I$1000"), INDIRECT("'" & Q$4 & "'!$G$11:$G$1000"), $E10, INDIRECT("'" & Q$4 & "'!$A$11:$A$1000"), "INZIA IL TRATTAMENTO-VENDITA") -> 0 | R10: =SUM(C10:Q10) -> 1499
B11: CARDONE | C11: =SUMIFS('OPPORTUNITA DI VENDITA'!$J$198:$J$1000, 'OPPORTUNITA DI VENDITA'!$H$198:$H$1000, B11, 'OPPORTUNITA DI VENDITA'!$B$198:$B$1000, "ESEGUITO") -> 0 | E11: CARDONE | F11: =SUMIFS(INDIRECT("'" & $F$4 & "'!$I$11:$I$1000"), INDIRECT("'" & $F$4 & "'!$G$11:$G$1000"), $E11, INDIRECT("'" & $F$4 & "'!$A$11:$A$1000"), "INZIA IL TRATTAMENTO-VENDITA") -> 7785 | G11: =SUMIFS(INDIRECT("'" & $G$4 & "'!$I$11:$I$1000"), INDIRECT("'" & $G$4 & "'!$G$11:$G$1000"), $E11, INDIRECT("'" & $G$4 & "'!$A$11:$A$1000"), "INZIA IL TRATTAMENTO-VENDITA") -> 0 | H11: =SUMIFS(INDIRECT("'" & $H$4 & "'!$I$11:$I$1000"), INDIRECT("'" & $H$4 & "'!$G$11:$G$1000"), $E11, INDIRECT("'" & $H$4 & "'!$A$11:$A$1000"), "INZIA IL TRATTAMENTO-VENDITA") -> 11520 | I11: =SUMIFS(INDIRECT("'" & $I$4 & "'!$I$11:$I$1000"), INDIRECT("'" & $I$4 & "'!$G$11:$G$1000"), $E11, INDIRECT("'" & $I$4 & "'!$A$11:$A$1000"), "INZIA IL TRATTAMENTO-VENDITA") -> 4191 | J11: =SUMIFS(INDIRECT("'" & J$4 & "'!$I$11:$I$1000"), INDIRECT("'" & J$4 & "'!$G$11:$G$1000"), $E11, INDIRECT("'" & J$4 & "'!$A$11:$A$1000"), "INZIA IL TRATTAMENTO-VENDITA") -> 0 | K11: =SUMIFS(INDIRECT("'" & K$4 & "'!$I$11:$I$1000"), INDIRECT("'" & K$4 & "'!$G$11:$G$1000"), $E11, INDIRECT("'" & K$4 & "'!$A$11:$A$1000"), "INZIA IL TRATTAMENTO-VENDITA") -> 4590 | L11: =SUMIFS(INDIRECT("'" & L$4 & "'!$I$11:$I$1000"), INDIRECT("'" & L$4 & "'!$G$11:$G$1000"), $E11, INDIRECT("'" & L$4 & "'!$A$11:$A$1000"), "INZIA IL TRATTAMENTO-VENDITA") -> 0 | M11: =SUMIFS(INDIRECT("'" & M$4 & "'!$I$11:$I$1000"), INDIRECT("'" & M$4 & "'!$G$11:$G$1000"), $E11, INDIRECT("'" & M$4 & "'!$A$11:$A$1000"), "INZIA IL TRATTAMENTO-VENDITA") -> 0 | N11: =SUMIFS(INDIRECT("'" & N$4 & "'!$I$11:$I$1000"), INDIRECT("'" & N$4 & "'!$G$11:$G$1000"), $E11, INDIRECT("'" & N$4 & "'!$A$11:$A$1000"), "INZIA IL TRATTAMENTO-VENDITA") -> 0 | O11: =SUMIFS(INDIRECT("'" & O$4 & "'!$I$11:$I$1000"), INDIRECT("'" & O$4 & "'!$G$11:$G$1000"), $E11, INDIRECT("'" & O$4 & "'!$A$11:$A$1000"), "INZIA IL TRATTAMENTO-VENDITA") -> 0 | P11: =SUMIFS(INDIRECT("'" & P$4 & "'!$I$11:$I$1000"), INDIRECT("'" & P$4 & "'!$G$11:$G$1000"), $E11, INDIRECT("'" & P$4 & "'!$A$11:$A$1000"), "INZIA IL TRATTAMENTO-VENDITA") -> 0 | Q11: =SUMIFS(INDIRECT("'" & Q$4 & "'!$I$11:$I$1000"), INDIRECT("'" & Q$4 & "'!$G$11:$G$1000"), $E11, INDIRECT("'" & Q$4 & "'!$A$11:$A$1000"), "INZIA IL TRATTAMENTO-VENDITA") -> 0 | R11: =SUM(C11:Q11) -> 28086
B12: MARCANTONI | C12: =SUMIFS('OPPORTUNITA DI VENDITA'!$J$198:$J$1000, 'OPPORTUNITA DI VENDITA'!$H$198:$H$1000, B12, 'OPPORTUNITA DI VENDITA'!$B$198:$B$1000, "ESEGUITO") -> 0 | E12: MARCANTONI | F12: =SUMIFS(INDIRECT("'" & $F$4 & "'!$I$11:$I$1000"), INDIRECT("'" & $F$4 & "'!$G$11:$G$1000"), $E12, INDIRECT("'" & $F$4 & "'!$A$11:$A$1000"), "INZIA IL TRATTAMENTO-VENDITA") -> 304 | G12: =SUMIFS(INDIRECT("'" & $G$4 & "'!$I$11:$I$1000"), INDIRECT("'" & $G$4 & "'!$G$11:$G$1000"), $E12, INDIRECT("'" & $G$4 & "'!$A$11:$A$1000"), "INZIA IL TRATTAMENTO-VENDITA") -> 240 | H12: =SUMIFS(INDIRECT("'" & $H$4 & "'!$I$11:$I$1000"), INDIRECT("'" & $H$4 & "'!$G$11:$G$1000"), $E12, INDIRECT("'" & $H$4 & "'!$A$11:$A$1000"), "INZIA IL TRATTAMENTO-VENDITA") -> 392 | I12: =SUMIFS(INDIRECT("'" & $I$4 & "'!$I$11:$I$1000"), INDIRECT("'" & $I$4 & "'!$G$11:$G$1000"), $E12, INDIRECT("'" & $I$4 & "'!$A$11:$A$1000"), "INZIA IL TRATTAMENTO-VENDITA") -> 0 | J12: =SUMIFS(INDIRECT("'" & J$4 & "'!$I$11:$I$1000"), INDIRECT("'" & J$4 & "'!$G$11:$G$1000"), $E12, INDIRECT("'" & J$4 & "'!$A$11:$A$1000"), "INZIA IL TRATTAMENTO-VENDITA") -> 205 | K12: =SUMIFS(INDIRECT("'" & K$4 & "'!$I$11:$I$1000"), INDIRECT("'" & K$4 & "'!$G$11:$G$1000"), $E12, INDIRECT("'" & K$4 & "'!$A$11:$A$1000"), "INZIA IL TRATTAMENTO-VENDITA") -> 100 | L12: =SUMIFS(INDIRECT("'" & L$4 & "'!$I$11:$I$1000"), INDIRECT("'" & L$4 & "'!$G$11:$G$1000"), $E12, INDIRECT("'" & L$4 & "'!$A$11:$A$1000"), "INZIA IL TRATTAMENTO-VENDITA") -> 0 | M12: =SUMIFS(INDIRECT("'" & M$4 & "'!$I$11:$I$1000"), INDIRECT("'" & M$4 & "'!$G$11:$G$1000"), $E12, INDIRECT("'" & M$4 & "'!$A$11:$A$1000"), "INZIA IL TRATTAMENTO-VENDITA") -> 0 | N12: =SUMIFS(INDIRECT("'" & N$4 & "'!$I$11:$I$1000"), INDIRECT("'" & N$4 & "'!$G$11:$G$1000"), $E12, INDIRECT("'" & N$4 & "'!$A$11:$A$1000"), "INZIA IL TRATTAMENTO-VENDITA") -> 0 | O12: =SUMIFS(INDIRECT("'" & O$4 & "'!$I$11:$I$1000"), INDIRECT("'" & O$4 & "'!$G$11:$G$1000"), $E12, INDIRECT("'" & O$4 & "'!$A$11:$A$1000"), "INZIA IL TRATTAMENTO-VENDITA") -> 0 | P12: =SUMIFS(INDIRECT("'" & P$4 & "'!$I$11:$I$1000"), INDIRECT("'" & P$4 & "'!$G$11:$G$1000"), $E12, INDIRECT("'" & P$4 & "'!$A$11:$A$1000"), "INZIA IL TRATTAMENTO-VENDITA") -> 0 | Q12: =SUMIFS(INDIRECT("'" & Q$4 & "'!$I$11:$I$1000"), INDIRECT("'" & Q$4 & "'!$G$11:$G$1000"), $E12, INDIRECT("'" & Q$4 & "'!$A$11:$A$1000"), "INZIA IL TRATTAMENTO-VENDITA") -> 0 | R12: =SUM(C12:Q12) -> 1241
B13: MIRACOLO | C13: =SUMIFS('OPPORTUNITA DI VENDITA'!$J$198:$J$1000, 'OPPORTUNITA DI VENDITA'!$H$198:$H$1000, B13, 'OPPORTUNITA DI VENDITA'!$B$198:$B$1000, "ESEGUITO") -> 10844 | E13: MIRACOLO | F13: =SUMIFS(INDIRECT("'" & $F$4 & "'!$I$11:$I$1000"), INDIRECT("'" & $F$4 & "'!$G$11:$G$1000"), $E13, INDIRECT("'" & $F$4 & "'!$A$11:$A$1000"), "INZIA IL TRATTAMENTO-VENDITA") -> 0 | G13: =SUMIFS(INDIRECT("'" & $G$4 & "'!$I$11:$I$1000"), INDIRECT("'" & $G$4 & "'!$G$11:$G$1000"), $E13, INDIRECT("'" & $G$4 & "'!$A$11:$A$1000"), "INZIA IL TRATTAMENTO-VENDITA") -> 70 | H13: =SUMIFS(INDIRECT("'" & $H$4 & "'!$I$11:$I$1000"), INDIRECT("'" & $H$4 & "'!$G$11:$G$1000"), $E13, INDIRECT("'" & $H$4 & "'!$A$11:$A$1000"), "INZIA IL TRATTAMENTO-VENDITA") -> 10250 | I13: =SUMIFS(INDIRECT("'" & $I$4 & "'!$I$11:$I$1000"), INDIRECT("'" & $I$4 & "'!$G$11:$G$1000"), $E13, INDIRECT("'" & $I$4 & "'!$A$11:$A$1000"), "INZIA IL TRATTAMENTO-VENDITA") -> 0 | J13: =SUMIFS(INDIRECT("'" & J$4 & "'!$I$11:$I$1000"), INDIRECT("'" & J$4 & "'!$G$11:$G$1000"), $E13, INDIRECT("'" & J$4 & "'!$A$11:$A$1000"), "INZIA IL TRATTAMENTO-VENDITA") -> 2103 | K13: =SUMIFS(INDIRECT("'" & K$4 & "'!$I$11:$I$1000"), INDIRECT("'" & K$4 & "'!$G$11:$G$1000"), $E13, INDIRECT("'" & K$4 & "'!$A$11:$A$1000"), "INZIA IL TRATTAMENTO-VENDITA") -> 1450 | L13: =SUMIFS(INDIRECT("'" & L$4 & "'!$I$11:$I$1000"), INDIRECT("'" & L$4 & "'!$G$11:$G$1000"), $E13, INDIRECT("'" & L$4 & "'!$A$11:$A$1000"), "INZIA IL TRATTAMENTO-VENDITA") -> 0 | M13: =SUMIFS(INDIRECT("'" & M$4 & "'!$I$11:$I$1000"), INDIRECT("'" & M$4 & "'!$G$11:$G$1000"), $E13, INDIRECT("'" & M$4 & "'!$A$11:$A$1000"), "INZIA IL TRATTAMENTO-VENDITA") -> 0 | N13: =SUMIFS(INDIRECT("'" & N$4 & "'!$I$11:$I$1000"), INDIRECT("'" & N$4 & "'!$G$11:$G$1000"), $E13, INDIRECT("'" & N$4 & "'!$A$11:$A$1000"), "INZIA IL TRATTAMENTO-VENDITA") -> 0 | O13: =SUMIFS(INDIRECT("'" & O$4 & "'!$I$11:$I$1000"), INDIRECT("'" & O$4 & "'!$G$11:$G$1000"), $E13, INDIRECT("'" & O$4 & "'!$A$11:$A$1000"), "INZIA IL TRATTAMENTO-VENDITA") -> 0 | P13: =SUMIFS(INDIRECT("'" & P$4 & "'!$I$11:$I$1000"), INDIRECT("'" & P$4 & "'!$G$11:$G$1000"), $E13, INDIRECT("'" & P$4 & "'!$A$11:$A$1000"), "INZIA IL TRATTAMENTO-VENDITA") -> 0 | Q13: =SUMIFS(INDIRECT("'" & Q$4 & "'!$I$11:$I$1000"), INDIRECT("'" & Q$4 & "'!$G$11:$G$1000"), $E13, INDIRECT("'" & Q$4 & "'!$A$11:$A$1000"), "INZIA IL TRATTAMENTO-VENDITA") -> 0 | R13: =SUM(C13:Q13) -> 24717
B14: MAZZELLI | C14: =SUMIFS('OPPORTUNITA DI VENDITA'!$J$198:$J$1000, 'OPPORTUNITA DI VENDITA'!$H$198:$H$1000, B14, 'OPPORTUNITA DI VENDITA'!$B$198:$B$1000, "ESEGUITO") -> 0 | E14: MAZZELLI | F14: =SUMIFS(INDIRECT("'" & $F$4 & "'!$I$11:$I$1000"), INDIRECT("'" & $F$4 & "'!$G$11:$G$1000"), $E14, INDIRECT("'" & $F$4 & "'!$A$11:$A$1000"), "INZIA IL TRATTAMENTO-VENDITA") -> 21830 | G14: =SUMIFS(INDIRECT("'" & $G$4 & "'!$I$11:$I$1000"), INDIRECT("'" & $G$4 & "'!$G$11:$G$1000"), $E14, INDIRECT("'" & $G$4 & "'!$A$11:$A$1000"), "INZIA IL TRATTAMENTO-VENDITA") -> 22358 | H14: =SUMIFS(INDIRECT("'" & $H$4 & "'!$I$11:$I$1000"), INDIRECT("'" & $H$4 & "'!$G$11:$G$1000"), $E14, INDIRECT("'" & $H$4 & "'!$A$11:$A$1000"), "INZIA IL TRATTAMENTO-VENDITA") -> 7900 | I14: =SUMIFS(INDIRECT("'" & $I$4 & "'!$I$11:$I$1000"), INDIRECT("'" & $I$4 & "'!$G$11:$G$1000"), $E14, INDIRECT("'" & $I$4 & "'!$A$11:$A$1000"), "INZIA IL TRATTAMENTO-VENDITA") -> 1055 | J14: =SUMIFS(INDIRECT("'" & J$4 & "'!$I$11:$I$1000"), INDIRECT("'" & J$4 & "'!$G$11:$G$1000"), $E14, INDIRECT("'" & J$4 & "'!$A$11:$A$1000"), "INZIA IL TRATTAMENTO-VENDITA") -> 17001 | K14: =SUMIFS(INDIRECT("'" & K$4 & "'!$I$11:$I$1000"), INDIRECT("'" & K$4 & "'!$G$11:$G$1000"), $E14, INDIRECT("'" & K$4 & "'!$A$11:$A$1000"), "INZIA IL TRATTAMENTO-VENDITA") -> 0 | L14: =SUMIFS(INDIRECT("'" & L$4 & "'!$I$11:$I$1000"), INDIRECT("'" & L$4 & "'!$G$11:$G$1000"), $E14, INDIRECT("'" & L$4 & "'!$A$11:$A$1000"), "INZIA IL TRATTAMENTO-VENDITA") -> 0 | M14: =SUMIFS(INDIRECT("'" & M$4 & "'!$I$11:$I$1000"), INDIRECT("'" & M$4 & "'!$G$11:$G$1000"), $E14, INDIRECT("'" & M$4 & "'!$A$11:$A$1000"), "INZIA IL TRATTAMENTO-VENDITA") -> 0 | N14: =SUMIFS(INDIRECT("'" & N$4 & "'!$I$11:$I$1000"), INDIRECT("'" & N$4 & "'!$G$11:$G$1000"), $E14, INDIRECT("'" & N$4 & "'!$A$11:$A$1000"), "INZIA IL TRATTAMENTO-VENDITA") -> 0 | O14: =SUMIFS(INDIRECT("'" & O$4 & "'!$I$11:$I$1000"), INDIRECT("'" & O$4 & "'!$G$11:$G$1000"), $E14, INDIRECT("'" & O$4 & "'!$A$11:$A$1000"), "INZIA IL TRATTAMENTO-VENDITA") -> 0 | P14: =SUMIFS(INDIRECT("'" & P$4 & "'!$I$11:$I$1000"), INDIRECT("'" & P$4 & "'!$G$11:$G$1000"), $E14, INDIRECT("'" & P$4 & "'!$A$11:$A$1000"), "INZIA IL TRATTAMENTO-VENDITA") -> 0 | Q14: =SUMIFS(INDIRECT("'" & Q$4 & "'!$I$11:$I$1000"), INDIRECT("'" & Q$4 & "'!$G$11:$G$1000"), $E14, INDIRECT("'" & Q$4 & "'!$A$11:$A$1000"), "INZIA IL TRATTAMENTO-VENDITA") -> 0 | R14: =SUM(C14:Q14) -> 70144
B15: GAGLIARDI | C15: =SUMIFS('OPPORTUNITA DI VENDITA'!$J$198:$J$1000, 'OPPORTUNITA DI VENDITA'!$H$198:$H$1000, B15, 'OPPORTUNITA DI VENDITA'!$B$198:$B$1000, "ESEGUITO") -> 0 | E15: GAGLIARDI | F15: =SUMIFS(INDIRECT("'" & $F$4 & "'!$I$11:$I$1000"), INDIRECT("'" & $F$4 & "'!$G$11:$G$1000"), $E15, INDIRECT("'" & $F$4 & "'!$A$11:$A$1000"), "INZIA IL TRATTAMENTO-VENDITA") -> 0 | G15: =SUMIFS(INDIRECT("'" & $G$4 & "'!$I$11:$I$1000"), INDIRECT("'" & $G$4 & "'!$G$11:$G$1000"), $E15, INDIRECT("'" & $G$4 & "'!$A$11:$A$1000"), "INZIA IL TRATTAMENTO-VENDITA") -> 0 | H15: =SUMIFS(INDIRECT("'" & $H$4 & "'!$I$11:$I$1000"), INDIRECT("'" & $H$4 & "'!$G$11:$G$1000"), $E15, INDIRECT("'" & $H$4 & "'!$A$11:$A$1000"), "INZIA IL TRATTAMENTO-VENDITA") -> 0 | I15: =SUMIFS(INDIRECT("'" & $I$4 & "'!$I$11:$I$1000"), INDIRECT("'" & $I$4 & "'!$G$11:$G$1000"), $E15, INDIRECT("'" & $I$4 & "'!$A$11:$A$1000"), "INZIA IL TRATTAMENTO-VENDITA") -> 0 | J15: =SUMIFS(INDIRECT("'" & J$4 & "'!$I$11:$I$1000"), INDIRECT("'" & J$4 & "'!$G$11:$G$1000"), $E15, INDIRECT("'" & J$4 & "'!$A$11:$A$1000"), "INZIA IL TRATTAMENTO-VENDITA") -> 0 | K15: =SUMIFS(INDIRECT("'" & K$4 & "'!$I$11:$I$1000"), INDIRECT("'" & K$4 & "'!$G$11:$G$1000"), $E15, INDIRECT("'" & K$4 & "'!$A$11:$A$1000"), "INZIA IL TRATTAMENTO-VENDITA") -> 0 | L15: =SUMIFS(INDIRECT("'" & L$4 & "'!$I$11:$I$1000"), INDIRECT("'" & L$4 & "'!$G$11:$G$1000"), $E15, INDIRECT("'" & L$4 & "'!$A$11:$A$1000"), "INZIA IL TRATTAMENTO-VENDITA") -> 0 | M15: =SUMIFS(INDIRECT("'" & M$4 & "'!$I$11:$I$1000"), INDIRECT("'" & M$4 & "'!$G$11:$G$1000"), $E15, INDIRECT("'" & M$4 & "'!$A$11:$A$1000"), "INZIA IL TRATTAMENTO-VENDITA") -> 0 | N15: =SUMIFS(INDIRECT("'" & N$4 & "'!$I$11:$I$1000"), INDIRECT("'" & N$4 & "'!$G$11:$G$1000"), $E15, INDIRECT("'" & N$4 & "'!$A$11:$A$1000"), "INZIA IL TRATTAMENTO-VENDITA") -> 0 | O15: =SUMIFS(INDIRECT("'" & O$4 & "'!$I$11:$I$1000"), INDIRECT("'" & O$4 & "'!$G$11:$G$1000"), $E15, INDIRECT("'" & O$4 & "'!$A$11:$A$1000"), "INZIA IL TRATTAMENTO-VENDITA") -> 0 | P15: =SUMIFS(INDIRECT("'" & P$4 & "'!$I$11:$I$1000"), INDIRECT("'" & P$4 & "'!$G$11:$G$1000"), $E15, INDIRECT("'" & P$4 & "'!$A$11:$A$1000"), "INZIA IL TRATTAMENTO-VENDITA") -> 0 | Q15: =SUMIFS(INDIRECT("'" & Q$4 & "'!$I$11:$I$1000"), INDIRECT("'" & Q$4 & "'!$G$11:$G$1000"), $E15, INDIRECT("'" & Q$4 & "'!$A$11:$A$1000"), "INZIA IL TRATTAMENTO-VENDITA") -> 0 | R15: =SUM(C15:Q15) -> 0
C16: =SUMIFS('OPPORTUNITA DI VENDITA'!$J$198:$J$1000, 'OPPORTUNITA DI VENDITA'!$H$198:$H$1000, B16, 'OPPORTUNITA DI VENDITA'!$B$198:$B$1000, "ESEGUITO") -> 0 | F16: =SUMIFS(INDIRECT("'" & $F$4 & "'!$I$11:$I$1000"), INDIRECT("'" & $F$4 & "'!$G$11:$G$1000"), $E16, INDIRECT("'" & $F$4 & "'!$A$11:$A$1000"), "INZIA IL TRATTAMENTO-VENDITA") -> 0 | G16: =SUMIFS(INDIRECT("'" & $G$4 & "'!$I$11:$I$1000"), INDIRECT("'" & $G$4 & "'!$G$11:$G$1000"), $E16, INDIRECT("'" & $G$4 & "'!$A$11:$A$1000"), "INZIA IL TRATTAMENTO-VENDITA") -> 0 | H16: =SUMIFS(INDIRECT("'" & $H$4 & "'!$I$11:$I$1000"), INDIRECT("'" & $H$4 & "'!$G$11:$G$1000"), $E16, INDIRECT("'" & $H$4 & "'!$A$11:$A$1000"), "INZIA IL TRATTAMENTO-VENDITA") -> 0 | I16: =SUMIFS(INDIRECT("'" & $I$4 & "'!$I$11:$I$1000"), INDIRECT("'" & $I$4 & "'!$G$11:$G$1000"), $E16, INDIRECT("'" & $I$4 & "'!$A$11:$A$1000"), "INZIA IL TRATTAMENTO-VENDITA") -> 0 | J16: =SUMIFS(INDIRECT("'" & J$4 & "'!$I$11:$I$1000"), INDIRECT("'" & J$4 & "'!$G$11:$G$1000"), $E16, INDIRECT("'" & J$4 & "'!$A$11:$A$1000"), "INZIA IL TRATTAMENTO-VENDITA") -> 0 | K16: =SUMIFS(INDIRECT("'" & K$4 & "'!$I$11:$I$1000"), INDIRECT("'" & K$4 & "'!$G$11:$G$1000"), $E16, INDIRECT("'" & K$4 & "'!$A$11:$A$1000"), "INZIA IL TRATTAMENTO-VENDITA") -> 0 | L16: =SUMIFS(INDIRECT("'" & L$4 & "'!$I$11:$I$1000"), INDIRECT("'" & L$4 & "'!$G$11:$G$1000"), $E16, INDIRECT("'" & L$4 & "'!$A$11:$A$1000"), "INZIA IL TRATTAMENTO-VENDITA") -> 0 | M16: =SUMIFS(INDIRECT("'" & M$4 & "'!$I$11:$I$1000"), INDIRECT("'" & M$4 & "'!$G$11:$G$1000"), $E16, INDIRECT("'" & M$4 & "'!$A$11:$A$1000"), "INZIA IL TRATTAMENTO-VENDITA") -> 0 | N16: =SUMIFS(INDIRECT("'" & N$4 & "'!$I$11:$I$1000"), INDIRECT("'" & N$4 & "'!$G$11:$G$1000"), $E16, INDIRECT("'" & N$4 & "'!$A$11:$A$1000"), "INZIA IL TRATTAMENTO-VENDITA") -> 0 | O16: =SUMIFS(INDIRECT("'" & O$4 & "'!$I$11:$I$1000"), INDIRECT("'" & O$4 & "'!$G$11:$G$1000"), $E16, INDIRECT("'" & O$4 & "'!$A$11:$A$1000"), "INZIA IL TRATTAMENTO-VENDITA") -> 0 | P16: =SUMIFS(INDIRECT("'" & P$4 & "'!$I$11:$I$1000"), INDIRECT("'" & P$4 & "'!$G$11:$G$1000"), $E16, INDIRECT("'" & P$4 & "'!$A$11:$A$1000"), "INZIA IL TRATTAMENTO-VENDITA") -> 0 | Q16: =SUMIFS(INDIRECT("'" & Q$4 & "'!$I$11:$I$1000"), INDIRECT("'" & Q$4 & "'!$G$11:$G$1000"), $E16, INDIRECT("'" & Q$4 & "'!$A$11:$A$1000"), "INZIA IL TRATTAMENTO-VENDITA") -> 0 | R16: =SUM(C16:Q16) -> 0
C17: =SUMIFS('OPPORTUNITA DI VENDITA'!$J$198:$J$1000, 'OPPORTUNITA DI VENDITA'!$H$198:$H$1000, B17, 'OPPORTUNITA DI VENDITA'!$B$198:$B$1000, "ESEGUITO") -> 0 | F17: =SUMIFS(INDIRECT("'" & $F$4 & "'!$I$11:$I$1000"), INDIRECT("'" & $F$4 & "'!$G$11:$G$1000"), $E17, INDIRECT("'" & $F$4 & "'!$A$11:$A$1000"), "INZIA IL TRATTAMENTO-VENDITA") -> 0 | G17: =SUMIFS(INDIRECT("'" & $G$4 & "'!$I$11:$I$1000"), INDIRECT("'" & $G$4 & "'!$G$11:$G$1000"), $E17, INDIRECT("'" & $G$4 & "'!$A$11:$A$1000"), "INZIA IL TRATTAMENTO-VENDITA") -> 0 | H17: =SUMIFS(INDIRECT("'" & $H$4 & "'!$I$11:$I$1000"), INDIRECT("'" & $H$4 & "'!$G$11:$G$1000"), $E17, INDIRECT("'" & $H$4 & "'!$A$11:$A$1000"), "INZIA IL TRATTAMENTO-VENDITA") -> 0 | I17: =SUMIFS(INDIRECT("'" & $I$4 & "'!$I$11:$I$1000"), INDIRECT("'" & $I$4 & "'!$G$11:$G$1000"), $E17, INDIRECT("'" & $I$4 & "'!$A$11:$A$1000"), "INZIA IL TRATTAMENTO-VENDITA") -> 0 | J17: =SUMIFS(INDIRECT("'" & J$4 & "'!$I$11:$I$1000"), INDIRECT("'" & J$4 & "'!$G$11:$G$1000"), $E17, INDIRECT("'" & J$4 & "'!$A$11:$A$1000"), "INZIA IL TRATTAMENTO-VENDITA") -> 0 | K17: =SUMIFS(INDIRECT("'" & K$4 & "'!$I$11:$I$1000"), INDIRECT("'" & K$4 & "'!$G$11:$G$1000"), $E17, INDIRECT("'" & K$4 & "'!$A$11:$A$1000"), "INZIA IL TRATTAMENTO-VENDITA") -> 0 | L17: =SUMIFS(INDIRECT("'" & L$4 & "'!$I$11:$I$1000"), INDIRECT("'" & L$4 & "'!$G$11:$G$1000"), $E17, INDIRECT("'" & L$4 & "'!$A$11:$A$1000"), "INZIA IL TRATTAMENTO-VENDITA") -> 0 | M17: =SUMIFS(INDIRECT("'" & M$4 & "'!$I$11:$I$1000"), INDIRECT("'" & M$4 & "'!$G$11:$G$1000"), $E17, INDIRECT("'" & M$4 & "'!$A$11:$A$1000"), "INZIA IL TRATTAMENTO-VENDITA") -> 0 | N17: =SUMIFS(INDIRECT("'" & N$4 & "'!$I$11:$I$1000"), INDIRECT("'" & N$4 & "'!$G$11:$G$1000"), $E17, INDIRECT("'" & N$4 & "'!$A$11:$A$1000"), "INZIA IL TRATTAMENTO-VENDITA") -> 0 | O17: =SUMIFS(INDIRECT("'" & O$4 & "'!$I$11:$I$1000"), INDIRECT("'" & O$4 & "'!$G$11:$G$1000"), $E17, INDIRECT("'" & O$4 & "'!$A$11:$A$1000"), "INZIA IL TRATTAMENTO-VENDITA") -> 0 | P17: =SUMIFS(INDIRECT("'" & P$4 & "'!$I$11:$I$1000"), INDIRECT("'" & P$4 & "'!$G$11:$G$1000"), $E17, INDIRECT("'" & P$4 & "'!$A$11:$A$1000"), "INZIA IL TRATTAMENTO-VENDITA") -> 0 | Q17: =SUMIFS(INDIRECT("'" & Q$4 & "'!$I$11:$I$1000"), INDIRECT("'" & Q$4 & "'!$G$11:$G$1000"), $E17, INDIRECT("'" & Q$4 & "'!$A$11:$A$1000"), "INZIA IL TRATTAMENTO-VENDITA") -> 0 | R17: =SUM(C17:Q17) -> 0
C18: =SUMIFS('OPPORTUNITA DI VENDITA'!$J$198:$J$1000, 'OPPORTUNITA DI VENDITA'!$H$198:$H$1000, B18, 'OPPORTUNITA DI VENDITA'!$B$198:$B$1000, "ESEGUITO") -> 0 | F18: =SUMIFS(INDIRECT("'" & $F$4 & "'!$I$11:$I$1000"), INDIRECT("'" & $F$4 & "'!$G$11:$G$1000"), $E18, INDIRECT("'" & $F$4 & "'!$A$11:$A$1000"), "INZIA IL TRATTAMENTO-VENDITA") -> 0 | G18: =SUMIFS(INDIRECT("'" & $G$4 & "'!$I$11:$I$1000"), INDIRECT("'" & $G$4 & "'!$G$11:$G$1000"), $E18, INDIRECT("'" & $G$4 & "'!$A$11:$A$1000"), "INZIA IL TRATTAMENTO-VENDITA") -> 0 | H18: =SUMIFS(INDIRECT("'" & $H$4 & "'!$I$11:$I$1000"), INDIRECT("'" & $H$4 & "'!$G$11:$G$1000"), $E18, INDIRECT("'" & $H$4 & "'!$A$11:$A$1000"), "INZIA IL TRATTAMENTO-VENDITA") -> 0 | I18: =SUMIFS(INDIRECT("'" & $I$4 & "'!$I$11:$I$1000"), INDIRECT("'" & $I$4 & "'!$G$11:$G$1000"), $E18, INDIRECT("'" & $I$4 & "'!$A$11:$A$1000"), "INZIA IL TRATTAMENTO-VENDITA") -> 0 | J18: =SUMIFS(INDIRECT("'" & J$4 & "'!$I$11:$I$1000"), INDIRECT("'" & J$4 & "'!$G$11:$G$1000"), $E18, INDIRECT("'" & J$4 & "'!$A$11:$A$1000"), "INZIA IL TRATTAMENTO-VENDITA") -> 0 | K18: =SUMIFS(INDIRECT("'" & K$4 & "'!$I$11:$I$1000"), INDIRECT("'" & K$4 & "'!$G$11:$G$1000"), $E18, INDIRECT("'" & K$4 & "'!$A$11:$A$1000"), "INZIA IL TRATTAMENTO-VENDITA") -> 0 | L18: =SUMIFS(INDIRECT("'" & L$4 & "'!$I$11:$I$1000"), INDIRECT("'" & L$4 & "'!$G$11:$G$1000"), $E18, INDIRECT("'" & L$4 & "'!$A$11:$A$1000"), "INZIA IL TRATTAMENTO-VENDITA") -> 0 | M18: =SUMIFS(INDIRECT("'" & M$4 & "'!$I$11:$I$1000"), INDIRECT("'" & M$4 & "'!$G$11:$G$1000"), $E18, INDIRECT("'" & M$4 & "'!$A$11:$A$1000"), "INZIA IL TRATTAMENTO-VENDITA") -> 0 | N18: =SUMIFS(INDIRECT("'" & N$4 & "'!$I$11:$I$1000"), INDIRECT("'" & N$4 & "'!$G$11:$G$1000"), $E18, INDIRECT("'" & N$4 & "'!$A$11:$A$1000"), "INZIA IL TRATTAMENTO-VENDITA") -> 0 | O18: =SUMIFS(INDIRECT("'" & O$4 & "'!$I$11:$I$1000"), INDIRECT("'" & O$4 & "'!$G$11:$G$1000"), $E18, INDIRECT("'" & O$4 & "'!$A$11:$A$1000"), "INZIA IL TRATTAMENTO-VENDITA") -> 0 | P18: =SUMIFS(INDIRECT("'" & P$4 & "'!$I$11:$I$1000"), INDIRECT("'" & P$4 & "'!$G$11:$G$1000"), $E18, INDIRECT("'" & P$4 & "'!$A$11:$A$1000"), "INZIA IL TRATTAMENTO-VENDITA") -> 0 | Q18: =SUMIFS(INDIRECT("'" & Q$4 & "'!$I$11:$I$1000"), INDIRECT("'" & Q$4 & "'!$G$11:$G$1000"), $E18, INDIRECT("'" & Q$4 & "'!$A$11:$A$1000"), "INZIA IL TRATTAMENTO-VENDITA") -> 0 | R18: =SUM(C18:Q18) -> 0
B19: Tot.Anno---> | C19: =SUM(C5:C18) -> 36232 | E19: Tot.Mese---> | F19: =SUM(F5:F18) -> 35484 | G19: =SUM(G5:G18) -> 104999 | H19: =SUM(H5:H18) -> 54103 | I19: =SUM(I5:I18) -> 23735 | J19: =SUM(J5:J18) -> 39216 | K19: =SUM(K5:K18) -> 24720 | L19: =SUM(L5:L18) -> 0 | M19: =SUM(M5:M18) -> 0 | ... R19: =SUM(R5:R18) -> 318489 | S19: <---Tot.Accettato Complessivo
B24: Consuntivo Annuale | C24: Opp.tà di Vendita | D24: Colonna 2 | E24: Preventivato Mese RIFIUTATO | F24: 1 | G24: 2 | H24: 3 | I24: 4 | J24: 5 | K24: 6 | L24: 7 | M24: 8 | N24: 9 | O24: 10 | P24: 11 | Q24: 12 | R24: TOTALE | S24: ,,
F25: gennaio | G25: febbraio | H25: marzo | I25: aprile | J25: maggio | K25: giugno | L25: luglio | M25: agosto | N25: settembre | O25: ottobre | P25: novembre | Q25: dicembre
B26: DOMENICI | C26: =SUMIFS('OPPORTUNITA DI VENDITA'!$J$198:$J$1000, 'OPPORTUNITA DI VENDITA'!$H$198:$H$1000, B26, 'OPPORTUNITA DI VENDITA'!$B$198:$B$1000, "NON ESEGUITO") -> 0 | E26: DOMENICI | F26: =SUMIFS(INDIRECT("'" & $F$4 & "'!$I$11:$I$1000"), INDIRECT("'" & $F$4 & "'!$G$11:$G$1000"), $E26, INDIRECT("'" & $F$4 & "'!$A$11:$A$1000"), "NESSUNA VENDITA") -> 26088 | G26: =SUMIFS(INDIRECT("'" & $G$4 & "'!$I$11:$I$1000"), INDIRECT("'" & $G$4 & "'!$G$11:$G$1000"), $E26, INDIRECT("'" & $G$4 & "'!$A$11:$A$1000"), "NESSUNA VENDITA") -> 75785 | H26: =SUMIFS(INDIRECT("'" & $H$4 & "'!$I$11:$I$1000"), INDIRECT("'" & $H$4 & "'!$G$11:$G$1000"), $E26, INDIRECT("'" & $H$4 & "'!$A$11:$A$1000"), "NESSUNA VENDITA") -> 2072 | I26: =SUMIFS(INDIRECT("'" & I$4 & "'!$I$11:$I$1000"), INDIRECT("'" & I$4 & "'!$G$11:$G$1000"), $E26, INDIRECT("'" & I$4 & "'!$A$11:$A$1000"), "NESSUNA VENDITA") -> 28522 | J26: =SUMIFS(INDIRECT("'" & J$4 & "'!$I$11:$I$1000"), INDIRECT("'" & J$4 & "'!$G$11:$G$1000"), $E26, INDIRECT("'" & J$4 & "'!$A$11:$A$1000"), "NESSUNA VENDITA") -> 22356 | K26: =SUMIFS(INDIRECT("'" & K$4 & "'!$I$11:$I$1000"), INDIRECT("'" & K$4 & "'!$G$11:$G$1000"), $E26, INDIRECT("'" & K$4 & "'!$A$11:$A$1000"), "NESSUNA VENDITA") -> 0 | L26: =SUMIFS(INDIRECT("'" & L$4 & "'!$I$11:$I$1000"), INDIRECT("'" & L$4 & "'!$G$11:$G$1000"), $E26, INDIRECT("'" & L$4 & "'!$A$11:$A$1000"), "NESSUNA VENDITA") -> 0 | M26: =SUMIFS(INDIRECT("'" & M$4 & "'!$I$11:$I$1000"), INDIRECT("'" & M$4 & "'!$G$11:$G$1000"), $E26, INDIRECT("'" & M$4 & "'!$A$11:$A$1000"), "NESSUNA VENDITA") -> 0 | N26: =SUMIFS(INDIRECT("'" & N$4 & "'!$I$11:$I$1000"), INDIRECT("'" & N$4 & "'!$G$11:$G$1000"), $E26, INDIRECT("'" & N$4 & "'!$A$11:$A$1000"), "NESSUNA VENDITA") -> 0 | O26: =SUMIFS(INDIRECT("'" & O$4 & "'!$I$11:$I$1000"), INDIRECT("'" & O$4 & "'!$G$11:$G$1000"), $E26, INDIRECT("'" & O$4 & "'!$A$11:$A$1000"), "NESSUNA VENDITA") -> 0 | P26: =SUMIFS(INDIRECT("'" & P$4 & "'!$I$11:$I$1000"), INDIRECT("'" & P$4 & "'!$G$11:$G$1000"), $E26, INDIRECT("'" & P$4 & "'!$A$11:$A$1000"), "NESSUNA VENDITA") -> 0 | Q26: =SUMIFS(INDIRECT("'" & Q$4 & "'!$I$11:$I$1000"), INDIRECT("'" & Q$4 & "'!$G$11:$G$1000"), $E26, INDIRECT("'" & Q$4 & "'!$A$11:$A$1000"), "NESSUNA VENDITA") -> 0 | R26: =SUM(C26:Q26) -> 154823
B27: AMOROSO | C27: =SUMIFS('OPPORTUNITA DI VENDITA'!$J$198:$J$1000, 'OPPORTUNITA DI VENDITA'!$H$198:$H$1000, B27, 'OPPORTUNITA DI VENDITA'!$B$198:$B$1000, "NON ESEGUITO") -> 0 | E27: AMOROSO | F27: =SUMIFS(INDIRECT("'" & $F$4 & "'!$I$11:$I$1000"), INDIRECT("'" & $F$4 & "'!$G$11:$G$1000"), $E27, INDIRECT("'" & $F$4 & "'!$A$11:$A$1000"), "NESSUNA VENDITA") -> 18880 | G27: =SUMIFS(INDIRECT("'" & $G$4 & "'!$I$11:$I$1000"), INDIRECT("'" & $G$4 & "'!$G$11:$G$1000"), $E27, INDIRECT("'" & $G$4 & "'!$A$11:$A$1000"), "NESSUNA VENDITA") -> 0 | H27: =SUMIFS(INDIRECT("'" & $H$4 & "'!$I$11:$I$1000"), INDIRECT("'" & $H$4 & "'!$G$11:$G$1000"), $E27, INDIRECT("'" & $H$4 & "'!$A$11:$A$1000"), "NESSUNA VENDITA") -> 32430 | I27: =SUMIFS(INDIRECT("'" & I$4 & "'!$I$11:$I$1000"), INDIRECT("'" & I$4 & "'!$G$11:$G$1000"), $E27, INDIRECT("'" & I$4 & "'!$A$11:$A$1000"), "NESSUNA VENDITA") -> 18555 | J27: =SUMIFS(INDIRECT("'" & J$4 & "'!$I$11:$I$1000"), INDIRECT("'" & J$4 & "'!$G$11:$G$1000"), $E27, INDIRECT("'" & J$4 & "'!$A$11:$A$1000"), "NESSUNA VENDITA") -> 15556 | K27: =SUMIFS(INDIRECT("'" & K$4 & "'!$I$11:$I$1000"), INDIRECT("'" & K$4 & "'!$G$11:$G$1000"), $E27, INDIRECT("'" & K$4 & "'!$A$11:$A$1000"), "NESSUNA VENDITA") -> 0 | L27: =SUMIFS(INDIRECT("'" & L$4 & "'!$I$11:$I$1000"), INDIRECT("'" & L$4 & "'!$G$11:$G$1000"), $E27, INDIRECT("'" & L$4 & "'!$A$11:$A$1000"), "NESSUNA VENDITA") -> 0 | M27: =SUMIFS(INDIRECT("'" & M$4 & "'!$I$11:$I$1000"), INDIRECT("'" & M$4 & "'!$G$11:$G$1000"), $E27, INDIRECT("'" & M$4 & "'!$A$11:$A$1000"), "NESSUNA VENDITA") -> 0 | N27: =SUMIFS(INDIRECT("'" & N$4 & "'!$I$11:$I$1000"), INDIRECT("'" & N$4 & "'!$G$11:$G$1000"), $E27, INDIRECT("'" & N$4 & "'!$A$11:$A$1000"), "NESSUNA VENDITA") -> 0 | O27: =SUMIFS(INDIRECT("'" & O$4 & "'!$I$11:$I$1000"), INDIRECT("'" & O$4 & "'!$G$11:$G$1000"), $E27, INDIRECT("'" & O$4 & "'!$A$11:$A$1000"), "NESSUNA VENDITA") -> 0 | P27: =SUMIFS(INDIRECT("'" & P$4 & "'!$I$11:$I$1000"), INDIRECT("'" & P$4 & "'!$G$11:$G$1000"), $E27, INDIRECT("'" & P$4 & "'!$A$11:$A$1000"), "NESSUNA VENDITA") -> 0 | Q27: =SUMIFS(INDIRECT("'" & Q$4 & "'!$I$11:$I$1000"), INDIRECT("'" & Q$4 & "'!$G$11:$G$1000"), $E27, INDIRECT("'" & Q$4 & "'!$A$11:$A$1000"), "NESSUNA VENDITA") -> 0 | R27: =SUM(C27:Q27) -> 85421
B28: INNOCENTE | C28: =SUMIFS('OPPORTUNITA DI VENDITA'!$J$198:$J$1000, 'OPPORTUNITA DI VENDITA'!$H$198:$H$1000, B28, 'OPPORTUNITA DI VENDITA'!$B$198:$B$1000, "NON ESEGUITO") -> 0 | E28: INNOCENTE | F28: =SUMIFS(INDIRECT("'" & $F$4 & "'!$I$11:$I$1000"), INDIRECT("'" & $F$4 & "'!$G$11:$G$1000"), $E28, INDIRECT("'" & $F$4 & "'!$A$11:$A$1000"), "NESSUNA VENDITA") -> 0 | G28: =SUMIFS(INDIRECT("'" & $G$4 & "'!$I$11:$I$1000"), INDIRECT("'" & $G$4 & "'!$G$11:$G$1000"), $E28, INDIRECT("'" & $G$4 & "'!$A$11:$A$1000"), "NESSUNA VENDITA") -> 0 | H28: =SUMIFS(INDIRECT("'" & $H$4 & "'!$I$11:$I$1000"), INDIRECT("'" & $H$4 & "'!$G$11:$G$1000"), $E28, INDIRECT("'" & $H$4 & "'!$A$11:$A$1000"), "NESSUNA VENDITA") -> 0 | I28: =SUMIFS(INDIRECT("'" & I$4 & "'!$I$11:$I$1000"), INDIRECT("'" & I$4 & "'!$G$11:$G$1000"), $E28, INDIRECT("'" & I$4 & "'!$A$11:$A$1000"), "NESSUNA VENDITA") -> 0 | J28: =SUMIFS(INDIRECT("'" & J$4 & "'!$I$11:$I$1000"), INDIRECT("'" & J$4 & "'!$G$11:$G$1000"), $E28, INDIRECT("'" & J$4 & "'!$A$11:$A$1000"), "NESSUNA VENDITA") -> 0 | K28: =SUMIFS(INDIRECT("'" & K$4 & "'!$I$11:$I$1000"), INDIRECT("'" & K$4 & "'!$G$11:$G$1000"), $E28, INDIRECT("'" & K$4 & "'!$A$11:$A$1000"), "NESSUNA VENDITA") -> 0 | L28: =SUMIFS(INDIRECT("'" & L$4 & "'!$I$11:$I$1000"), INDIRECT("'" & L$4 & "'!$G$11:$G$1000"), $E28, INDIRECT("'" & L$4 & "'!$A$11:$A$1000"), "NESSUNA VENDITA") -> 0 | M28: =SUMIFS(INDIRECT("'" & M$4 & "'!$I$11:$I$1000"), INDIRECT("'" & M$4 & "'!$G$11:$G$1000"), $E28, INDIRECT("'" & M$4 & "'!$A$11:$A$1000"), "NESSUNA VENDITA") -> 0 | N28: =SUMIFS(INDIRECT("'" & N$4 & "'!$I$11:$I$1000"), INDIRECT("'" & N$4 & "'!$G$11:$G$1000"), $E28, INDIRECT("'" & N$4 & "'!$A$11:$A$1000"), "NESSUNA VENDITA") -> 0 | O28: =SUMIFS(INDIRECT("'" & O$4 & "'!$I$11:$I$1000"), INDIRECT("'" & O$4 & "'!$G$11:$G$1000"), $E28, INDIRECT("'" & O$4 & "'!$A$11:$A$1000"), "NESSUNA VENDITA") -> 0 | P28: =SUMIFS(INDIRECT("'" & P$4 & "'!$I$11:$I$1000"), INDIRECT("'" & P$4 & "'!$G$11:$G$1000"), $E28, INDIRECT("'" & P$4 & "'!$A$11:$A$1000"), "NESSUNA VENDITA") -> 0 | Q28: =SUMIFS(INDIRECT("'" & Q$4 & "'!$I$11:$I$1000"), INDIRECT("'" & Q$4 & "'!$G$11:$G$1000"), $E28, INDIRECT("'" & Q$4 & "'!$A$11:$A$1000"), "NESSUNA VENDITA") -> 0 | R28: =SUM(C28:Q28) -> 0
B29: BERARDI | C29: =SUMIFS('OPPORTUNITA DI VENDITA'!$J$198:$J$1000, 'OPPORTUNITA DI VENDITA'!$H$198:$H$1000, B29, 'OPPORTUNITA DI VENDITA'!$B$198:$B$1000, "NON ESEGUITO") -> 0 | E29: BERARDI | F29: =SUMIFS(INDIRECT("'" & $F$4 & "'!$I$11:$I$1000"), INDIRECT("'" & $F$4 & "'!$G$11:$G$1000"), $E29, INDIRECT("'" & $F$4 & "'!$A$11:$A$1000"), "NESSUNA VENDITA") -> 0 | G29: =SUMIFS(INDIRECT("'" & $G$4 & "'!$I$11:$I$1000"), INDIRECT("'" & $G$4 & "'!$G$11:$G$1000"), $E29, INDIRECT("'" & $G$4 & "'!$A$11:$A$1000"), "NESSUNA VENDITA") -> 0 | H29: =SUMIFS(INDIRECT("'" & $H$4 & "'!$I$11:$I$1000"), INDIRECT("'" & $H$4 & "'!$G$11:$G$1000"), $E29, INDIRECT("'" & $H$4 & "'!$A$11:$A$1000"), "NESSUNA VENDITA") -> 0 | I29: =SUMIFS(INDIRECT("'" & I$4 & "'!$I$11:$I$1000"), INDIRECT("'" & I$4 & "'!$G$11:$G$1000"), $E29, INDIRECT("'" & I$4 & "'!$A$11:$A$1000"), "NESSUNA VENDITA") -> 0 | J29: =SUMIFS(INDIRECT("'" & J$4 & "'!$I$11:$I$1000"), INDIRECT("'" & J$4 & "'!$G$11:$G$1000"), $E29, INDIRECT("'" & J$4 & "'!$A$11:$A$1000"), "NESSUNA VENDITA") -> 0 | K29: =SUMIFS(INDIRECT("'" & K$4 & "'!$I$11:$I$1000"), INDIRECT("'" & K$4 & "'!$G$11:$G$1000"), $E29, INDIRECT("'" & K$4 & "'!$A$11:$A$1000"), "NESSUNA VENDITA") -> 0 | L29: =SUMIFS(INDIRECT("'" & L$4 & "'!$I$11:$I$1000"), INDIRECT("'" & L$4 & "'!$G$11:$G$1000"), $E29, INDIRECT("'" & L$4 & "'!$A$11:$A$1000"), "NESSUNA VENDITA") -> 0 | M29: =SUMIFS(INDIRECT("'" & M$4 & "'!$I$11:$I$1000"), INDIRECT("'" & M$4 & "'!$G$11:$G$1000"), $E29, INDIRECT("'" & M$4 & "'!$A$11:$A$1000"), "NESSUNA VENDITA") -> 0 | N29: =SUMIFS(INDIRECT("'" & N$4 & "'!$I$11:$I$1000"), INDIRECT("'" & N$4 & "'!$G$11:$G$1000"), $E29, INDIRECT("'" & N$4 & "'!$A$11:$A$1000"), "NESSUNA VENDITA") -> 0 | O29: =SUMIFS(INDIRECT("'" & O$4 & "'!$I$11:$I$1000"), INDIRECT("'" & O$4 & "'!$G$11:$G$1000"), $E29, INDIRECT("'" & O$4 & "'!$A$11:$A$1000"), "NESSUNA VENDITA") -> 0 | P29: =SUMIFS(INDIRECT("'" & P$4 & "'!$I$11:$I$1000"), INDIRECT("'" & P$4 & "'!$G$11:$G$1000"), $E29, INDIRECT("'" & P$4 & "'!$A$11:$A$1000"), "NESSUNA VENDITA") -> 0 | Q29: =SUMIFS(INDIRECT("'" & Q$4 & "'!$I$11:$I$1000"), INDIRECT("'" & Q$4 & "'!$G$11:$G$1000"), $E29, INDIRECT("'" & Q$4 & "'!$A$11:$A$1000"), "NESSUNA VENDITA") -> 0 | R29: =SUM(C29:Q29) -> 0
B30: BERNARDINI | C30: =SUMIFS('OPPORTUNITA DI VENDITA'!$J$198:$J$1000, 'OPPORTUNITA DI VENDITA'!$H$198:$H$1000, B30, 'OPPORTUNITA DI VENDITA'!$B$198:$B$1000, "NON ESEGUITO") -> 0 | E30: BERNARDINI | F30: =SUMIFS(INDIRECT("'" & $F$4 & "'!$I$11:$I$1000"), INDIRECT("'" & $F$4 & "'!$G$11:$G$1000"), $E30, INDIRECT("'" & $F$4 & "'!$A$11:$A$1000"), "NESSUNA VENDITA") -> 0 | G30: =SUMIFS(INDIRECT("'" & $G$4 & "'!$I$11:$I$1000"), INDIRECT("'" & $G$4 & "'!$G$11:$G$1000"), $E30, INDIRECT("'" & $G$4 & "'!$A$11:$A$1000"), "NESSUNA VENDITA") -> 0 | H30: =SUMIFS(INDIRECT("'" & $H$4 & "'!$I$11:$I$1000"), INDIRECT("'" & $H$4 & "'!$G$11:$G$1000"), $E30, INDIRECT("'" & $H$4 & "'!$A$11:$A$1000"), "NESSUNA VENDITA") -> 0 | I30: =SUMIFS(INDIRECT("'" & I$4 & "'!$I$11:$I$1000"), INDIRECT("'" & I$4 & "'!$G$11:$G$1000"), $E30, INDIRECT("'" & I$4 & "'!$A$11:$A$1000"), "NESSUNA VENDITA") -> 0 | J30: =SUMIFS(INDIRECT("'" & J$4 & "'!$I$11:$I$1000"), INDIRECT("'" & J$4 & "'!$G$11:$G$1000"), $E30, INDIRECT("'" & J$4 & "'!$A$11:$A$1000"), "NESSUNA VENDITA") -> 0 | K30: =SUMIFS(INDIRECT("'" & K$4 & "'!$I$11:$I$1000"), INDIRECT("'" & K$4 & "'!$G$11:$G$1000"), $E30, INDIRECT("'" & K$4 & "'!$A$11:$A$1000"), "NESSUNA VENDITA") -> 0 | L30: =SUMIFS(INDIRECT("'" & L$4 & "'!$I$11:$I$1000"), INDIRECT("'" & L$4 & "'!$G$11:$G$1000"), $E30, INDIRECT("'" & L$4 & "'!$A$11:$A$1000"), "NESSUNA VENDITA") -> 0 | M30: =SUMIFS(INDIRECT("'" & M$4 & "'!$I$11:$I$1000"), INDIRECT("'" & M$4 & "'!$G$11:$G$1000"), $E30, INDIRECT("'" & M$4 & "'!$A$11:$A$1000"), "NESSUNA VENDITA") -> 0 | N30: =SUMIFS(INDIRECT("'" & N$4 & "'!$I$11:$I$1000"), INDIRECT("'" & N$4 & "'!$G$11:$G$1000"), $E30, INDIRECT("'" & N$4 & "'!$A$11:$A$1000"), "NESSUNA VENDITA") -> 0 | O30: =SUMIFS(INDIRECT("'" & O$4 & "'!$I$11:$I$1000"), INDIRECT("'" & O$4 & "'!$G$11:$G$1000"), $E30, INDIRECT("'" & O$4 & "'!$A$11:$A$1000"), "NESSUNA VENDITA") -> 0 | P30: =SUMIFS(INDIRECT("'" & P$4 & "'!$I$11:$I$1000"), INDIRECT("'" & P$4 & "'!$G$11:$G$1000"), $E30, INDIRECT("'" & P$4 & "'!$A$11:$A$1000"), "NESSUNA VENDITA") -> 0 | Q30: =SUMIFS(INDIRECT("'" & Q$4 & "'!$I$11:$I$1000"), INDIRECT("'" & Q$4 & "'!$G$11:$G$1000"), $E30, INDIRECT("'" & Q$4 & "'!$A$11:$A$1000"), "NESSUNA VENDITA") -> 0 | R30: =SUM(C30:Q30) -> 0
B31: MASTRORILLI | C31: =SUMIFS('OPPORTUNITA DI VENDITA'!$J$198:$J$1000, 'OPPORTUNITA DI VENDITA'!$H$198:$H$1000, B31, 'OPPORTUNITA DI VENDITA'!$B$198:$B$1000, "NON ESEGUITO") -> 0 | E31: MASTRORILLI | F31: =SUMIFS(INDIRECT("'" & $F$4 & "'!$I$11:$I$1000"), INDIRECT("'" & $F$4 & "'!$G$11:$G$1000"), $E31, INDIRECT("'" & $F$4 & "'!$A$11:$A$1000"), "NESSUNA VENDITA") -> 0 | G31: =SUMIFS(INDIRECT("'" & $G$4 & "'!$I$11:$I$1000"), INDIRECT("'" & $G$4 & "'!$G$11:$G$1000"), $E31, INDIRECT("'" & $G$4 & "'!$A$11:$A$1000"), "NESSUNA VENDITA") -> 0 | H31: =SUMIFS(INDIRECT("'" & $H$4 & "'!$I$11:$I$1000"), INDIRECT("'" & $H$4 & "'!$G$11:$G$1000"), $E31, INDIRECT("'" & $H$4 & "'!$A$11:$A$1000"), "NESSUNA VENDITA") -> 0 | I31: =SUMIFS(INDIRECT("'" & I$4 & "'!$I$11:$I$1000"), INDIRECT("'" & I$4 & "'!$G$11:$G$1000"), $E31, INDIRECT("'" & I$4 & "'!$A$11:$A$1000"), "NESSUNA VENDITA") -> 6500 | J31: =SUMIFS(INDIRECT("'" & J$4 & "'!$I$11:$I$1000"), INDIRECT("'" & J$4 & "'!$G$11:$G$1000"), $E31, INDIRECT("'" & J$4 & "'!$A$11:$A$1000"), "NESSUNA VENDITA") -> 0 | K31: =SUMIFS(INDIRECT("'" & K$4 & "'!$I$11:$I$1000"), INDIRECT("'" & K$4 & "'!$G$11:$G$1000"), $E31, INDIRECT("'" & K$4 & "'!$A$11:$A$1000"), "NESSUNA VENDITA") -> 0 | L31: =SUMIFS(INDIRECT("'" & L$4 & "'!$I$11:$I$1000"), INDIRECT("'" & L$4 & "'!$G$11:$G$1000"), $E31, INDIRECT("'" & L$4 & "'!$A$11:$A$1000"), "NESSUNA VENDITA") -> 0 | M31: =SUMIFS(INDIRECT("'" & M$4 & "'!$I$11:$I$1000"), INDIRECT("'" & M$4 & "'!$G$11:$G$1000"), $E31, INDIRECT("'" & M$4 & "'!$A$11:$A$1000"), "NESSUNA VENDITA") -> 0 | N31: =SUMIFS(INDIRECT("'" & N$4 & "'!$I$11:$I$1000"), INDIRECT("'" & N$4 & "'!$G$11:$G$1000"), $E31, INDIRECT("'" & N$4 & "'!$A$11:$A$1000"), "NESSUNA VENDITA") -> 0 | O31: =SUMIFS(INDIRECT("'" & O$4 & "'!$I$11:$I$1000"), INDIRECT("'" & O$4 & "'!$G$11:$G$1000"), $E31, INDIRECT("'" & O$4 & "'!$A$11:$A$1000"), "NESSUNA VENDITA") -> 0 | P31: =SUMIFS(INDIRECT("'" & P$4 & "'!$I$11:$I$1000"), INDIRECT("'" & P$4 & "'!$G$11:$G$1000"), $E31, INDIRECT("'" & P$4 & "'!$A$11:$A$1000"), "NESSUNA VENDITA") -> 0 | Q31: =SUMIFS(INDIRECT("'" & Q$4 & "'!$I$11:$I$1000"), INDIRECT("'" & Q$4 & "'!$G$11:$G$1000"), $E31, INDIRECT("'" & Q$4 & "'!$A$11:$A$1000"), "NESSUNA VENDITA") -> 0 | R31: =SUM(C31:Q31) -> 6500
B32: CARDONE | C32: =SUMIFS('OPPORTUNITA DI VENDITA'!$J$198:$J$1000, 'OPPORTUNITA DI VENDITA'!$H$198:$H$1000, B32, 'OPPORTUNITA DI VENDITA'!$B$198:$B$1000, "NON ESEGUITO") -> 0 | E32: CARDONE | F32: =SUMIFS(INDIRECT("'" & $F$4 & "'!$I$11:$I$1000"), INDIRECT("'" & $F$4 & "'!$G$11:$G$1000"), $E32, INDIRECT("'" & $F$4 & "'!$A$11:$A$1000"), "NESSUNA VENDITA") -> 5800 | G32: =SUMIFS(INDIRECT("'" & $G$4 & "'!$I$11:$I$1000"), INDIRECT("'" & $G$4 & "'!$G$11:$G$1000"), $E32, INDIRECT("'" & $G$4 & "'!$A$11:$A$1000"), "NESSUNA VENDITA") -> 0 | H32: =SUMIFS(INDIRECT("'" & $H$4 & "'!$I$11:$I$1000"), INDIRECT("'" & $H$4 & "'!$G$11:$G$1000"), $E32, INDIRECT("'" & $H$4 & "'!$A$11:$A$1000"), "NESSUNA VENDITA") -> 6790 | I32: =SUMIFS(INDIRECT("'" & I$4 & "'!$I$11:$I$1000"), INDIRECT("'" & I$4 & "'!$G$11:$G$1000"), $E32, INDIRECT("'" & I$4 & "'!$A$11:$A$1000"), "NESSUNA VENDITA") -> 9400 | J32: =SUMIFS(INDIRECT("'" & J$4 & "'!$I$11:$I$1000"), INDIRECT("'" & J$4 & "'!$G$11:$G$1000"), $E32, INDIRECT("'" & J$4 & "'!$A$11:$A$1000"), "NESSUNA VENDITA") -> 0 | K32: =SUMIFS(INDIRECT("'" & K$4 & "'!$I$11:$I$1000"), INDIRECT("'" & K$4 & "'!$G$11:$G$1000"), $E32, INDIRECT("'" & K$4 & "'!$A$11:$A$1000"), "NESSUNA VENDITA") -> 0 | L32: =SUMIFS(INDIRECT("'" & L$4 & "'!$I$11:$I$1000"), INDIRECT("'" & L$4 & "'!$G$11:$G$1000"), $E32, INDIRECT("'" & L$4 & "'!$A$11:$A$1000"), "NESSUNA VENDITA") -> 0 | M32: =SUMIFS(INDIRECT("'" & M$4 & "'!$I$11:$I$1000"), INDIRECT("'" & M$4 & "'!$G$11:$G$1000"), $E32, INDIRECT("'" & M$4 & "'!$A$11:$A$1000"), "NESSUNA VENDITA") -> 0 | N32: =SUMIFS(INDIRECT("'" & N$4 & "'!$I$11:$I$1000"), INDIRECT("'" & N$4 & "'!$G$11:$G$1000"), $E32, INDIRECT("'" & N$4 & "'!$A$11:$A$1000"), "NESSUNA VENDITA") -> 0 | O32: =SUMIFS(INDIRECT("'" & O$4 & "'!$I$11:$I$1000"), INDIRECT("'" & O$4 & "'!$G$11:$G$1000"), $E32, INDIRECT("'" & O$4 & "'!$A$11:$A$1000"), "NESSUNA VENDITA") -> 0 | P32: =SUMIFS(INDIRECT("'" & P$4 & "'!$I$11:$I$1000"), INDIRECT("'" & P$4 & "'!$G$11:$G$1000"), $E32, INDIRECT("'" & P$4 & "'!$A$11:$A$1000"), "NESSUNA VENDITA") -> 0 | Q32: =SUMIFS(INDIRECT("'" & Q$4 & "'!$I$11:$I$1000"), INDIRECT("'" & Q$4 & "'!$G$11:$G$1000"), $E32, INDIRECT("'" & Q$4 & "'!$A$11:$A$1000"), "NESSUNA VENDITA") -> 0 | R32: =SUM(C32:Q32) -> 21990
B33: MARCANTONI | C33: =SUMIFS('OPPORTUNITA DI VENDITA'!$J$198:$J$1000, 'OPPORTUNITA DI VENDITA'!$H$198:$H$1000, B33, 'OPPORTUNITA DI VENDITA'!$B$198:$B$1000, "NON ESEGUITO") -> 0 | E33: MARCANTONI | F33: =SUMIFS(INDIRECT("'" & $F$4 & "'!$I$11:$I$1000"), INDIRECT("'" & $F$4 & "'!$G$11:$G$1000"), $E33, INDIRECT("'" & $F$4 & "'!$A$11:$A$1000"), "NESSUNA VENDITA") -> 0 | G33: =SUMIFS(INDIRECT("'" & $G$4 & "'!$I$11:$I$1000"), INDIRECT("'" & $G$4 & "'!$G$11:$G$1000"), $E33, INDIRECT("'" & $G$4 & "'!$A$11:$A$1000"), "NESSUNA VENDITA") -> 0 | H33: =SUMIFS(INDIRECT("'" & $H$4 & "'!$I$11:$I$1000"), INDIRECT("'" & $H$4 & "'!$G$11:$G$1000"), $E33, INDIRECT("'" & $H$4 & "'!$A$11:$A$1000"), "NESSUNA VENDITA") -> 1212 | I33: =SUMIFS(INDIRECT("'" & I$4 & "'!$I$11:$I$1000"), INDIRECT("'" & I$4 & "'!$G$11:$G$1000"), $E33, INDIRECT("'" & I$4 & "'!$A$11:$A$1000"), "NESSUNA VENDITA") -> 0 | J33: =SUMIFS(INDIRECT("'" & J$4 & "'!$I$11:$I$1000"), INDIRECT("'" & J$4 & "'!$G$11:$G$1000"), $E33, INDIRECT("'" & J$4 & "'!$A$11:$A$1000"), "NESSUNA VENDITA") -> 0 | K33: =SUMIFS(INDIRECT("'" & K$4 & "'!$I$11:$I$1000"), INDIRECT("'" & K$4 & "'!$G$11:$G$1000"), $E33, INDIRECT("'" & K$4 & "'!$A$11:$A$1000"), "NESSUNA VENDITA") -> 0 | L33: =SUMIFS(INDIRECT("'" & L$4 & "'!$I$11:$I$1000"), INDIRECT("'" & L$4 & "'!$G$11:$G$1000"), $E33, INDIRECT("'" & L$4 & "'!$A$11:$A$1000"), "NESSUNA VENDITA") -> 0 | M33: =SUMIFS(INDIRECT("'" & M$4 & "'!$I$11:$I$1000"), INDIRECT("'" & M$4 & "'!$G$11:$G$1000"), $E33, INDIRECT("'" & M$4 & "'!$A$11:$A$1000"), "NESSUNA VENDITA") -> 0 | N33: =SUMIFS(INDIRECT("'" & N$4 & "'!$I$11:$I$1000"), INDIRECT("'" & N$4 & "'!$G$11:$G$1000"), $E33, INDIRECT("'" & N$4 & "'!$A$11:$A$1000"), "NESSUNA VENDITA") -> 0 | O33: =SUMIFS(INDIRECT("'" & O$4 & "'!$I$11:$I$1000"), INDIRECT("'" & O$4 & "'!$G$11:$G$1000"), $E33, INDIRECT("'" & O$4 & "'!$A$11:$A$1000"), "NESSUNA VENDITA") -> 0 | P33: =SUMIFS(INDIRECT("'" & P$4 & "'!$I$11:$I$1000"), INDIRECT("'" & P$4 & "'!$G$11:$G$1000"), $E33, INDIRECT("'" & P$4 & "'!$A$11:$A$1000"), "NESSUNA VENDITA") -> 0 | Q33: =SUMIFS(INDIRECT("'" & Q$4 & "'!$I$11:$I$1000"), INDIRECT("'" & Q$4 & "'!$G$11:$G$1000"), $E33, INDIRECT("'" & Q$4 & "'!$A$11:$A$1000"), "NESSUNA VENDITA") -> 0 | R33: =SUM(C33:Q33) -> 1212
B34: MIRACOLO | C34: =SUMIFS('OPPORTUNITA DI VENDITA'!$J$198:$J$1000, 'OPPORTUNITA DI VENDITA'!$H$198:$H$1000, B34, 'OPPORTUNITA DI VENDITA'!$B$198:$B$1000, "NON ESEGUITO") -> 0 | E34: MIRACOLO | F34: =SUMIFS(INDIRECT("'" & $F$4 & "'!$I$11:$I$1000"), INDIRECT("'" & $F$4 & "'!$G$11:$G$1000"), $E34, INDIRECT("'" & $F$4 & "'!$A$11:$A$1000"), "NESSUNA VENDITA") -> 5380 | G34: =SUMIFS(INDIRECT("'" & $G$4 & "'!$I$11:$I$1000"), INDIRECT("'" & $G$4 & "'!$G$11:$G$1000"), $E34, INDIRECT("'" & $G$4 & "'!$A$11:$A$1000"), "NESSUNA VENDITA") -> 0 | H34: =SUMIFS(INDIRECT("'" & $H$4 & "'!$I$11:$I$1000"), INDIRECT("'" & $H$4 & "'!$G$11:$G$1000"), $E34, INDIRECT("'" & $H$4 & "'!$A$11:$A$1000"), "NESSUNA VENDITA") -> 5781 | I34: =SUMIFS(INDIRECT("'" & I$4 & "'!$I$11:$I$1000"), INDIRECT("'" & I$4 & "'!$G$11:$G$1000"), $E34, INDIRECT("'" & I$4 & "'!$A$11:$A$1000"), "NESSUNA VENDITA") -> 7900 | J34: =SUMIFS(INDIRECT("'" & J$4 & "'!$I$11:$I$1000"), INDIRECT("'" & J$4 & "'!$G$11:$G$1000"), $E34, INDIRECT("'" & J$4 & "'!$A$11:$A$1000"), "NESSUNA VENDITA") -> 0 | K34: =SUMIFS(INDIRECT("'" & K$4 & "'!$I$11:$I$1000"), INDIRECT("'" & K$4 & "'!$G$11:$G$1000"), $E34, INDIRECT("'" & K$4 & "'!$A$11:$A$1000"), "NESSUNA VENDITA") -> 0 | L34: =SUMIFS(INDIRECT("'" & L$4 & "'!$I$11:$I$1000"), INDIRECT("'" & L$4 & "'!$G$11:$G$1000"), $E34, INDIRECT("'" & L$4 & "'!$A$11:$A$1000"), "NESSUNA VENDITA") -> 0 | M34: =SUMIFS(INDIRECT("'" & M$4 & "'!$I$11:$I$1000"), INDIRECT("'" & M$4 & "'!$G$11:$G$1000"), $E34, INDIRECT("'" & M$4 & "'!$A$11:$A$1000"), "NESSUNA VENDITA") -> 0 | N34: =SUMIFS(INDIRECT("'" & N$4 & "'!$I$11:$I$1000"), INDIRECT("'" & N$4 & "'!$G$11:$G$1000"), $E34, INDIRECT("'" & N$4 & "'!$A$11:$A$1000"), "NESSUNA VENDITA") -> 0 | O34: =SUMIFS(INDIRECT("'" & O$4 & "'!$I$11:$I$1000"), INDIRECT("'" & O$4 & "'!$G$11:$G$1000"), $E34, INDIRECT("'" & O$4 & "'!$A$11:$A$1000"), "NESSUNA VENDITA") -> 0 | P34: =SUMIFS(INDIRECT("'" & P$4 & "'!$I$11:$I$1000"), INDIRECT("'" & P$4 & "'!$G$11:$G$1000"), $E34, INDIRECT("'" & P$4 & "'!$A$11:$A$1000"), "NESSUNA VENDITA") -> 0 | Q34: =SUMIFS(INDIRECT("'" & Q$4 & "'!$I$11:$I$1000"), INDIRECT("'" & Q$4 & "'!$G$11:$G$1000"), $E34, INDIRECT("'" & Q$4 & "'!$A$11:$A$1000"), "NESSUNA VENDITA") -> 0 | R34: =SUM(C34:Q34) -> 19061
B35: MAZZELLI | C35: =SUMIFS('OPPORTUNITA DI VENDITA'!$J$198:$J$1000, 'OPPORTUNITA DI VENDITA'!$H$198:$H$1000, B35, 'OPPORTUNITA DI VENDITA'!$B$198:$B$1000, "NON ESEGUITO") -> 0 | E35: MAZZELLI | F35: =SUMIFS(INDIRECT("'" & $F$4 & "'!$I$11:$I$1000"), INDIRECT("'" & $F$4 & "'!$G$11:$G$1000"), $E35, INDIRECT("'" & $F$4 & "'!$A$11:$A$1000"), "NESSUNA VENDITA") -> 6720 | G35: =SUMIFS(INDIRECT("'" & $G$4 & "'!$I$11:$I$1000"), INDIRECT("'" & $G$4 & "'!$G$11:$G$1000"), $E35, INDIRECT("'" & $G$4 & "'!$A$11:$A$1000"), "NESSUNA VENDITA") -> 150 | H35: =SUMIFS(INDIRECT("'" & $H$4 & "'!$I$11:$I$1000"), INDIRECT("'" & $H$4 & "'!$G$11:$G$1000"), $E35, INDIRECT("'" & $H$4 & "'!$A$11:$A$1000"), "NESSUNA VENDITA") -> 4355 | I35: =SUMIFS(INDIRECT("'" & I$4 & "'!$I$11:$I$1000"), INDIRECT("'" & I$4 & "'!$G$11:$G$1000"), $E35, INDIRECT("'" & I$4 & "'!$A$11:$A$1000"), "NESSUNA VENDITA") -> 45621 | J35: =SUMIFS(INDIRECT("'" & J$4 & "'!$I$11:$I$1000"), INDIRECT("'" & J$4 & "'!$G$11:$G$1000"), $E35, INDIRECT("'" & J$4 & "'!$A$11:$A$1000"), "NESSUNA VENDITA") -> 2000 | K35: =SUMIFS(INDIRECT("'" & K$4 & "'!$I$11:$I$1000"), INDIRECT("'" & K$4 & "'!$G$11:$G$1000"), $E35, INDIRECT("'" & K$4 & "'!$A$11:$A$1000"), "NESSUNA VENDITA") -> 0 | L35: =SUMIFS(INDIRECT("'" & L$4 & "'!$I$11:$I$1000"), INDIRECT("'" & L$4 & "'!$G$11:$G$1000"), $E35, INDIRECT("'" & L$4 & "'!$A$11:$A$1000"), "NESSUNA VENDITA") -> 0 | M35: =SUMIFS(INDIRECT("'" & M$4 & "'!$I$11:$I$1000"), INDIRECT("'" & M$4 & "'!$G$11:$G$1000"), $E35, INDIRECT("'" & M$4 & "'!$A$11:$A$1000"), "NESSUNA VENDITA") -> 0 | N35: =SUMIFS(INDIRECT("'" & N$4 & "'!$I$11:$I$1000"), INDIRECT("'" & N$4 & "'!$G$11:$G$1000"), $E35, INDIRECT("'" & N$4 & "'!$A$11:$A$1000"), "NESSUNA VENDITA") -> 0 | O35: =SUMIFS(INDIRECT("'" & O$4 & "'!$I$11:$I$1000"), INDIRECT("'" & O$4 & "'!$G$11:$G$1000"), $E35, INDIRECT("'" & O$4 & "'!$A$11:$A$1000"), "NESSUNA VENDITA") -> 0 | P35: =SUMIFS(INDIRECT("'" & P$4 & "'!$I$11:$I$1000"), INDIRECT("'" & P$4 & "'!$G$11:$G$1000"), $E35, INDIRECT("'" & P$4 & "'!$A$11:$A$1000"), "NESSUNA VENDITA") -> 0 | Q35: =SUMIFS(INDIRECT("'" & Q$4 & "'!$I$11:$I$1000"), INDIRECT("'" & Q$4 & "'!$G$11:$G$1000"), $E35, INDIRECT("'" & Q$4 & "'!$A$11:$A$1000"), "NESSUNA VENDITA") -> 0 | R35: =SUM(C35:Q35) -> 58846
B36: GAGLIARDI | C36: =SUMIFS('OPPORTUNITA DI VENDITA'!$J$198:$J$1000, 'OPPORTUNITA DI VENDITA'!$H$198:$H$1000, B36, 'OPPORTUNITA DI VENDITA'!$B$198:$B$1000, "NON ESEGUITO") -> 0 | E36: GAGLIARDI | F36: =SUMIFS(INDIRECT("'" & $F$4 & "'!$I$11:$I$1000"), INDIRECT("'" & $F$4 & "'!$G$11:$G$1000"), $E36, INDIRECT("'" & $F$4 & "'!$A$11:$A$1000"), "NESSUNA VENDITA") -> 0 | G36: =SUMIFS(INDIRECT("'" & $G$4 & "'!$I$11:$I$1000"), INDIRECT("'" & $G$4 & "'!$G$11:$G$1000"), $E36, INDIRECT("'" & $G$4 & "'!$A$11:$A$1000"), "NESSUNA VENDITA") -> 0 | H36: =SUMIFS(INDIRECT("'" & $H$4 & "'!$I$11:$I$1000"), INDIRECT("'" & $H$4 & "'!$G$11:$G$1000"), $E36, INDIRECT("'" & $H$4 & "'!$A$11:$A$1000"), "NESSUNA VENDITA") -> 0 | I36: =SUMIFS(INDIRECT("'" & I$4 & "'!$I$11:$I$1000"), INDIRECT("'" & I$4 & "'!$G$11:$G$1000"), $E36, INDIRECT("'" & I$4 & "'!$A$11:$A$1000"), "NESSUNA VENDITA") -> 0 | J36: =SUMIFS(INDIRECT("'" & J$4 & "'!$I$11:$I$1000"), INDIRECT("'" & J$4 & "'!$G$11:$G$1000"), $E36, INDIRECT("'" & J$4 & "'!$A$11:$A$1000"), "NESSUNA VENDITA") -> 0 | K36: =SUMIFS(INDIRECT("'" & K$4 & "'!$I$11:$I$1000"), INDIRECT("'" & K$4 & "'!$G$11:$G$1000"), $E36, INDIRECT("'" & K$4 & "'!$A$11:$A$1000"), "NESSUNA VENDITA") -> 0 | L36: =SUMIFS(INDIRECT("'" & L$4 & "'!$I$11:$I$1000"), INDIRECT("'" & L$4 & "'!$G$11:$G$1000"), $E36, INDIRECT("'" & L$4 & "'!$A$11:$A$1000"), "NESSUNA VENDITA") -> 0 | M36: =SUMIFS(INDIRECT("'" & M$4 & "'!$I$11:$I$1000"), INDIRECT("'" & M$4 & "'!$G$11:$G$1000"), $E36, INDIRECT("'" & M$4 & "'!$A$11:$A$1000"), "NESSUNA VENDITA") -> 0 | N36: =SUMIFS(INDIRECT("'" & N$4 & "'!$I$11:$I$1000"), INDIRECT("'" & N$4 & "'!$G$11:$G$1000"), $E36, INDIRECT("'" & N$4 & "'!$A$11:$A$1000"), "NESSUNA VENDITA") -> 0 | O36: =SUMIFS(INDIRECT("'" & O$4 & "'!$I$11:$I$1000"), INDIRECT("'" & O$4 & "'!$G$11:$G$1000"), $E36, INDIRECT("'" & O$4 & "'!$A$11:$A$1000"), "NESSUNA VENDITA") -> 0 | P36: =SUMIFS(INDIRECT("'" & P$4 & "'!$I$11:$I$1000"), INDIRECT("'" & P$4 & "'!$G$11:$G$1000"), $E36, INDIRECT("'" & P$4 & "'!$A$11:$A$1000"), "NESSUNA VENDITA") -> 0 | Q36: =SUMIFS(INDIRECT("'" & Q$4 & "'!$I$11:$I$1000"), INDIRECT("'" & Q$4 & "'!$G$11:$G$1000"), $E36, INDIRECT("'" & Q$4 & "'!$A$11:$A$1000"), "NESSUNA VENDITA") -> 0 | R36: =SUM(C36:Q36) -> 0
C37: =SUMIFS('OPPORTUNITA DI VENDITA'!$J$198:$J$1000, 'OPPORTUNITA DI VENDITA'!$H$198:$H$1000, B37, 'OPPORTUNITA DI VENDITA'!$B$198:$B$1000, "NON ESEGUITO") -> 0 | F37: =SUMIFS(INDIRECT("'" & $F$4 & "'!$I$11:$I$1000"), INDIRECT("'" & $F$4 & "'!$G$11:$G$1000"), $E37, INDIRECT("'" & $F$4 & "'!$A$11:$A$1000"), "NESSUNA VENDITA") -> 0 | G37: =SUMIFS(INDIRECT("'" & $G$4 & "'!$I$11:$I$1000"), INDIRECT("'" & $G$4 & "'!$G$11:$G$1000"), $E37, INDIRECT("'" & $G$4 & "'!$A$11:$A$1000"), "NESSUNA VENDITA") -> 0 | H37: =SUMIFS(INDIRECT("'" & $H$4 & "'!$I$11:$I$1000"), INDIRECT("'" & $H$4 & "'!$G$11:$G$1000"), $E37, INDIRECT("'" & $H$4 & "'!$A$11:$A$1000"), "NESSUNA VENDITA") -> 0 | I37: =SUMIFS(INDIRECT("'" & I$4 & "'!$I$11:$I$1000"), INDIRECT("'" & I$4 & "'!$G$11:$G$1000"), $E37, INDIRECT("'" & I$4 & "'!$A$11:$A$1000"), "NESSUNA VENDITA") -> 0 | J37: =SUMIFS(INDIRECT("'" & J$4 & "'!$I$11:$I$1000"), INDIRECT("'" & J$4 & "'!$G$11:$G$1000"), $E37, INDIRECT("'" & J$4 & "'!$A$11:$A$1000"), "NESSUNA VENDITA") -> 0 | K37: =SUMIFS(INDIRECT("'" & K$4 & "'!$I$11:$I$1000"), INDIRECT("'" & K$4 & "'!$G$11:$G$1000"), $E37, INDIRECT("'" & K$4 & "'!$A$11:$A$1000"), "NESSUNA VENDITA") -> 0 | L37: =SUMIFS(INDIRECT("'" & L$4 & "'!$I$11:$I$1000"), INDIRECT("'" & L$4 & "'!$G$11:$G$1000"), $E37, INDIRECT("'" & L$4 & "'!$A$11:$A$1000"), "NESSUNA VENDITA") -> 0 | M37: =SUMIFS(INDIRECT("'" & M$4 & "'!$I$11:$I$1000"), INDIRECT("'" & M$4 & "'!$G$11:$G$1000"), $E37, INDIRECT("'" & M$4 & "'!$A$11:$A$1000"), "NESSUNA VENDITA") -> 0 | N37: =SUMIFS(INDIRECT("'" & N$4 & "'!$I$11:$I$1000"), INDIRECT("'" & N$4 & "'!$G$11:$G$1000"), $E37, INDIRECT("'" & N$4 & "'!$A$11:$A$1000"), "NESSUNA VENDITA") -> 0 | O37: =SUMIFS(INDIRECT("'" & O$4 & "'!$I$11:$I$1000"), INDIRECT("'" & O$4 & "'!$G$11:$G$1000"), $E37, INDIRECT("'" & O$4 & "'!$A$11:$A$1000"), "NESSUNA VENDITA") -> 0 | P37: =SUMIFS(INDIRECT("'" & P$4 & "'!$I$11:$I$1000"), INDIRECT("'" & P$4 & "'!$G$11:$G$1000"), $E37, INDIRECT("'" & P$4 & "'!$A$11:$A$1000"), "NESSUNA VENDITA") -> 0 | Q37: =SUMIFS(INDIRECT("'" & Q$4 & "'!$I$11:$I$1000"), INDIRECT("'" & Q$4 & "'!$G$11:$G$1000"), $E37, INDIRECT("'" & Q$4 & "'!$A$11:$A$1000"), "NESSUNA VENDITA") -> 0 | R37: =SUM(C37:Q37) -> 0
C38: =SUMIFS('OPPORTUNITA DI VENDITA'!$J$198:$J$1000, 'OPPORTUNITA DI VENDITA'!$H$198:$H$1000, B38, 'OPPORTUNITA DI VENDITA'!$B$198:$B$1000, "NON ESEGUITO") -> 0 | F38: =SUMIFS(INDIRECT("'" & $F$4 & "'!$I$11:$I$1000"), INDIRECT("'" & $F$4 & "'!$G$11:$G$1000"), $E38, INDIRECT("'" & $F$4 & "'!$A$11:$A$1000"), "NESSUNA VENDITA") -> 0 | G38: =SUMIFS(INDIRECT("'" & $G$4 & "'!$I$11:$I$1000"), INDIRECT("'" & $G$4 & "'!$G$11:$G$1000"), $E38, INDIRECT("'" & $G$4 & "'!$A$11:$A$1000"), "NESSUNA VENDITA") -> 0 | H38: =SUMIFS(INDIRECT("'" & $H$4 & "'!$I$11:$I$1000"), INDIRECT("'" & $H$4 & "'!$G$11:$G$1000"), $E38, INDIRECT("'" & $H$4 & "'!$A$11:$A$1000"), "NESSUNA VENDITA") -> 0 | I38: =SUMIFS(INDIRECT("'" & I$4 & "'!$I$11:$I$1000"), INDIRECT("'" & I$4 & "'!$G$11:$G$1000"), $E38, INDIRECT("'" & I$4 & "'!$A$11:$A$1000"), "NESSUNA VENDITA") -> 0 | J38: =SUMIFS(INDIRECT("'" & J$4 & "'!$I$11:$I$1000"), INDIRECT("'" & J$4 & "'!$G$11:$G$1000"), $E38, INDIRECT("'" & J$4 & "'!$A$11:$A$1000"), "NESSUNA VENDITA") -> 0 | K38: =SUMIFS(INDIRECT("'" & K$4 & "'!$I$11:$I$1000"), INDIRECT("'" & K$4 & "'!$G$11:$G$1000"), $E38, INDIRECT("'" & K$4 & "'!$A$11:$A$1000"), "NESSUNA VENDITA") -> 0 | L38: =SUMIFS(INDIRECT("'" & L$4 & "'!$I$11:$I$1000"), INDIRECT("'" & L$4 & "'!$G$11:$G$1000"), $E38, INDIRECT("'" & L$4 & "'!$A$11:$A$1000"), "NESSUNA VENDITA") -> 0 | M38: =SUMIFS(INDIRECT("'" & M$4 & "'!$I$11:$I$1000"), INDIRECT("'" & M$4 & "'!$G$11:$G$1000"), $E38, INDIRECT("'" & M$4 & "'!$A$11:$A$1000"), "NESSUNA VENDITA") -> 0 | N38: =SUMIFS(INDIRECT("'" & N$4 & "'!$I$11:$I$1000"), INDIRECT("'" & N$4 & "'!$G$11:$G$1000"), $E38, INDIRECT("'" & N$4 & "'!$A$11:$A$1000"), "NESSUNA VENDITA") -> 0 | O38: =SUMIFS(INDIRECT("'" & O$4 & "'!$I$11:$I$1000"), INDIRECT("'" & O$4 & "'!$G$11:$G$1000"), $E38, INDIRECT("'" & O$4 & "'!$A$11:$A$1000"), "NESSUNA VENDITA") -> 0 | P38: =SUMIFS(INDIRECT("'" & P$4 & "'!$I$11:$I$1000"), INDIRECT("'" & P$4 & "'!$G$11:$G$1000"), $E38, INDIRECT("'" & P$4 & "'!$A$11:$A$1000"), "NESSUNA VENDITA") -> 0 | Q38: =SUMIFS(INDIRECT("'" & Q$4 & "'!$I$11:$I$1000"), INDIRECT("'" & Q$4 & "'!$G$11:$G$1000"), $E38, INDIRECT("'" & Q$4 & "'!$A$11:$A$1000"), "NESSUNA VENDITA") -> 0 | R38: =SUM(C38:Q38) -> 0
C39: =SUMIFS('OPPORTUNITA DI VENDITA'!$J$198:$J$1000, 'OPPORTUNITA DI VENDITA'!$H$198:$H$1000, B39, 'OPPORTUNITA DI VENDITA'!$B$198:$B$1000, "NON ESEGUITO") -> 0 | F39: =SUMIFS(INDIRECT("'" & $F$4 & "'!$I$11:$I$1000"), INDIRECT("'" & $F$4 & "'!$G$11:$G$1000"), $E39, INDIRECT("'" & $F$4 & "'!$A$11:$A$1000"), "NESSUNA VENDITA") -> 0 | G39: =SUMIFS(INDIRECT("'" & $G$4 & "'!$I$11:$I$1000"), INDIRECT("'" & $G$4 & "'!$G$11:$G$1000"), $E39, INDIRECT("'" & $G$4 & "'!$A$11:$A$1000"), "NESSUNA VENDITA") -> 0 | H39: =SUMIFS(INDIRECT("'" & $H$4 & "'!$I$11:$I$1000"), INDIRECT("'" & $H$4 & "'!$G$11:$G$1000"), $E39, INDIRECT("'" & $H$4 & "'!$A$11:$A$1000"), "NESSUNA VENDITA") -> 0 | I39: =SUMIFS(INDIRECT("'" & I$4 & "'!$I$11:$I$1000"), INDIRECT("'" & I$4 & "'!$G$11:$G$1000"), $E39, INDIRECT("'" & I$4 & "'!$A$11:$A$1000"), "NESSUNA VENDITA") -> 0 | J39: =SUMIFS(INDIRECT("'" & J$4 & "'!$I$11:$I$1000"), INDIRECT("'" & J$4 & "'!$G$11:$G$1000"), $E39, INDIRECT("'" & J$4 & "'!$A$11:$A$1000"), "NESSUNA VENDITA") -> 0 | K39: =SUMIFS(INDIRECT("'" & K$4 & "'!$I$11:$I$1000"), INDIRECT("'" & K$4 & "'!$G$11:$G$1000"), $E39, INDIRECT("'" & K$4 & "'!$A$11:$A$1000"), "NESSUNA VENDITA") -> 0 | L39: =SUMIFS(INDIRECT("'" & L$4 & "'!$I$11:$I$1000"), INDIRECT("'" & L$4 & "'!$G$11:$G$1000"), $E39, INDIRECT("'" & L$4 & "'!$A$11:$A$1000"), "NESSUNA VENDITA") -> 0 | M39: =SUMIFS(INDIRECT("'" & M$4 & "'!$I$11:$I$1000"), INDIRECT("'" & M$4 & "'!$G$11:$G$1000"), $E39, INDIRECT("'" & M$4 & "'!$A$11:$A$1000"), "NESSUNA VENDITA") -> 0 | N39: =SUMIFS(INDIRECT("'" & N$4 & "'!$I$11:$I$1000"), INDIRECT("'" & N$4 & "'!$G$11:$G$1000"), $E39, INDIRECT("'" & N$4 & "'!$A$11:$A$1000"), "NESSUNA VENDITA") -> 0 | O39: =SUMIFS(INDIRECT("'" & O$4 & "'!$I$11:$I$1000"), INDIRECT("'" & O$4 & "'!$G$11:$G$1000"), $E39, INDIRECT("'" & O$4 & "'!$A$11:$A$1000"), "NESSUNA VENDITA") -> 0 | P39: =SUMIFS(INDIRECT("'" & P$4 & "'!$I$11:$I$1000"), INDIRECT("'" & P$4 & "'!$G$11:$G$1000"), $E39, INDIRECT("'" & P$4 & "'!$A$11:$A$1000"), "NESSUNA VENDITA") -> 0 | Q39: =SUMIFS(INDIRECT("'" & Q$4 & "'!$I$11:$I$1000"), INDIRECT("'" & Q$4 & "'!$G$11:$G$1000"), $E39, INDIRECT("'" & Q$4 & "'!$A$11:$A$1000"), "NESSUNA VENDITA") -> 0 | R39: =SUM(C39:Q39) -> 0
B40: Tot.Anno---> | C40: =SUM(C26:C39) -> 0 | E40: Tot.Mese---> | F40: =SUM(F26:F39) -> 62868 | G40: =SUM(G26:G39) -> 75935 | H40: =SUM(H26:H39) -> 52640 | I40: =SUM(I26:I39) -> 116498 | J40: =SUM(J26:J39) -> 39912 | K40: =SUM(K26:K39) -> 0 | L40: =SUM(L26:L39) -> 0 | M40: =SUM(M26:M39) -> 0 | ... R40: =SUM(R26:R39) -> 347853 | S40: <---Tot.Rifiutato Complessivo
O44: Percentuale Generale | Delta
O45: =IFERROR(R19 / (R19 + R40), 0) -> 0.47796627 | P45: =IFERROR(R40 / (R19 + R40), 0) -> 0.52203373
O46: =O45-P45 -> -0.044067461

Sheet OPPORTUNITA DI VENDITA
E1: CLINICA GioDental | F1: VILLA BETANIA
A7: ANNO RIF. | B7: Esito/Stato | C7: Data | D7: Consulente | E7: Paziente | F7: Proveniente | G7: Gender | H7: Assegnazione/Medico | J7: Importo | K7: Importo accettato | L7: Data Vautazione | P7: Anticipo | Q7: Mod.Pagamento | S7: Data App. | T7: NOTE
A9: Anno 2024 | B9: Tot. ANNO | J9: =SUMIF(B10:B99,"ESEGUITO", J10:J1287) -> 0
A100: Anno 2025 | B100: Tot. ANNO | J100: =SUMIF(B101:B196,"ESEGUITO", J101:J1378) -> 0
A197: Anno in corso | B197: Tot. ANNO | J197: =SUMIF(B198:B1485,"ESEGUITO", J198:J1485) -> 36232
B198: ESEGUITO | C198: 46161 | E198: PLACIDI C | F198: URGENZA | G198: F | H198: AMOROSO | J198: 10580 | K198: 2250 | L198: 46161 | R198: CARICO ASSIC-NE
B199: ESEGUITO | C199: 46176 | E199: BAZZUCCHI M | F199: URGENZA | G199: F | H199: AMOROSO | J199: 9808 | K199: 9808 | L199: 46176 | R199: BONIFICO
B200: ESEGUITO | C200: 46183 | E200: DE FRANCESO C | F200: AMPLIAMENTO | G200: M | H200: AMOROSO | J200: 5000 | K200: 5000 | L200: 46183 | R200: PAGODIL
B201: ESEGUITO | C201: 11/0/2026 | E201: CHIAPPONE G | F201: RIVALUTAZIONE | G201: M | H201: MIRACOLO | J201: 5822 | K201: 5822 | L201: 46184 | R201: 3 TRANCHES
B202: ESEGUITO | C202: 46184 | E202: DEL SORDO V | F202: RIVALUTAZIONE | G202: F | H202: MIRACOLO | J202: 5022 | K202: 2258 | L202: 46184

Sheet GENNAIO
D1: CLINICA GioDental | E1: VILLA BETANIA | G1: CONSULENTI COMMERCIALI
J5: OBIETTIVO
I6: Tot. Foglio Mese | L6: =SUMIF(A11:A140,"INZIA IL TRATTAMENTO-VENDITA", I11:I140) -> 35594
I7: Tot. Complessivo | L7: =L6+SUMIFS('OPPORTUNITA DI VENDITA'!J198:J513,'OPPORTUNITA DI VENDITA'!C198:C513, ">=01/01/2026", 'OPPORTUNITA DI VENDITA'!C198:C513, "<=31/01/2026",'OPPORTUNITA DI VENDITA'!B198:B513,"ESEGUITO") -> 35594
A9: Esito/Stato | B9: Data | C9: Consulente | D9: Paziente | E9: Proveniente | F9: Gender | G9: Assegnazione/Medico | I9: Importo | J9: Data Valutazione | N9: Anticipo | O9: Mod.Pagamento | Q9: Data App. | R9: NOTE
A11: NESSUNA VENDITA | B11: 46029 | D11: MAFFEI R | E11: TOTEM | F11: F | G11: DOMENICI | I11: 6718 | J11: 46029 | R11: CI VUOLE PENSARE
A12: NESSUNA VENDITA | B12: 46031 | D12: GORINI F | E12: INTERNET | F12: F | G12: AMOROSO | I12: 4080 | J12: 46031 | R12: CI VUOLE PENSARE STA VALUTANDO VARI PREVENTIVI
A13: NESSUNA VENDITA | B13: 46034 | D13: TENO P | E13: TOTEM | F13: M | G13: DOMENICI | I13: 14220 | J13: 46034 | R13: NON FINANZIABILE DEVE CHIEDERE AL NIPOTE SE FA DA GARANTE
A14: NESSUNA VENDITA | B14: 46034 | D14: MUNGIGUERRA D | E14: PVT DOMENICI | F14: M | G14: DOMENICI | I14: 150 | J14: 46034 | P14: UNICO | Q14: 46048 | R14: ANNULLA L'APPUNTAMENTO E NON RIFISSA
A15: INZIA IL TRATTAMENTO-VENDITA | B15: 46035 | D15: SETTEMBRINI L | E15: HUB SPOKE | F15: M | G15: AMOROSO | I15: 130 | J15: 46035 | P15: UNICO | Q15: 46035
A16: PAZIENTE SANO | B16: 46035 | D16: FORTI F | E16: PVT AMOROSO | F16: M | G16: AMOROSO | J16: 46035
A17: NESSUNA VENDITA | B17: 46036 | D17: RUIA A | E17: PASSAPAROLA | F17: F | G17: AMOROSO | I17: 8910 | J17: 46036
A18: NESSUNA VENDITA | B18: 46036 | D18: VENNERI D | E18: PASSAPAROLA | F18: M | G18: AMOROSO | I18: 3690 | J18: 46036
A19: NESSUNA VENDITA | B19: 46036 | D19: CASTELLANI T | E19: PASSAPAROLA | F19: M | G19: DOMENICI | I19: 5000 | J19: 46036 | R19: parla con il papà per il discorso economico e ci fa sapere
A20: NESSUNA VENDITA | B20: 46037 | D20: PRECIUTTI S | E20: PASSAPAROLA | F20: F | G20: CARDONE | I20: 5800 | J20: 46037 | R20: NON VUOLE FARLO DICE CHE IL COSTO E' TROPPO ALTO
A21: INZIA IL TRATTAMENTO-VENDITA | B21: 46037 | D21: PERROTTA A | E21: DIPENDENTE | F21: F | G21: MARCANTONI | I21: 304 | J21: 46037 | P21: UNICO
A22: PAZIENTE SANO | B22: 46037 | D22: LISI A | E22: PASSAPAROLA | F22: M | G22: MARCANTONI | J22: 46037
A23: INZIA IL TRATTAMENTO-VENDITA | B23: 46038 | D23: SABATINI G | E23: HUB SPOKE | F23: F | G23: AMOROSO | I23: 530 | J23: 46038 | P23: UNICO
A24: INZIA IL TRATTAMENTO-VENDITA | B24: 46042 | D24: SPADONI M | E24: HUB SPOKE | F24: F | G24: AMOROSO | I24: 780 | J24: 46042 | P24: UNICO
A25: NESSUNA VENDITA | B25: 46042 | D25: DI CLEMENTE A | E25: TOTEM | F25: F | G25: AMOROSO | I25: 2200 | J25: 46042
A26: NESSUNA VENDITA | B26: 46044 | D26: COLLINI I | E26: TOTEM | F26: F | G26: MAZZELLI | I26: 240 | J26: 46044 | R26: ABT E COLLETTI - VIENE A FARE CONSULTO ORTO E FISSA APP PER CONSERVATIVA - FATTA RIV ORTO COSTO TROPPO ALTO NON VUOLE FARLO
A27: INZIA IL TRATTAMENTO-VENDITA | B27: 46044 | D27: QUILLARES ALVARADO M | E27: DIPENDENTE | F27: F | G27: MAZZELLI | I27: 3280 | J27: 46044 | P27: PAGODIL
A28: INZIA IL TRATTAMENTO-VENDITA | B28: 46044 | D28: DIAFOUCKA Y | E28: TOTEM | F28: F | G28: MAZZELLI | I28: 12900 | J28: 46044 | P28: ACC. + DILAZIONE | Q28: 46065
A29: NESSUNA VENDITA | B29: 46044 | D29: GARUGLIERI L | E29: CUP | F29: F | G29: MAZZELLI | I29: 4820 | J29: 46044 | R29: pz disoccupata non finanziabile si deve organizzare su come pagare e ci fa sapere
A30: NESSUNA VENDITA | B30: 46049 | D30: GASTALDI E | E30: CUP | F30: M | G30: AMOROSO | J30: 46049 | R30: Pz molto anziano, non vuole fare nulla e non permette il completamento della visita
A31: INZIA IL TRATTAMENTO-VENDITA | B31: 46050 | D31: KOBELIA O | E31: HUB SPOKE | F31: F | G31: AMOROSO | I31: 280 | J31: 46050 | P31: UNICO
A32: INZIA IL TRATTAMENTO-VENDITA | B32: 46050 | D32: DUARTE F | E32: HUB SPOKE | F32: F | G32: AMOROSO | I32: 280 | J32: 46050 | P32: UNICO
A33: INZIA IL TRATTAMENTO-VENDITA | B33: 46050 | D33: DUO' A | E33: HUB SPOKE | F33: F | G33: AMOROSO | I33: 280 | J33: 46050 | P33: UNICO
A34: INZIA IL TRATTAMENTO-VENDITA | B34: 46050 | D34: MANUKIAN A | E34: INTERNATIONAL CARE | F34: M | G34: MASTRIRILLI | I34: 110 | J34: 46050 | P34: UNICO
A35: PAZIENTE SANO | B35: 46050 | D35: SMARRA L | E35: PASSAPAROLA | F35: F | G35: AMOROSO | J35: 46050
A36: INZIA IL TRATTAMENTO-VENDITA | B36: 46050 | D36: BRUNO G | E36: TOTEM | F36: M | G36: DOMENICI | I36: 3285 | J36: 46050 | P36: 2 TRANCHES | Q36: 46057
A37: PAZIENTE SANO | B37: 46050 | D37: GARELLA L | E37: PASSAPAROLA | F37: F | G37: MASTRIRILLI | J37: 46050
A38: INZIA IL TRATTAMENTO-VENDITA | B38: 46051 | D38: DE ANGELIS C | E38: PASSAPAROLA | F38: F | G38: MAZZELLI | I38: 4000 | J38: 46051 | P38: ACC. + DILAZIONE
A39: INZIA IL TRATTAMENTO-VENDITA | B39: 46051 | D39: TREDICI G | E39: INTERNET | F39: M | G39: CARDONE | I39: 4585 | J39: 46051 | P39: ACC. + DILAZIONE
A40: INZIA IL TRATTAMENTO-VENDITA | B40: 46051 | D40: TREDICI D | E40: INTERNET | F40: F | G40: CARDONE | I40: 3200 | J40: 46051 | P40: ACC. + DILAZIONE
A41: INZIA IL TRATTAMENTO-VENDITA | B41: 46051 | D41: ZANNI G | E41: INTERNET | F41: M | G41: MAZZELLI | I41: 1650 | J41: 46051 | P41: 2 TRANCHES
A42: NESSUNA VENDITA | B42: 46051 | D42: PALMA G | E42: PASSAPAROLA | F42: M | G42: MIRACOLO | I42: 5380 | J42: 46051 | R42: parla con la sua assicurazione e ci fa sapere
A43: NESSUNA VENDITA | B43: 46051 | D43: ROSCANI D | E43: PASSAPAROLA | F43: M | G43: MAZZELLI | I43: 1660 | J43: 46051 | R43: CI DEVE PENSARE - non vuole fare il lavoro perché fatto di recente da altro dentista. Torna dal suo dentista per farlo in garanzia
A44: PAZIENTE SANO | B44: 46051 | D44: GUARINI M | E44: CUP | F44: F | G44: MIRACOLO | J44: 46051
A45: PAZIENTE SANO | B45: 46052 | D45: PIERBATTISTA V | E45: PASSAPAROLA | F45: F | G45: GAGLIARDI | J45: 46052
A46: PAZIENTE SANO | B46: 46052 | D46: LAVRENKO S | E46: PASSAPAROLA | F46: F | G46: GAGLIARDI | J46: 46052

Sheet FEBBRAIO
D1: CLINICA GioDental | E1: VILLA BETANIA | G1: CONSULENTI COMMERCIALI
J5: OBIETTIVO
I6: Tot. Foglio Mese | L6: =SUMIF(A11:A139,"INZIA IL TRATTAMENTO-VENDITA", I11:I139) -> 104999
I7: Tot. Complessivo | L7: =L6+SUMIFS('OPPORTUNITA DI VENDITA'!J198:J513,'OPPORTUNITA DI VENDITA'!C198:C513, ">=01/02/2026", 'OPPORTUNITA DI VENDITA'!C198:C513, "<=28/02/2026",'OPPORTUNITA DI VENDITA'!B198:B513,"ESEGUITO") -> 104999
A9: Esito/Stato | B9: Data | C9: Consulente | D9: Paziente | E9: Proveniente | F9: Gender | G9: Assegnazione/Medico | I9: Importo | J9: Data Valutazione | N9: Anticipo | O9: Mod.Pagamento | Q9: Data App. | R9: NOTE
A11: NESSUNA VENDITA | B11: 46055 | D11: MAIONE F | E11: CUP | F11: M | G11: DOMENICI | I11: 5850 | R11: CI VUOLE PENSARE - STA VALUTANDO ALTRI PREVENTIVI
A12: INZIA IL TRATTAMENTO-VENDITA | B12: 46055 | D12: STOIAN C | E12: PASSAPAROLA | F12: F | G12: DOMENICI | I12: 9504 | P12: ACC. + DILAZIONE | Q12: 46062
A13: INZIA IL TRATTAMENTO-VENDITA | B13: 46055 | D13: OFFIDANI R | E13: INTERNET | F13: F | G13: DOMENICI | I13: 325 | P13: CARICO ASSIC-NE | Q13: 46063
A14: NESSUNA VENDITA | B14: 46057 | D14: TATULLI G | E14: DIPENDENTE | F14: F | G14: DOMENICI | I14: 240 | R14: DEVE ESTRARRE 38, VUOLE PRIMA PROVARE CON ANTIBIOTICO - SE IL DOLORE NON LE PASSA VERRA' A FARE L'ESTRAZIONE
A15: PAZIENTE SANO | B15: 46057 | D15: DI TROCCHIO M | E15: PASSAPAROLA | F15: M | G15: MASTRIRILLI
A16: NESSUNA VENDITA | B16: 46057 | D16: BORZI S | E16: PASSAPAROLA | F16: M | G16: DOMENICI | I16: 18000 | R16: non vuole fare il lavoro
A17: NESSUNA VENDITA | B17: 46057 | D17: COGONI M | E17: PASSAPAROLA | F17: F | G17: DOMENICI | I17: 13000 | R17: non vuole fare nulla
A18: INZIA IL TRATTAMENTO-VENDITA | B18: 46057 | D18: DOS SANTOS M | E18: TOTEM | F18: F | G18: DOMENICI | I18: 12000 | P18: DILAZIONATO
A19: INZIA IL TRATTAMENTO-VENDITA | B19: 46058 | D19: LAWNICZAK R | E19: INTERNET | F19: M | G19: MAZZELLI | I19: 6270 | P19: 2 TRANCHES
A20: INZIA IL TRATTAMENTO-VENDITA | B20: 46058 | D20: BONACCI P | E20: PASSAPAROLA | F20: F | G20: MAZZELLI | I20: 648 | P20: UNICO
A21: PAZIENTE SANO | B21: 46058 | D21: PREZIUSO D | E21: PASSAPAROLA | F21: M | G21: MARCANTONI | R21: BOCCA SANA - BIMBO DI 3 ANNI RIMANDATO A CONTROLLO TRA 6 MESI
A22: INZIA IL TRATTAMENTO-VENDITA | B22: 46058 | D22: SPICCIARIELLO S | E22: PASSAPAROLA | F22: F | G22: MARCANTONI | I22: 240 | P22: UNICO
A23: NESSUNA VENDITA | B23: 46062 | D23: CESARI R | E23: DIPENDENTE | F23: F | G23: DOMENICI | I23: 1640 | R23: Deve parlare con il dentista che le ha fatto il precedente lavoro
A24: INZIA IL TRATTAMENTO-VENDITA | B24: 46062 | D24: MASLOWSKI E | E24: PASSAPAROLA | F24: F | G24: DOMENICI | I24: 4585 | P24: PAGODIL
A25: INZIA IL TRATTAMENTO-VENDITA | B25: 46062 | D25: BERARDI C | E25: DIPENDENTE | F25: F | G25: DOMENICI | I25: 480 | P25: 2 TRANCHES | Q25: 46077 | R25: deve estrarre i denti del giudizio inferiori
A26: INZIA IL TRATTAMENTO-VENDITA | B26: 46062 | D26: GIORGI L | E26: PASSAPAROLA | F26: M | G26: DOMENICI | I26: 590 | P26: a PRESTAZIONE | Q26: 46072 | R26: fatto controllo, si rimanda a visita con pedodontista
A27: INZIA IL TRATTAMENTO-VENDITA | B27: 46063 | D27: CIARAMBINO C | E27: HUB SPOKE | F27: F | G27: AMOROSO | I27: 4130 | P27: UNICO
A28: INZIA IL TRATTAMENTO-VENDITA | B28: 46064 | D28: NIGRO P | E28: HUB SPOKE | F28: F | G28: AMOROSO | I28: 880 | P28: UNICO | Q28: 46066
A29: INZIA IL TRATTAMENTO-VENDITA | B29: 46064 | D29: CASTIGLIONE A | E29: PASSAPAROLA | F29: F | G29: DOMENICI | I29: 1601 | P29: CARICO ASSIC-NE | Q29: 46073
A30: INZIA IL TRATTAMENTO-VENDITA | B30: 46065 | D30: ZANATTA A | E30: INTERNET | F30: F | G30: MIRACOLO | I30: 70 | P30: UNICO | R30: Contattati da NH hotel accanto VB per urgenza di un loro cliente
A31: INZIA IL TRATTAMENTO-VENDITA | B31: 46065 | D31: FIORE C | E31: PASSAPAROLA | F31: F | G31: MAZZELLI | I31: 650 | P31: 2 TRANCHES | Q31: 46072 | R31: EXT 18-48 + OTT 47
A32: INZIA IL TRATTAMENTO-VENDITA | B32: 46066 | D32: ONOFREI A | E32: HUB SPOKE | F32: F | G32: AMOROSO | I32: 230 | P32: UNICO
A33: NESSUNA VENDITA | B33: 46069 | D33: MARTINI A | E33: PASSAPAROLA | F33: F | G33: DOMENICI | I33: 1220 | R33: NON VUOLE FARE NULLA
A34: INZIA IL TRATTAMENTO-VENDITA | B34: 46069 | D34: BOTTICELLLI L | E34: PASSAPAROLA | F34: F | G34: DOMENICI | I34: 3490 | P34: ACC. + DILAZIONE | Q34: 46078
A35: NESSUNA VENDITA | B35: 46069 | D35: COLLORAFICI F | E35: PASSAPAROLA | F35: M | G35: DOMENICI | I35: 21425 | R35: TARIFFA MYASSISTANCE - deve sentire la sua assicurazione quanto copre
A36: INZIA IL TRATTAMENTO-VENDITA | B36: 46070 | D36: MARTINO D | E36: HUB SPOKE | F36: M | G36: AMOROSO | I36: 800 | P36: UNICO
A37: INZIA IL TRATTAMENTO-VENDITA | B37: 46070 | D37: SALANDINI M | E37: INTERNET | F37: F | G37: AMOROSO | I37: 500 | P37: UNICO
A38: INZIA IL TRATTAMENTO-VENDITA | B38: 46070 | D38: MARCOLINI M | E38: PASSAPAROLA | F38: M | G38: AMOROSO | I38: 4905 | P38: a PRESTAZIONE | R38: per il momento fa solo ext ed ott, per l'apparecchio ci vuole pensare
A39: INZIA IL TRATTAMENTO-VENDITA | B39: 46070 | D39: IZZO S | E39: HUB SPOKE | F39: M | G39: AMOROSO | I39: 280 | P39: UNICO
A40: NESSUNA VENDITA | B40: 46071 | D40: MORETTI D | E40: DIPENDENTE | F40: F | G40: DOMENICI | I40: 4800 | R40: INVISALIGN - PER IL MOMENTO NON VUOLE FARLO
A41: INZIA IL TRATTAMENTO-VENDITA | B41: 46071 | D41: TOCCI A | E41: HUB SPOKE | F41: M | G41: AMOROSO | I41: 458 | P41: UNICO | Q41: 46168
A42: NESSUNA VENDITA | B42: 46071 | D42: ABENANTE B | E42: TOTEM | F42: M | G42: DOMENICI | I42: 7000 | R42: ci deve riflettere
A43: INZIA IL TRATTAMENTO-VENDITA | B43: 46071 | D43: GABURA A | E43: PVT AMOROSO | F43: M | G43: AMOROSO | I43: 250 | P43: UNICO
A44: INZIA IL TRATTAMENTO-VENDITA | B44: 46071 | D44: SAVIGLIANO G | E44: TOTEM | F44: M | G44: DOMENICI | I44: 3393 | P44: a PRESTAZIONE
A45: NESSUNA VENDITA | B45: 46071 | D45: GENCO C | E45: TOTEM | F45: F | G45: DOMENICI | I45: 2610
A46: INZIA IL TRATTAMENTO-VENDITA | B46: 46071 | D46: COSTANTINI L | E46: HUB SPOKE | F46: M | G46: AMOROSO | I46: 1200 | P46: UNICO
A47: INZIA IL TRATTAMENTO-VENDITA | B47: 46071 | D47: FERRARI F | E47: PASSAPAROLA | F47: F | G47: DOMENICI | I47: 8400 | P47: ACC. + DILAZIONE
A48: INZIA IL TRATTAMENTO-VENDITA | B48: 46071 | D48: TORANO A | E48: PASSAPAROLA | F48: M | G48: DOMENICI | I48: 19000 | P48: ACC. + DILAZIONE
A49: PAZIENTE SANO | B49: 46071 | D49: MONACO F | E49: FAMIGLIA | F49: F | G49: MASTRIRILLI
A50: INZIA IL TRATTAMENTO-VENDITA | B50: 46072 | D50: CATALANO S | E50: TOTEM | F50: F | G50: MAZZELLI | I50: 2750 | P50: CARICO ASSIC-NE
A51: PAZIENTE SANO | B51: 46072 | D51: VINCENZI N | E51: TOTEM | F51: F | G51: MIRACOLO
A52: PAZIENTE SANO | B52: 46072 | D52: KALB S | E52: PASSAPAROLA | F52: M | G52: MARCANTONI
A53: PAZIENTE SANO | B53: 46072 | D53: SUNNY L | E53: TOTEM | F53: M | G53: MARCANTONI
A54: NESSUNA VENDITA | B54: 46076 | D54: DELLO SCHIAVO T | E54: TOTEM | F54: F | G54: INNOCENTE | R54: VISTA IN URGENZA INVIATA A DOMENICI PER COMPLETAMENTO VISITA
A55: RICHIAMERA' / RICHIAMARE | B55: 46077 | D55: AMASIO V | E55: HUB SPOKE | F55: F | G55: AMOROSO | I55: 500 | R55: Pz in stato di gravidanza al settimo mese, faraà le estrazioni dopo aver partorito
A56: INZIA IL TRATTAMENTO-VENDITA | B56: 46077 | D56: DI PAOLA S | E56: PASSAPAROLA | F56: M | G56: AMOROSO | I56: 3357 | P56: 2 TRANCHES
A57: INZIA IL TRATTAMENTO-VENDITA | B57: 46078 | D57: BONDANI A | E57: HUB SPOKE | F57: M | G57: AMOROSO | I57: 73 | P57: UNICO
A58: INZIA IL TRATTAMENTO-VENDITA | B58: 46078 | D58: SUBOTENKO T | E58: PVT AMOROSO | F58: F | G58: AMOROSO | I58: 1900 | P58: 2 TRANCHES
A59: INZIA IL TRATTAMENTO-VENDITA | B59: 46079 | D59: PASSERI G | E59: DIPENDENTE | F59: F | G59: MAZZELLI | I59: 140 | P59: UNICO
A60: INZIA IL TRATTAMENTO-VENDITA | B60: 46079 | D60: SATIRA C | E60: PASSAPAROLA | F60: F | G60: MAZZELLI | I60: 11900 | P60: 3 TRANCHES
A61: NESSUNA VENDITA | B61: 46079 | D61: GIRAFFA M | E61: INTERNET | F61: F | G61: MAZZELLI | I61: 150 | R61: pz non vuole fare opt, dice che preferisce andare al Cristo Re perché più vicino a casa sua

Sheet MARZO
D1: CLINICA GioDental | E1: VILLA BETANIA | G1: CONSULENTI COMMERCIALI
J5: OBIETTIVO
I6: Tot. Foglio Mese | L6: =SUMIF(A11:A140,"INZIA IL TRATTAMENTO-VENDITA", I11:I140) -> 54103
I7: Tot. Complessivo | L7: =L6+SUMIFS('OPPORTUNITA DI VENDITA'!J198:J513,'OPPORTUNITA DI VENDITA'!C198:C513, ">=01/03/2026", 'OPPORTUNITA DI VENDITA'!C198:C513, "<=31/03/2026",'OPPORTUNITA DI VENDITA'!B198:B513,"ESEGUITO") -> 54103
A9: Esito/Stato | B9: Data | C9: Consulente | D9: Paziente | E9: Proveniente | F9: Gender | G9: Assegnazione/Medico | I9: Importo | J9: Data Valutazione | N9: Anticipo | O9: Mod.Pagamento | Q9: Data App. | R9: NOTE
A11: NESSUNA VENDITA | B11: 46084 | D11: MELE M | E11: DIPENDENTE | F11: F | G11: AMOROSO | I11: 7360 | R11: AO4 SUP - PZ NON FINANZIABILE
A12: INZIA IL TRATTAMENTO-VENDITA | B12: 46085 | D12: STIRCU A | E12: HUB SPOKE | F12: F | G12: AMOROSO | I12: 1230 | P12: 2 TRANCHES
A13: NESSUNA VENDITA | B13: 46086 | D13: PERNICE A | E13: FAMIGLIA | F13: M | G13: MIRACOLO | I13: 150 | R13: Ha il suo dentista, voleva solo un secondo parere
A14: INZIA IL TRATTAMENTO-VENDITA | B14: 46086 | D14: NOCENTINI L | E14: PASSAPAROLA | F14: F | G14: CARDONE | I14: 2400 | P14: UNICO
A15: INZIA IL TRATTAMENTO-VENDITA | B15: 46086 | D15: LUPO E | E15: TOTEM | F15: F | G15: MIRACOLO | I15: 1520 | P15: 2 TRANCHES
A16: INZIA IL TRATTAMENTO-VENDITA | B16: 46090 | D16: GALAZKA A | E16: PASSAPAROLA | F16: F | G16: DOMENICI | I16: 1478 | P16: a PRESTAZIONE
A17: NESSUNA VENDITA | B17: 46091 | D17: DE VITA D | E17: HUB SPOKE | F17: F | G17: AMOROSO | I17: 2030 | R17: si deve organizzare e ci farà sapere
A18: INZIA IL TRATTAMENTO-VENDITA | B18: 46091 | D18: SCATOLINI S | E18: HUB SPOKE | F18: M | G18: AMOROSO | I18: 230 | P18: UNICO
A19: INZIA IL TRATTAMENTO-VENDITA | B19: 46091 | D19: RINALDI S | E19: FAMIGLIA | F19: F | G19: AMOROSO | I19: 6500 | P19: 2 TRANCHES
A20: INZIA IL TRATTAMENTO-VENDITA | B20: 46091 | D20: CARICE G | E20: FAMIGLIA | F20: F | G20: AMOROSO | I20: 100 | P20: UNICO
A21: INZIA IL TRATTAMENTO-VENDITA | B21: 46091 | D21: PALOMBI D | E21: HUB SPOKE | F21: F | G21: AMOROSO | I21: 280 | P21: UNICO
A22: NESSUNA VENDITA | B22: 46092 | D22: DI BIAGGIO S | E22: INTERNET | F22: F | G22: MASTRIRILLI | I22: 975 | R22: Si organizza con il lavoro e ci fa sapere
A23: PAZIENTE SANO | B23: 46092 | D23: ARDITI D | E23: PASSAPAROLA | F23: F | G23: MASTRIRILLI
A24: INZIA IL TRATTAMENTO-VENDITA | B24: 46092 | D24: DE FACENDIS L | E24: PASSAPAROLA | F24: F | G24: DOMENICI | I24: 453 | P24: UNICO
A25: INZIA IL TRATTAMENTO-VENDITA | B25: 46093 | D25: SAVINO V | E25: TOTEM | F25: M | G25: MAZZELLI | I25: 5100 | P25: 2 TRANCHES
A26: INZIA IL TRATTAMENTO-VENDITA | B26: 46093 | D26: REINA G | E26: PASSAPAROLA | F26: M | G26: MIRACOLO | I26: 8730 | P26: CARICO ASSIC-NE
A27: INZIA IL TRATTAMENTO-VENDITA | B27: 46094 | D27: TANCIONI R | E27: FAMIGLIA | F27: M | G27: AMOROSO | I27: 250 | P27: UNICO
A28: PAZIENTE SANO | B28: 46094 | D28: SCHIPPER T | E28: INTERNET | F28: M | G28: AMOROSO | R28: PZ INTERNATIONAL CARE
A29: INZIA IL TRATTAMENTO-VENDITA | B29: 46094 | D29: GERARDI C | E29: HUB SPOKE | F29: M | G29: AMOROSO | I29: 630 | P29: PAGODIL
A30: INZIA IL TRATTAMENTO-VENDITA | B30: 46094 | D30: TREBISONDI G | E30: HUB SPOKE | F30: M | G30: AMOROSO | I30: 1430 | P30: PAGODIL
A31: NESSUNA VENDITA | B31: 46094 | D31: DAMIA L | E31: TOTEM | F31: M | G31: AMOROSO | I31: 3960 | R31: ci pesna - non vuole fare nulla
A32: PAZIENTE SANO | B32: 46094 | D32: DUARTE A | E32: TOTEM | F32: F | G32: AMOROSO
A33: NESSUNA VENDITA | B33: 46097 | D33: CORINALDESI L | E33: INTERNET | F33: F | G33: DOMENICI | I33: 720 | R33: Si attende risposta da parte dell'assicurazione - L'ASSICURAZIONE NON LE COPRE LE SPESE
A34: INZIA IL TRATTAMENTO-VENDITA | B34: 46098 | D34: CORSINI SCORPIONI A | E34: HUB SPOKE | F34: F | G34: AMOROSO | I34: 830 | P34: 2 TRANCHES
A35: INZIA IL TRATTAMENTO-VENDITA | B35: 46098 | D35: BELLUMORI U | E35: PASSAPAROLA | F35: M | G35: AMOROSO | I35: 1700 | P35: 2 TRANCHES
A36: NESSUNA VENDITA | B36: 46098 | D36: PETTINARI M | E36: HUB SPOKE | F36: F | G36: AMOROSO | I36: 780 | R36: deve rimuovere 3 impianti ma rimarrebbe senza denti nell'arcata sup, parla con il dentista che l'ha mandata qui per farsi fare una protesi totale prima della rimozione degli impianti e ci farà sapere quando procedere con l'intervento
A37: INZIA IL TRATTAMENTO-VENDITA | B37: 46098 | D37: AMARA A | E37: HUB SPOKE | F37: F | G37: AMOROSO | I37: 206 | P37: UNICO
A38: INZIA IL TRATTAMENTO-VENDITA | B38: 46099 | D38: PANELLA F | E38: HUB SPOKE | F38: F | G38: AMOROSO | I38: 830 | P38: UNICO
A39: INZIA IL TRATTAMENTO-VENDITA | B39: 46099 | D39: FINOCCHIARO A | E39: DIPENDENTE | F39: M | G39: DOMENICI | I39: 224 | P39: UNICO
A40: NESSUNA VENDITA | B40: 46100 | D40: DASCOLA F | E40: INTERNET | F40: M | G40: MAZZELLI | I40: 4355 | P40: CARICO ASSIC-NE | R40: Attende risposta dalla sua assicurazione (MyAssistance) e ci fa sapere
A41: NESSUNA VENDITA | B41: 46100 | D41: TROIA P | E41: TOTEM | F41: F | G41: MIRACOLO | I41: 831
A42: NESSUNA VENDITA | B42: 46100 | D42: BARONE M | E42: TOTEM | F42: M | G42: MIRACOLO | I42: 4800 | R42: ci riflette - per il momento vuole fare solo l'otturazione
A43: NESSUNA VENDITA | B43: 46102 | D43: NAPOLITANO E | E43: DIPENDENTE | F43: M | G43: MARCANTONI | I43: 192 | R43: La mamma è dipendente VB, si organizza con i turni e ci chiama per fissare app ad Aprile - ANNULLA E' STATO VISTO DA UN ALTRO DENTISTA CHE GLI HA DETTO CHE LA CARIE NON C'E
A44: INZIA IL TRATTAMENTO-VENDITA | B44: 46102 | D44: ROSUELO G | E44: TOTEM | F44: M | G44: CARDONE | I44: 4400 | P44: DILAZIONATO
A45: NESSUNA VENDITA | B45: 46102 | D45: TIRABASSI A | E45: FAMIGLIA | F45: M | G45: MARCANTONI | I45: 70
A46: INZIA IL TRATTAMENTO-VENDITA | B46: 46102 | D46: FRISONI R | E46: DIPENDENTE | F46: M | G46: MARCANTONI | I46: 224 | P46: a PRESTAZIONE
A47: NESSUNA VENDITA | B47: 46102 | D47: ROMEI E | E47: INTERNET | F47: M | G47: MARCANTONI | I47: 950 | R47: Annulla l'appuntamento per inizio cure e non rifissa
A48: NESSUNA VENDITA | B48: 46102 | D48: ARISTOTILE F | E48: DIPENDENTE | F48: M | G48: CARDONE | I48: 1470 | R48: Deve chiedere alla sua assicurazione se ha rimborso
A49: NESSUNA VENDITA | B49: 46102 | D49: ARISTOTILE L | E49: DIPENDENTE | F49: M | G49: CARDONE | I49: 5320 | R49: Deve chiedere alla sua assicurazione se ha rimborso
A50: INZIA IL TRATTAMENTO-VENDITA | B50: 46102 | D50: PERROTTA L | E50: DIPENDENTE | F50: M | G50: MARCANTONI | I50: 112 | P50: UNICO
A51: INZIA IL TRATTAMENTO-VENDITA | B51: 46102 | D51: MASCIA G | E51: PASSAPAROLA | F51: F | G51: MARCANTONI | I51: 56 | P51: UNICO
A52: INZIA IL TRATTAMENTO-VENDITA | B52: 46102 | D52: GALASSO M | E52: INTERNET | F52: F | G52: CARDONE | I52: 4720 | P52: PAGODIL
A53: PAZIENTE SANO | B53: 46102 | D53: GALASSO E | E53: INTERNET | F53: M | G53: CARDONE
A54: NESSUNA VENDITA | B54: 46104 | D54: CANDIDO O | E54: DIPENDENTE | F54: F | G54: DOMENICI | I54: 1352 | R54: Si deve organizzare con i turni e chiamerà per fissare app
A55: INZIA IL TRATTAMENTO-VENDITA | B55: 46104 | D55: VOLCHOK N | E55: PASSAPAROLA | F55: F | G55: INNOCENTE | I55: 770 | P55: UNICO
A56: NESSUNA VENDITA | B56: 46105 | D56: MUZZI L | E56: FAMIGLIA | F56: F | G56: AMOROSO | I56: 500
A57: INZIA IL TRATTAMENTO-VENDITA | B57: 46106 | D57: CICGLIANA S | E57: INTERNET | F57: F | G57: AMOROSO | I57: 4740 | P57: 2 TRANCHES
A58: NESSUNA VENDITA | B58: 46106 | D58: RANALDI E | E58: PASSAPAROLA | F58: F | G58: AMOROSO | I58: 4500 | R58: Non lo farà, la mamma non vuole
A59: INZIA IL TRATTAMENTO-VENDITA | B59: 46107 | D59: GUASTELLA F | E59: PASSAPAROLA | F59: M | G59: MAZZELLI | I59: 2800 | P59: 3 TRANCHES
A60: INZIA IL TRATTAMENTO-VENDITA | B60: 46108 | D60: MEDROS A | E60: HUB SPOKE | F60: F | G60: AMOROSO | I60: 1030 | P60: UNICO
A61: NESSUNA VENDITA | B61: 46112 | D61: SALVATORI C | E61: PASSAPAROLA | F61: F | G61: AMOROSO | I61: 4600 | R61: Ci riflette - NON VUOLE FARE L'APPARECCHIO
A62: NESSUNA VENDITA | B62: 46112 | D62: CRUCIANI M | E62: TOTEM | F62: M | G62: AMOROSO | I62: 7400
A63: NESSUNA VENDITA | B63: 46112 | D63: BAGHI J | E63: PASSAPAROLA | F63: F | G63: AMOROSO | I63: 1300 | R63: ext 4 ottavi - si organizza con il lavoro e fissa app
A64: INZIA IL TRATTAMENTO-VENDITA | B64: 46112 | D64: CENTURIONI M | E64: HUB SPOKE | F64: F | G64: AMOROSO | I64: 1130 | P64: UNICO

Sheet APRILE
D1: CLINICA GioDental | E1: VILLA BETANIA | G1: CONSULENTI COMMERCIALI
J5: OBIETTIVO
I6: Tot. Foglio Mese | L6: =SUMIF(A11:A140,"INZIA IL TRATTAMENTO-VENDITA", I11:I140) -> 23735
I7: Tot. Complessivo | L7: =L6+SUMIFS('OPPORTUNITA DI VENDITA'!J198:J513,'OPPORTUNITA DI VENDITA'!C198:C513, ">=01/04/2026", 'OPPORTUNITA DI VENDITA'!C198:C513, "<=30/04/2026",'OPPORTUNITA DI VENDITA'!B198:B513,"ESEGUITO") -> 23735
A9: Esito/Stato | B9: Data | C9: Consulente | D9: Paziente | E9: Proveniente | F9: Gender | G9: Assegnazione/Medico | I9: Importo | J9: Data Valutazione | N9: Anticipo | O9: Mod.Pagamento | Q9: Data App. | R9: NOTE
A11: INZIA IL TRATTAMENTO-VENDITA | B11: 46113 | D11: JOSEPH MYLADOOR N | E11: CUP | F11: F | G11: MASTRORILLI | I11: 90 | P11: UNICO
A12: NESSUNA VENDITA | B12: 46113 | D12: AGOSTINI M | E12: CUP | F12: F | G12: AMOROSO | I12: 4410 | R12: Deve avere autorizzazione dal fondo assicurativo
A13: NESSUNA VENDITA | B13: 46113 | D13: PINTRIJEL M | E13: DIPENDENTE | F13: M | G13: AMOROSO | I13: 2000
A14: INZIA IL TRATTAMENTO-VENDITA | B14: 46113 | D14: SY J | E14: CUP | F14: F | G14: MASTRORILLI | I14: 351 | P14: 2 TRANCHES
A15: PAZIENTE SANO | B15: 46113 | D15: JANISZEWSKI U | E15: CUP | F15: F | G15: AMOROSO
A16: NESSUNA VENDITA | B16: 46113 | D16: AMBROSETTI S | E16: FAMIGLIA | F16: F | G16: DOMENICI | I16: 250 | R16: pz edentula prende bifosfonati, ha protesi mobile che va ribasata
A17: NESSUNA VENDITA | B17: 46113 | D17: FORASTIERI D | E17: PASSAPAROLA | F17: F | G17: DOMENICI | I17: 500 | R17: Si organizza con il lavoro e ci chiama per fissare app - chiama per dire che non vuole fare nulla
A18: PAZIENTE SANO | B18: 46114 | D18: BELLOTTO B | E18: INTERNET | F18: F | G18: MAZZELLI
A19: NESSUNA VENDITA | B19: 46114 | D19: COLETTI R | E19: FAMIGLIA | F19: M | G19: MIRACOLO | I19: 7900 | R19: non vuole fare nulla
A20: NESSUNA VENDITA | B20: 46120 | D20: TANNI S | E20: TOTEM | F20: M | G20: AMOROSO | I20: 3195 | R20: non vuole fare nulla
A21: INZIA IL TRATTAMENTO-VENDITA | B21: 46120 | D21: GIACOMODONATO M | E21: HUB SPOKE | F21: M | G21: AMOROSO | I21: 630 | P21: UNICO
A22: PAZIENTE SANO | B22: 46120 | D22: MANCINI G | E22: PVT AMOROSO | F22: F | G22: AMOROSO
A23: INZIA IL TRATTAMENTO-VENDITA | B23: 46120 | D23: SANTORO I | E23: HUB SPOKE | F23: F | G23: AMOROSO | I23: 530 | P23: UNICO
A24: NESSUNA VENDITA | B24: 46120 | D24: GROCEANU COLTEA A | E24: TOTEM | F24: M | G24: MASTRORILLI | I24: 6500 | R24: non finanziabile, ci pensa e ci fa sapere
A25: NESSUNA VENDITA | B25: 46120 | D25: LUJAN VELASQUE K | E25: FAMIGLIA | F25: F | G25: AMOROSO | I25: 3900 | R25: Non finanziabile, prova a trovare un garante e ci fa sapere
A26: NESSUNA VENDITA | B26: 46121 | D26: LOMBARDI B | E26: TOTEM | F26: M | G26: MAZZELLI | I26: 9522 | R26: VIVE A SALERNO
A27: NESSUNA VENDITA | B27: 46121 | D27: MESCHINI A | E27: TOTEM | F27: M | G27: CARDONE | I27: 5400 | R27: accompagnato dalla mamma, deve chiedere consenso al papà in quanto genitori separati
A28: INZIA IL TRATTAMENTO-VENDITA | B28: 46121 | D28: GIRELLI G | E28: PASSAPAROLA | F28: F | G28: MAZZELLI | I28: 395 | P28: a PRESTAZIONE
A29: NESSUNA VENDITA | B29: 46125 | D29: GARGANI T | E29: PASSAPAROLA | F29: M | G29: DOMENICI | I29: 5670 | R29: Pz non finanziabile, non è passato il pagodil, parla con la mamma per fare da garante
A30: NESSUNA VENDITA | B30: 46125 | D30: GARGANI G | E30: PASSAPAROLA | F30: F | G30: DOMENICI | I30: 11061 | R30: Pz non finanziabile, non è passato il pagodil, parla con la mamma per fare da garante
A31: RICHIAMERA' / RICHIAMARE | B31: 46125 | D31: ROMANELLI G | E31: FAMIGLIA | F31: F | G31: DOMENICI | I31: 3690 | R31: PREV PER INVISALING - VUOLE INIZIARE A SETTEMBRE
A32: INZIA IL TRATTAMENTO-VENDITA | B32: 46126 | D32: MONTECOLLI L | E32: PVT AMOROSO | F32: F | G32: AMOROSO | I32: 1900 | P32: a PRESTAZIONE
A33: INZIA IL TRATTAMENTO-VENDITA | B33: 46126 | D33: DE VENUTI C | E33: HUB SPOKE | F33: F | G33: AMOROSO | I33: 1480 | P33: a PRESTAZIONE
A34: INZIA IL TRATTAMENTO-VENDITA | B34: 46127 | D34: BALDI M | E34: HUB SPOKE | F34: M | G34: AMOROSO | I34: 280 | P34: UNICO
A35: NESSUNA VENDITA | B35: 46127 | D35: GORINI L | E35: HUB SPOKE | F35: F | G35: AMOROSO | I35: 1230 | R35: Annulla l'appuntamento del 29/04 e non rifissa
A36: INZIA IL TRATTAMENTO-VENDITA | B36: 46127 | D36: CACACE R | E36: PASSAPAROLA | F36: F | G36: AMOROSO | I36: 5300 | P36: ACC. + DILAZIONE
A37: INZIA IL TRATTAMENTO-VENDITA | B37: 46127 | D37: ANTONELLI L | E37: PVT AMOROSO | F37: M | G37: AMOROSO | I37: 5000 | P37: 2 TRANCHES
A38: PAZIENTE SANO | B38: 46127 | D38: ANTONELLI E | E38: PVT AMOROSO | F38: F | G38: AMOROSO
A39: PAZIENTE SANO | B39: 46127 | D39: D'AMBROSIO D | E39: FAMIGLIA | F39: M | G39: DOMENICI
A40: NESSUNA VENDITA | B40: 46127 | D40: NEGRI A | E40: DIPENDENTE | F40: F | G40: AMOROSO | I40: 3820 | R40: CI RIFLETTE
A41: INZIA IL TRATTAMENTO-VENDITA | B41: 46127 | D41: D'ELIA F | E41: PASSAPAROLA | F41: F | G41: MASTRORILLI | I41: 318 | P41: UNICO
A42: NESSUNA VENDITA | B42: 46128 | D42: CASINI A | E42: PASSAPAROLA | F42: M | G42: MAZZELLI | I42: 33669 | R42: Ci deve riflettere, preventivo molto alto, proposto anche step alternativo, per il momento non accetta
A43: INZIA IL TRATTAMENTO-VENDITA | B43: 46128 | D43: RICCI M | E43: INTERNET | F43: F | G43: MAZZELLI | I43: 660 | P43: CARICO ASSIC-NE
A44: PAZIENTE SANO | B44: 46128 | D44: CATALANO J | E44: INTERNET | F44: F | G44: MAZZELLI
A45: INZIA IL TRATTAMENTO-VENDITA | B45: 46130 | D45: SALVEMME G | E45: SOCIAL | F45: M | G45: DOMENICI | I45: 80 | P45: CARICO ASSIC-NE
A46: NESSUNA VENDITA | B46: 46130 | D46: BILOTTI L | E46: SOCIAL | F46: M | G46: DOMENICI | I46: 425
A47: NESSUNA VENDITA | B47: 46130 | D47: GIUNTA T | E47: SOCIAL | F47: M | G47: DOMENICI | I47: 3527
A48: NESSUNA VENDITA | B48: 46130 | D48: ANNICCHIARO L | E48: SOCIAL | F48: M | G48: CARDONE | I48: 4000
A49: PAZIENTE SANO | B49: 46132 | D49: CUCCARO E | E49: TOTEM | F49: F | G49: DOMENICI
A50: PAZIENTE SANO | B50: 46133 | D50: RUTILI M | E50: TOTEM | F50: F | G50: AMOROSO
A51: INZIA IL TRATTAMENTO-VENDITA | B51: 46133 | D51: GONZALEZ TORRES J | E51: PVT AMOROSO | F51: M | G51: AMOROSO | I51: 100 | P51: UNICO
A52: INZIA IL TRATTAMENTO-VENDITA | B52: 46133 | D52: BENFATTI D | E52: HUB SPOKE | F52: M | G52: AMOROSO | I52: 1530 | P52: PAGODIL
A53: PAZIENTE SANO | B53: 46134 | D53: STIRPE J | E53: DI PASSAGGIO | F53: M | G53: DOMENICI
A54: NESSUNA VENDITA | B54: 46134 | D54: SCARANO A | E54: DIPENDENTE | F54: F | G54: DOMENICI | I54: 640
A55: NESSUNA VENDITA | B55: 46134 | D55: CIUFOLETTI CL | E55: TOTEM | F55: F | G55: DOMENICI | I55: 1500
A56: INZIA IL TRATTAMENTO-VENDITA | B56: 46134 | D56: CIUFOLETTI CR | E56: TOTEM | F56: F | G56: DOMENICI | I56: 440 | P56: a PRESTAZIONE
A57: NESSUNA VENDITA | B57: 46135 | D57: ZAKI H | E57: TOTEM | F57: M | G57: MAZZELLI | I57: 2430 | R57: PZ NON FINANZIABILE
A58: INZIA IL TRATTAMENTO-VENDITA | B58: 46135 | D58: D'AMBROSIO G | E58: FAMIGLIA | F58: M | G58: CARDONE | I58: 2921 | P58: CARICO ASSIC-NE
A59: INZIA IL TRATTAMENTO-VENDITA | B59: 46135 | D59: D'AMBROSIO A | E59: FAMIGLIA | F59: F | G59: CARDONE | I59: 1270 | P59: CARICO ASSIC-NE
A60: INZIA IL TRATTAMENTO-VENDITA | B60: 46140 | D60: NIKOLOVA M | E60: HUB SPOKE | F60: F | G60: AMOROSO | I60: 180 | P60: UNICO
A61: INZIA IL TRATTAMENTO-VENDITA | B61: 46141 | D61: ANGELINI M | E61: HUB SPOKE | F61: F | G61: AMOROSO | I61: 280 | P61: UNICO
A62: NESSUNA VENDITA | B62: 46141 | D62: GIRELLI G | E62: PASSAPAROLA | F62: M | G62: DOMENICI | I62: 4949

Sheet MAGGIO
D1: CLINICA GioDental | E1: VILLA BETANIA | G1: CONSULENTI COMMERCIALI
J5: OBIETTIVO
I6: Tot. Foglio Mese | L6: =SUMIF(A11:A143,"INZIA IL TRATTAMENTO-VENDITA", I11:I143) -> 48870
I7: Tot. Complessivo | L7: =L6+SUMIFS('OPPORTUNITA DI VENDITA'!J198:J513,'OPPORTUNITA DI VENDITA'!C198:C513, ">=01/05/2026", 'OPPORTUNITA DI VENDITA'!C198:C513, "<=31/05/2026",'OPPORTUNITA DI VENDITA'!B198:B513,"ESEGUITO") -> 59450
A9: Esito/Stato | B9: Data | C9: Consulente | D9: Paziente | E9: Proveniente | F9: Gender | G9: Assegnazione/Medico | I9: Importo | J9: Data Valutazione | N9: Anticipo | O9: Mod.Pagamento | Q9: Data App. | R9: NOTE
A11: INZIA IL TRATTAMENTO-VENDITA | B11: 46147 | D11: MONGELLI R | E11: PVT AMOROSO | F11: F | G11: AMOROSO | I11: 800 | P11: UNICO
A12: INZIA IL TRATTAMENTO-VENDITA | B12: 46147 | D12: ROSSETTI D | E12: DIPENDENTE | F12: M | G12: AMOROSO | I12: 80 | P12: UNICO
A13: INZIA IL TRATTAMENTO-VENDITA | B13: 46147 | D13: TUDOR E | E13: HUB SPOKE | F13: F | G13: AMOROSO | I13: 330 | P13: UNICO
A14: RICHIAMERA' / RICHIAMARE | B14: 46148 | D14: CONCATO A | E14: PVT AMOROSO | F14: F | G14: AMOROSO | I14: 9810
A15: INZIA IL TRATTAMENTO-VENDITA | B15: 46148 | D15: CASTAGNA M | E15: PASSAPAROLA | F15: F | G15: DOMENICI | I15: 380 | P15: a PRESTAZIONE
A16: PAZIENTE SANO | B16: 46148 | D16: BAUDAZZI E | E16: PVT AMOROSO | F16: M | G16: AMOROSO
A17: PAZIENTE SANO | B17: 46148 | D17: CAVARICCI M | E17: PVT AMOROSO | F17: F | G17: AMOROSO
A18: INZIA IL TRATTAMENTO-VENDITA | B18: 46149 | D18: PETROZZIELLO C | E18: TOTEM | F18: F | G18: MIRACOLO | I18: 1781
A19: RICHIAMERA' / RICHIAMARE | B19: 46149 | D19: CASTILLO M | E19: TOTEM | F19: F | G19: MAZZELLI | I19: 6400
A20: NESSUNA VENDITA | B20: 07/05/0206 | D20: DIAFOUKA G | E20: DI PASSAGGIO | F20: M | G20: MAZZELLI | I20: 2000
A21: RICHIAMERA' / RICHIAMARE | B21: 46149 | D21: SPANO' M | E21: PASSAPAROLA | F21: F | G21: MAZZELLI | I21: 5000
A22: INZIA IL TRATTAMENTO-VENDITA | B22: 46149 | D22: KULYK OK | E22: DIPENDENTE | F22: F | G22: MAZZELLI | I22: 3576 | P22: PAGODIL
A23: INZIA IL TRATTAMENTO-VENDITA | B23: 46149 | D23: NATALUCCI T | E23: PASSAPAROLA | F23: M | G23: MAZZELLI | I23: 4685 | P23: DILAZIONATO
A24: NESSUNA VENDITA | B24: 46153 | D24: GOMEZ ROSAS O | E24: TOTEM | F24: F | G24: DOMENICI | I24: 22356
A25: INZIA IL TRATTAMENTO-VENDITA | B25: 46154 | D25: FOSSATI A | E25: PVT FLORIO | F25: M | G25: FLORIO | I25: 250 | P25: UNICO
A26: INZIA IL TRATTAMENTO-VENDITA | B26: 46154 | D26: KULYK OL | E26: DIPENDENTE | F26: F | G26: FLORIO | I26: 4764 | P26: PAGODIL
A27: NESSUNA VENDITA | B27: 46154 | D27: MBAIHORNOM J | E27: CUP | F27: M | G27: FLORIO | I27: 200
A28: INZIA IL TRATTAMENTO-VENDITA | B28: 46154 | D28: MILONE G | E28: PASSAPAROLA | F28: F | G28: AMOROSO | I28: 1400 | P28: BONIFICO
A29: INZIA IL TRATTAMENTO-VENDITA | B29: 46155 | D29: SPURIO T | E29: PASSAPAROLA | F29: M | G29: AMOROSO | I29: 1000 | P29: PAGODIL
A30: NESSUNA VENDITA | B30: 46155 | D30: ROSSETTI S | E30: DIPENDENTE | F30: F | G30: AMOROSO | I30: 5200
A31: INZIA IL TRATTAMENTO-VENDITA | B31: 46155 | D31: PEDICO A | E31: TOTEM | F31: F | G31: MASTRORILLI | I31: 100 | P31: UNICO
A32: PAZIENTE SANO | B32: 46155 | D32: WOJCIK A | E32: HUB SPOKE | F32: F | G32: AMOROSO
A33: RICHIAMERA' / RICHIAMARE | B33: 46155 | D33: ELEUTERI A | E33: TOTEM | F33: M | G33: AMOROSO | I33: 4026
A34: PAZIENTE SANO | B34: 46155 | D34: FRANCESCONI G | E34: PVT AMOROSO | F34: F | G34: AMOROSO
A35: RICHIAMERA' / RICHIAMARE | B35: 46155 | D35: KUCHER S | E35: PASSAPAROLA | F35: F | G35: DOMENICI | I35: 2920
A36: INZIA IL TRATTAMENTO-VENDITA | B36: 46156 | D36: COLLARO R | E36: FAMIGLIA | F36: M | G36: MARCANTONI | I36: 205 | P36: CARICO ASSIC-NE
A37: INZIA IL TRATTAMENTO-VENDITA | B37: 46156 | D37: LORENZETTI F | E37: INTERNET | F37: F | G37: MIRACOLO | I37: 322 | P37: CARICO ASSIC-NE
A38: INZIA IL TRATTAMENTO-VENDITA | B38: 46157 | D38: MONETA V | E38: HUB SPOKE | F38: F | G38: AMOROSO | I38: 1330 | P38: BONIFICO
A39: NESSUNA VENDITA | B39: 46157 | D39: RANAWEERA ARACHCHILAGE T | E39: TOTEM | F39: M | G39: AMOROSO | I39: 1296
A40: NESSUNA VENDITA | B40: 46157 | D40: ROCHA T | E40: TOTEM | F40: F | G40: AMOROSO | I40: 1860
A41: INZIA IL TRATTAMENTO-VENDITA | B41: 46161 | D41: DE LEO A | E41: PVT AMOROSO | F41: F | G41: AMOROSO | I41: 5790
A42: INZIA IL TRATTAMENTO-VENDITA | B42: 46161 | D42: TERROSI S | E42: PVT FLORIO | F42: M | G42: FLORIO | I42: 340 | P42: a PRESTAZIONE
A43: INZIA IL TRATTAMENTO-VENDITA | B43: 46161 | D43: PITORRI M | E43: PVT FLORIO | F43: F | G43: FLORIO | I43: 520 | P43: a PRESTAZIONE
A44: INZIA IL TRATTAMENTO-VENDITA | B44: 46161 | D44: FERRI F | E44: HUB SPOKE | F44: F | G44: AMOROSO | I44: 330 | P44: UNICO
A45: PAZIENTE SANO | B45: 46161 | D45: MACCHINI P | E45: CUP | F45: F | G45: AMOROSO
A46: NESSUNA VENDITA | B46: 46161 | D46: CANTINI A | E46: PASSAPAROLA | F46: M | G46: AMOROSO | I46: 7200 | R46: Pz non finanziabile, non può fare il lavoro
A47: INZIA IL TRATTAMENTO-VENDITA | B47: 46162 | D47: D'ELIA S | E47: HUB SPOKE | F47: M | G47: AMOROSO | I47: 230 | P47: UNICO
A48: INZIA IL TRATTAMENTO-VENDITA | B48: 46162 | D48: MELUZIO P | E48: DIPENDENTE | F48: F | G48: DOMENICI | I48: 2656 | P48: PAGODIL
A49: INZIA IL TRATTAMENTO-VENDITA | B49: 46162 | D49: BAZZUCCHI M | E49: FAMIGLIA | F49: F | G49: AMOROSO | I49: 1030 | P49: UNICO
A50: PAZIENTE SANO | B50: 46162 | D50: MARI V | E50: INTERNET | F50: F | G50: AMOROSO
A51: INZIA IL TRATTAMENTO-VENDITA | B51: 46162 | D51: SAMPIERI | E51: PVT AMOROSO | F51: F | G51: AMOROSO | I51: 50
A52: RICHIAMERA' / RICHIAMARE | B52: 46163 | D52: VANINI V | E52: TOTEM | F52: F | G52: MIRACOLO | I52: 9657
A53: INZIA IL TRATTAMENTO-VENDITA | B53: 46167 | D53: PISCOPO C | E53: TOTEM | F53: F | G53: DOMENICI | I53: 1951 | P53: PAGODIL
A54: INZIA IL TRATTAMENTO-VENDITA | B54: 46168 | D54: LEPRE P | E54: PVT FLORIO | F54: F | G54: FLORIO | I54: 3780 | P54: a PRESTAZIONE
A55: PAZIENTE SANO | B55: 46168 | D55: APA E | E55: HUB SPOKE | F55: M | G55: AMOROSO
A56: INZIA IL TRATTAMENTO-VENDITA | B56: 46169 | D56: MONTEDURO M | E56: PASSAPAROLA | F56: M | G56: DOMENICI | I56: 650 | P56: BONIFICO
A57: INZIA IL TRATTAMENTO-VENDITA | B57: 46169 | D57: ROSCI B | E57: PASSAPAROLA | F57: F | G57: AMOROSO | I57: 640 | P57: UNICO
A58: INZIA IL TRATTAMENTO-VENDITA | B58: 46170 | D58: BROCANI M | E58: PVT MAZZELLI | F58: M | G58: MAZZELLI | I58: 7300 | P58: PAGODIL
A59: INZIA IL TRATTAMENTO-VENDITA | B59: 46170 | D59: VANNOZZI V | E59: PASSAPAROLA | F59: F | G59: MAZZELLI | I59: 1440 | P59: PAGODIL
A60: RICHIAMERA' / RICHIAMARE | B60: 46170 | D60: CECCHINI E | E60: TOTEM | F60: F | G60: MIRACOLO | I60: 2890
A61: RICHIAMERA' / RICHIAMARE | B61: 46171 | D61: VIGLIETTI E | E61: TOTEM | F61: M | G61: AMOROSO | I61: 1791
A62: INZIA IL TRATTAMENTO-VENDITA | B62: 46171 | D62: GIORGETTI A | E62: HUB SPOKE | F62: F | G62: AMOROSO | I62: 830
A63: INZIA IL TRATTAMENTO-VENDITA | B63: 46171 | D63: RODRIGUEZ M | E63: HUB SPOKE | F63: F | G63: AMOROSO | I63: 330

Sheet GIUGNO
A1: w | D1: CLINICA GioDental | E1: VILLA BETANIA | G1: CONSULENTI COMMERCIALI
J5: OBIETTIVO
I6: Tot. Foglio Mese | L6: =SUMIF(A11:A140,"INZIA IL TRATTAMENTO-VENDITA", I11:I140) -> 27051
I7: Tot. Complessivo | L7: =L6+SUMIFS('OPPORTUNITA DI VENDITA'!J198:J513,'OPPORTUNITA DI VENDITA'!C198:C513, ">=01/06/2026", 'OPPORTUNITA DI VENDITA'!C198:C513, "<=30/06/2026",'OPPORTUNITA DI VENDITA'!B198:B513,"ESEGUITO") -> 46881
A9: Esito/Stato | B9: Data | C9: Consulente | D9: Paziente | E9: Proveniente | F9: Gender | G9: Assegnazione/Medico | I9: Importo | J9: Data Valutazione | N9: Anticipo | O9: Mod.Pagamento | Q9: Data App. | R9: NOTE
A11: INZIA IL TRATTAMENTO-VENDITA | B11: 46176 | D11: BALMAS A | E11: PASSAPAROLA | F11: F | G11: MASTRORILLI | I11: 560
A12: INZIA IL TRATTAMENTO-VENDITA | B12: 46176 | D12: GARCIA ACEVEDO M | E12: INTERNET | F12: F | G12: DOMENICI | I12: 1490 | P12: 2 TRANCHES
A13: INZIA IL TRATTAMENTO-VENDITA | B13: 46177 | D13: MOSCONI T | E13: PASSAPAROLA | F13: M | G13: MARCANTONI | I13: 50 | P13: UNICO
A14: INZIA IL TRATTAMENTO-VENDITA | B14: 46177 | D14: MOSCONI C | E14: PASSAPAROLA | F14: F | G14: MARCANTONI | I14: 50 | P14: UNICO
A15: INZIA IL TRATTAMENTO-VENDITA | B15: 46182 | D15: TOCCACELI A | E15: PVT FLORIO | F15: F | G15: FLORIO | I15: 110 | P15: UNICO
A16: NESSUNA VENDITA | B16: 46182 | D16: RUGGIERI L | E16: TOTEM | F16: F | G16: FLORIO | I16: 380
A17: NESSUNA VENDITA | B17: 46182 | D17: CONTI A | E17: TOTEM | F17: M | G17: FLORIO | I17: 1150
A18: RICHIAMERA' / RICHIAMARE | B18: 46182 | D18: FANI M | E18: PVT FLORIO | F18: M | G18: FLORIO | I18: 2150
A19: INZIA IL TRATTAMENTO-VENDITA | B19: 46182 | D19: BARLETTA L | E19: TOTEM | F19: F | G19: FLORIO | I19: 1421 | P19: a PRESTAZIONE
A20: INZIA IL TRATTAMENTO-VENDITA | B20: 46182 | D20: DEL VECCHIO F | E20: PASSAPAROLA | F20: F | G20: AMOROSO | I20: 500 | P20: UNICO
A21: INZIA IL TRATTAMENTO-VENDITA | B21: 46183 | D21: MERLO E | E21: TOTEM | F21: F | G21: MASTRORILLI | I21: 80 | P21: UNICO
A22: INZIA IL TRATTAMENTO-VENDITA | B22: 46183 | D22: MERLINI M | E22: HUB SPOKE | F22: F | G22: AMOROSO | I22: 230 | P22: UNICO
A23: INZIA IL TRATTAMENTO-VENDITA | B23: 46183 | D23: PALA L | E23: INTERNET | F23: F | G23: DOMENICI | I23: 2690 | P23: 3 TRANCHES
A24: INZIA IL TRATTAMENTO-VENDITA | B24: 46183 | D24: INSOGNA M | E24: PVT AMOROSO | F24: F | G24: AMOROSO | I24: 3650 | P24: 3 TRANCHES
A25: INZIA IL TRATTAMENTO-VENDITA | B25: 46183 | D25: CALICCHIA A | E25: PVT AMOROSO | F25: M | G25: AMOROSO | I25: 5000 | P25: PAGODIL
A26: RICHIAMERA' / RICHIAMARE | B26: 46184 | D26: MARINUCCI R | E26: PASSAPAROLA | F26: F | G26: MAZZELLI | I26: 4563
A27: INZIA IL TRATTAMENTO-VENDITA | B27: 46184 | D27: ALES M | E27: DIPENDENTE | F27: M | G27: MIRACOLO | I27: 200 | P27: UNICO
A28: INZIA IL TRATTAMENTO-VENDITA | B28: 46184 | D28: TRIPI L | E28: PVT CARDONE | F28: M | G28: CARDONE | I28: 4590 | P28: 2 TRANCHES
A29: PAZIENTE SANO | B29: 46185 | D29: NAZZARO G | E29: PVT AMOROSO | F29: F | G29: AMOROSO
A30: INZIA IL TRATTAMENTO-VENDITA | B30: 46185 | D30: MARANO F | E30: HUB SPOKE | F30: F | G30: AMOROSO | I30: 630 | P30: 2 TRANCHES
A31: INZIA IL TRATTAMENTO-VENDITA | B31: 46188 | D31: TULCHHINETSKAYA D | E31: TOTEM | F31: F | G31: DOMENICI | I31: 220 | P31: 2 TRANCHES
A32: INZIA IL TRATTAMENTO-VENDITA | B32: 46189 | D32: GRASSI E | E32: HUB SPOKE | F32: F | G32: AMOROSO | I32: 1630 | P32: PAGODIL
A33: RICHIAMERA' / RICHIAMARE | B33: 46189 | D33: CATALANO M | E33: PVT FLORIO | F33: M | G33: FLORIO | I33: 1800
A34: INZIA IL TRATTAMENTO-VENDITA | B34: 46189 | D34: SPAGNOLI M | E34: PVT FLORIO | F34: M | G34: FLORIO | I34: 800 | P34: UNICO
A35: INZIA IL TRATTAMENTO-VENDITA | B35: 46190 | D35: STAFFIERO A | E35: PASSAPAROLA | F35: F | G35: DOMENICI | I35: 1570 | P35: 2 TRANCHES
A36: PAZIENTE SANO | B36: 46190 | D36: RAHMANIAN J | E36: TOTEM | F36: M | G36: AMOROSO
A37: RICHIAMERA' / RICHIAMARE | B37: 46191 | D37: OROBELLO P | E37: TOTEM | F37: F | G37: MIRACOLO | I37: 3869
A38: INZIA IL TRATTAMENTO-VENDITA | B38: 46191 | D38: LUCARELLI R | E38: TOTEM | F38: M | G38: MIRACOLO | I38: 1250 | P38: 2 TRANCHES
A39: INZIA IL TRATTAMENTO-VENDITA | B39: 46196 | D39: RICCI M | E39: HUB SPOKE | F39: F | G39: AMOROSO | I39: 330 | P39: UNICO

Sheet LUGLIO
D1: CLINICA GioDental | E1: VILLA BETANIA | G1: CONSULENTI COMMERCIALI
J5: OBIETTIVO
I6: Tot. Foglio Mese | L6: =SUMIF(A11:A140,"INZIA IL TRATTAMENTO-VENDITA", I11:I140) -> 0
I7: Tot. Complessivo | L7: =L6+SUMIFS('OPPORTUNITA DI VENDITA'!J198:J513,'OPPORTUNITA DI VENDITA'!C198:C513, ">=01/07/2026", 'OPPORTUNITA DI VENDITA'!C198:C513, "<=31/07/2026",'OPPORTUNITA DI VENDITA'!B198:B513,"ESEGUITO") -> 0
A9: Esito/Stato | B9: Data | C9: Consulente | D9: Paziente | E9: Proveniente | F9: Gender | G9: Assegnazione/Medico | I9: Importo | J9: Data Valutazione | N9: Anticipo | O9: Mod.Pagamento | Q9: Data App. | R9: NOTE

Sheet AGOSTO
D1: CLINICA GioDental | E1: VILLA BETANIA | G1: CONSULENTI COMMERCIALI
J5: OBIETTIVO
I6: Tot. Foglio Mese | L6: =SUMIF(A11:A140,"INZIA IL TRATTAMENTO-VENDITA", I11:I140) -> 0
I7: Tot. Complessivo | L7: =L6+SUMIFS('OPPORTUNITA DI VENDITA'!J198:J513,'OPPORTUNITA DI VENDITA'!C198:C513, ">=01/08/2026", 'OPPORTUNITA DI VENDITA'!C198:C513, "<=31/08/2026",'OPPORTUNITA DI VENDITA'!B198:B513,"ESEGUITO") -> 0
A9: Esito/Stato | B9: Data | C9: Consulente | D9: Paziente | E9: Proveniente | F9: Gender | G9: Assegnazione/Medico | I9: Importo | J9: Data Valutazione | N9: Anticipo | O9: Mod.Pagamento | Q9: Data App. | R9: NOTE

Sheet SETTEMBRE
D1: CLINICA GioDental | E1: VILLA BETANIA | G1: CONSULENTI COMMERCIALI
J5: OBIETTIVO
I6: Tot. Foglio Mese | L6: =SUMIF(A11:A140,"INZIA IL TRATTAMENTO-VENDITA", I11:I140) -> 0
I7: Tot. Complessivo | L7: =L6+SUMIFS('OPPORTUNITA DI VENDITA'!J198:J513,'OPPORTUNITA DI VENDITA'!C198:C513, ">=01/09/2026", 'OPPORTUNITA DI VENDITA'!C198:C513, "<=30/09/2026",'OPPORTUNITA DI VENDITA'!B198:B513,"ESEGUITO") -> 0
A9: Esito/Stato | B9: Data | C9: Consulente | D9: Paziente | E9: Proveniente | F9: Gender | G9: Assegnazione/Medico | I9: Importo | J9: Data Valutazione | N9: Anticipo | O9: Mod.Pagamento | Q9: Data App. | R9: NOTE

Sheet OTTOBRE
D1: CLINICA GioDental | E1: VILLA BETANIA | G1: CONSULENTI COMMERCIALI
J5: OBIETTIVO
I6: Tot. Foglio Mese | L6: =SUMIF(A11:A140,"INZIA IL TRATTAMENTO-VENDITA", I11:I140) -> 0
I7: Tot. Complessivo | L7: =L6+SUMIFS('OPPORTUNITA DI VENDITA'!J198:J513,'OPPORTUNITA DI VENDITA'!C198:C513, ">=01/10/2026", 'OPPORTUNITA DI VENDITA'!C198:C513, "<=31/10/2026",'OPPORTUNITA DI VENDITA'!B198:B513,"ESEGUITO") -> 0
A9: Esito/Stato | B9: Data | C9: Consulente | D9: Paziente | E9: Proveniente | F9: Gender | G9: Assegnazione/Medico | I9: Importo | J9: Data Valutazione | N9: Anticipo | O9: Mod.Pagamento | Q9: Data App. | R9: NOTE

Sheet NOVEMBRE
D1: CLINICA GioDental | E1: VILLA BETANIA | G1: CONSULENTI COMMERCIALI
J5: OBIETTIVO
I6: Tot. Foglio Mese | L6: =SUMIF(A11:A140,"INZIA IL TRATTAMENTO-VENDITA", I11:I140) -> 0
I7: Tot. Complessivo | L7: =L6+SUMIFS('OPPORTUNITA DI VENDITA'!J198:J513,'OPPORTUNITA DI VENDITA'!C198:C513, ">=01/11/2026", 'OPPORTUNITA DI VENDITA'!C198:C513, "<=30/11/2026",'OPPORTUNITA DI VENDITA'!B198:B513,"ESEGUITO") -> 0
A9: Esito/Stato | B9: Data | C9: Consulente | D9: Paziente | E9: Proveniente | F9: Gender | G9: Assegnazione/Medico | I9: Importo | J9: Data Valutazione | N9: Anticipo | O9: Mod.Pagamento | Q9: Data App. | R9: NOTE

Sheet DICEMBRE
D1: CLINICA GioDental | E1: VILLA BETANIA | G1: CONSULENTI COMMERCIALI
J5: OBIETTIVO
I6: Tot. Foglio Mese | L6: =SUMIF(A11:A140,"INZIA IL TRATTAMENTO-VENDITA", I11:I140) -> 0
I7: Tot. Complessivo | L7: =L6+SUMIFS('OPPORTUNITA DI VENDITA'!J198:J513,'OPPORTUNITA DI VENDITA'!C198:C513, ">=01/12/2026", 'OPPORTUNITA DI VENDITA'!C198:C513, "<=31/12/2026",'OPPORTUNITA DI VENDITA'!B198:B513,"ESEGUITO") -> 0
A9: Esito/Stato | B9: Data | C9: Consulente | D9: Paziente | E9: Proveniente | F9: Gender | G9: Assegnazione/Medico | I9: Importo | J9: Data Valutazione | N9: Anticipo | O9: Mod.Pagamento | Q9: Data App. | R9: NOTE

Sheet PREVISIONI INCASSO
A2: DATA VISITA | C2: PAZIENTE | D2: TOT. € | E2: MODALITA' DI PAG. | F2: CONFERMATO
A8: Aprile
F9: FALSE
F10: FALSE
F11: FALSE
F12: FALSE
F13: FALSE
F14: FALSE
F15: FALSE
F16: FALSE
F17: FALSE
F18: FALSE
F19: FALSE
F20: FALSE
... F33: FALSE
F34: =SUMIF(F5:F33, TRUE, D5:D33) -> 0 | G34: Totale Mese
A35: Maggio
C36: MAZZA S | D36: 1500 | E36: UNICO | F36: TRUE
C37: INGEGNERI V | D37: 1000 | E37: UNICO | F37: TRUE
C38: MELCHIONDA | D38: 1621 | E38: BONIFICO | F38: TRUE
C39: GALANTE D | D39: 1000 | E39: UNICO | F39: TRUE
C40: SPOSRTELLI A | D40: 700 | E40: BONIFICO | F40: TRUE
C41: TORANO A | D41: 5000 | E41: BONIFICO | F41: TRUE
C42: ANTONELLI L | D42: 2250 | E42: BONIFICO | F42: TRUE
C43: STENICO T | D43: 2000 | E43: BONIFICO | F43: TRUE
C44: LICO G | D44: 930 | E44: UNICO | F44: TRUE
C45: SANTONASTASO O | D45: 744 | E45: BONIFICO | F45: TRUE
C46: PICCA E | D46: 2000 | E46: BONIFICO | F46: TRUE
F47: FALSE
F48: FALSE
F49: FALSE
F50: FALSE
F51: FALSE
F52: FALSE
F53: FALSE
F54: FALSE
F55: FALSE
F56: =SUMIF(F36:F55, TRUE, D36:D55) -> 18745 | G56: Totale Mese
A57: Giugno
C58: INGEGNERI V | D58: 1000 | E58: UNICO | F58: FALSE
C59: GALANTE D | D59: 1000 | E59: UNICO | F59: FALSE
C60: PAGNANI L | D60: 2250 | E60: BONIFICO | F60: FALSE
C61: BIRON | D61: 600 | E61: UNICO | F61: FALSE
C62: DURANTE S | D62: 1000 | E62: UNICO | F62: FALSE
C63: SALVUCCI E | D63: 1242 | E63: BONIFICO | F63: TRUE
C64: MORETTI F | D64: 325 | E64: UNICO | F64: FALSE
C65: CANTINI T | D65: 1210 | E65: BONIFICO | F65: FALSE
C66: BOTTICELLI L | D66: 1000 | E66: BONIFICO | F66: TRUE
C67: DE BENEDICTIS | D67: 475 | E67: UNICO | F67: FALSE
C68: RESTALDI | D68: 300 | E68: UNICO | F68: TRUE
C69: TOMAROVA | D69: 760 | E69: UNICO | F69: TRUE
... C72: MELCHIONDA E | D72: 1250 | E72: BONIFICO | F72: FALSE
F73: FALSE
F74: FALSE
F75: FALSE
F76: FALSE
F77: FALSE
F78: =SUMIF(F56:F77, TRUE, D56:D77) -> 8852 | G78: Totale Mese
A79: Luglio
C80: INGEGNERI V | D80: 1640 | E80: UNICO | F80: FALSE
C81: GALANTE D | D81: 1000 | E81: UNICO | F81: FALSE
C82: BOTTICELLI L | D82: 1136 | E82: BONIFICO | F82: FALSE
C83: STENICO T | D83: 2000 | E83: BONIFICO | F83: FALSE
C84: LOMBARDI A | D84: 3000 | E84: UNICO | F84: FALSE
C85: SUBOTENKO | D85: 990 | E85: BONIFICO | F85: FALSE
C86: GENTILINI V | D86: 937 | E86: BONIFICO | F86: FALSE
F87: FALSE
F88: FALSE
F89: FALSE
F90: FALSE
F91: FALSE
F92: FALSE
F93: FALSE
F94: FALSE
F95: FALSE
F96: FALSE
F97: FALSE
F98: FALSE
... F104: FALSE
F105: =SUMIF(F76:F104, TRUE, D76:D104) -> 0 | G105: Totale Mese
A106: Agosto
C107: GALANTE D | D107: 1000 | E107: UNICO | F107: FALSE
C108: STENICO T | D108: 2000 | E108: UNICO | F108: FALSE
F109: FALSE
F110: FALSE
F111: FALSE
F112: FALSE
F113: FALSE
F114: FALSE
F115: FALSE
F116: FALSE
F117: FALSE
F118: FALSE
F119: FALSE
F120: FALSE
... F133: FALSE
F134: =SUMIF(F105:F133, TRUE, D105:D133) -> 0 | G134: Totale Mese
A135: Settembre
C136: STENICO T | D136: 2000 | E136: UNICO | F136: FALSE
C137: RINALDI S | D137: 3500 | E137: BONIFICO | F137: FALSE
...

Sheet OBIETTIVI 2026
B3: GENNAIO | C3: FEBBRAIO | D3: MARZO | E3: APRILE | F3: MAGGIO | G3: GIUGNO | H3: LUGLIO | I3: AGOSTO | J3: SETTEMBRE | K3: OTTOBRE | L3: NOVEMBRE | M3: DICEMBRE
A5: RISULATO 2025 | B5: 72157 | C5: 70823 | D5: 81253 | E5: 74804 | F5: 83883 | G5: 72619 | H5: 103799 | I5: 4804 | J5: 73493 | K5: 66947 | L5: 70967 | M5: 37000 | O5: =SUM(B5:N5) -> 812549
A6: OBIETTIVO 2026 | B6: 75000 | C6: 75000 | D6: 80000 | E6: 80000 | F6: 80000 | G6: 80000 | H6: 80000 | I6: 50000 | J6: 80000 | K6: 75000 | L6: 80000 | M6: 65000 | O6: 900000
A9: CONSUNTIVO MESE | B9: 75142 | C9: 77320 | D9: 81631 | E9: 83346 | F9: 80128 | G9: 78849
A11: % SU OBIETTIVO MESE | B11: =(B9-B6)/B6 -> 0.0018933333 | C11: =(C9-C6)/C6 -> 0.030933333 | D11: =(D9-D6)/D6 -> 0.0203875 | E11: =(E9-E6)/E6 -> 0.041825 | F11: =(F9-F6)/F6 -> 0.0016 | G11: =(G9-G6)/G6 -> -0.0143875 | H11: =(H9-H6)/H6 -> -1 | I11: =(I9-I6)/I6 -> -1 | ... M11: =(M9-M6)/M6 -> -1
A13: DIFFERENZA SU OBIETTIVO | B13: =B9-B6 -> 142 | C13: =C9-C6 -> 2320 | D13: =D9-D6 -> 1631 | E13: =E9-E6 -> 3346 | F13: =F9-F6 -> 128 | G13: =G9-G6 -> -1151 | H13: =H9-H6 -> -80000
C17: GENNAIO | D17: FEBBRAIO | E17: MARZO | F17: APRILE | G17: MAGGIO | H17: GIUGNO | I17: LUGLIO | J17: AGOSTO | K17: SETTEMBRE | L17: OTTOBRE | M17: NOVEMBRE | N17: DICEMBRE
A19: PROGRESSIVO BUDGET | C19: 75000 | D19: 150000 | E19: 230000 | F19: 310000 | G19: 390000 | H19: 470000 | I19: 550000 | J19: 600000 | K19: 680000 | L19: 755000 | M19: 835000 | N19: 900000
A20: PROGRESSIVO CONSUNTIVO | C20: 75142 | D20: =B9+C9 -> 152462 | E20: =B9+C9+D9 -> 234093 | F20: =B9+C9+D9+E9 -> 317439 | G20: =B9+C9+D9+E9+F9 -> 397567 | H20: =B9+C9+D9+E9+F9+G9 -> 476416 | I20: =B9+C9+D9+E9+F9+G9+H9 -> 476416
A21: DIFFERENZA SU PROGRESSIVO | C21: =C20-C19 -> 142 | D21: =D20-D19 -> 2462 | E21: =E20-E19 -> 4093 | F21: =F20-F19 -> 7439 | G21: =G20-G19 -> 7567 | H21: =H20-H19 -> 6416

Sheet Elenco Dip Sedi
B3: VILLA BETANIA | C3: 1 | D3: 2 | F3: Colonna 1 | G3: Colonna 2 | H3: Colonna 3 | J3: Mod. di Pag. | K3: 1 | M3: Provenienza | N3: 1
C4: MEDICI | D4: OPERATORI | K4: ELENCO | N4: ELENCO
C5: DOMENICI | D5: DIEGO | K5: a PRESTAZIONE | N5: CUP
C6: AMOROSO | D6: JACOPO | K6: ACC. + DILAZIONE | N6: CUP SOLIDALE
C7: INNOCENTE | D7: DIE-JAC | K7: DILAZIONATO | N7: DI PASSAGGIO
C8: BERARDI | D8: JAC-DIE | K8: ELYGHT | N8: FAMIGLIA
C9: BERNARDINI | K9: UNICO | N9: PASSAPAROLA
C10: MASTRORILLI | K10: PAGODIL | N10: SOCIAL
C11: CARDONE | K11: CARICO ASSIC-NE | N11: INTERNET
C12: MARCANTONI | K12: 2 TRANCHES | N12: GOOGLE
C13: MIRACOLO | K13: 3 TRANCHES | N13: VICINATO
C14: MAZZELLI | K14: BONIFICO | N14: ICOT
C15: GAGLIARDI | K15: CONTANTI | N15: DIPENDENTE
C16: FLORIO | N16: TOTEM
N17: HUB SPOKE
N18: PVT AMOROSO
N19: PVT DOMENICI
N20: PVT FLORIO
N21: PVT MAZZELLI
N22: PVT CARDONE
B38: Colonna 1 | C38: Colonna 2 | D38: Colonna 3 | F38: Colonna 1 | G38: Colonna 2 | H38: Colonna 3
B60: nb.: qui è possibile aggiungere nelle rispettive colonne, medici, operatori e modalità di pagamento, i menù a discesa nei vari fogli riconosceranno solo i dati inseriti entro le righe
